Workbook

Sheet Raw_Data
A1: ref_number | B1: disclosure_group | C1: title_en | D1: title_fr | E1: name | F1: purpose_en | G1: purpose_fr | H1: start_date | I1: end_date | J1: destination_en | K1: destination_fr | L1: destination_2_en | M1: destination_2_fr | N1: destination_other_en | O1: destination_other_fr | P1: airfare | Q1: other_transport | R1: lodging | S1: meals | T1: other_expenses | U1: total | V1: additional_comments_en | W1: additional_comments_fr | X1: owner_org | Y1: owner_org_title
A2: T-20120-P11-001 | B2: SLE | C2: Chief Executive Officer | D2: Président directeur-général | E2: Philip Rizcallah | F2: To attend meeting with Saskatchewan Provincial Government | G2: Pour assister à une réunion avec le gouvernement provincial de la Saskatchewan | H2: 43864 | I2: 43865 | J2: Regina, Saskatchewan, Canada | K2: Regina, Saskatchewan, Canada | P2: 646.17 | Q2: 117.26 | R2: 157.78 | S2: 197.25 | T2: 0 | U2: 1118.46 | X2: casdo-ocena | Y2: Accessibility Standards Canada | Normes d’accessibilité Canada
A3: T-2020-P11-0001 | B3: SLE | C3: Chair | D3: Président | E3: Bérubé, Paul-Claude | F3: Board members meeting | G3: Réunion du conseil | H3: 43870 | I3: 43874 | J3: Vancouver, British Columbia, Canada | K3: Vancouver, Colombie-Britannique | P3: 1104.27 | Q3: 189.72 | R3: 841.31 | S3: 461.84 | U3: 2597.14 | X3: casdo-ocena | Y3: Accessibility Standards Canada | Normes d’accessibilité Canada
A4: T-2020-P11-0002 | B4: SLE | C4: Vice Chair | D4: vice-présidente | E4: Reid, Mary | F4: Board members meeting | G4: Réunion du conseil | H4: 43870 | I4: 43875 | J4: Vancouver, British Columbia, Canada | K4: Vancouver, Colombie-Britannique | P4: 2511.31 | Q4: 132.48 | R4: 785.65 | S4: 591 | T4: 108.3 | U4: 4128.74 | X4: casdo-ocena | Y4: Accessibility Standards Canada | Normes d’accessibilité Canada
A5: T-2020-P11-0003 | B5: SLE | C5: Board Of Directors | D5: Membre du conseil de direction | E5: McLaughlin, Joseph | F5: Board members meeting | G5: Réunion du conseil | H5: 43870 | I5: 43873 | J5: Vancouver, British Columbia, Canada | K5: Vancouver, Colombie-Britannique | Q5: 58.32 | R5: 630.99 | S5: 264.6 | T5: 123 | U5: 1076.91 | X5: casdo-ocena | Y5: Accessibility Standards Canada | Normes d’accessibilité Canada
A6: T-2020-P11-0004 | B6: SLE | C6: Board Of Directors | D6: Membre du conseil de direction | E6: Haan, Maureen | F6: Board members meeting | G6: Réunion du conseil | H6: 43870 | I6: 43873 | J6: Vancouver, British Columbia, Canada | K6: Vancouver, Colombie-Britannique | P6: 880.99 | Q6: 192.76 | R6: 630.99 | S6: 332.45 | U6: 2037.19 | X6: casdo-ocena | Y6: Accessibility Standards Canada | Normes d’accessibilité Canada
A7: T-2020-P11-0005 | B7: SLE | C7: Board Of Directors | D7: Membre du conseil de direction | E7: Hartin, Penny | F7: Board members meeting | G7: Réunion du conseil | H7: 43870 | I7: 43873 | J7: Vancouver, British Columbia, Canada | K7: Vancouver, Colombie-Britannique | P7: 935.23 | Q7: 117.3 | R7: 630.99 | S7: 353.05 | U7: 2036.57 | X7: casdo-ocena | Y7: Accessibility Standards Canada | Normes d’accessibilité Canada
A8: T-2020-P11-0006 | B8: SLE | C8: Board Of Directors | D8: Membre du conseil de direction | E8: Earle, Kory | F8: Board members meeting | G8: Réunion du conseil | H8: 43870 | I8: 43873 | J8: Vancouver, British Columbia, Canada | K8: Vancouver, Colombie-Britannique | P8: 949.11 | R8: 630.99 | S8: 373.4 | U8: 1953.5 | X8: casdo-ocena | Y8: Accessibility Standards Canada | Normes d’accessibilité Canada
A9: T-2020-P11-0007 | B9: SLE | C9: Board Of Directors | D9: Membre du conseil de direction | E9: Ringaert, Laurie | F9: Board members meeting | G9: Réunion du conseil | H9: 43870 | I9: 43873 | J9: Vancouver, British Columbia, Canada | K9: Vancouver, Colombie-Britannique | P9: 662.91 | Q9: 128.43 | R9: 630.99 | S9: 332.45 | U9: 1754.78 | X9: casdo-ocena | Y9: Accessibility Standards Canada | Normes d’accessibilité Canada
A10: T-2020-P11-0008 | B10: SLE | C10: Board Of Directors | D10: Membre du conseil de direction | E10: Khedr, Rabia | F10: Board members meeting | G10: Réunion du conseil | H10: 43870 | I10: 43873 | J10: Vancouver, British Columbia, Canada | K10: Vancouver, Colombie-Britannique | P10: 935.23 | Q10: 118.3 | R10: 630.99 | S10: 353.05 | U10: 2037.57 | X10: casdo-ocena | Y10: Accessibility Standards Canada | Normes d’accessibilité Canada
A11: T-2020-P11-0009 | B11: SLE | C11: Chief Executive Officer | D11: Président-directeur général | E11: Rizcallah, Philip | F11: Board members meeting | G11: Réunion du conseil | H11: 43870 | I11: 43875 | J11: Vancouver, British Columbia, Canada | K11: Vancouver, Colombie-Britannique | P11: 1313.32 | Q11: 342.77 | R11: 970.75 | S11: 591 | T11: 313 | U11: 3530.84 | X11: casdo-ocena | Y11: Accessibility Standards Canada | Normes d’accessibilité Canada
A12: T-2020-P1-0001 | B12: SLE | C12: Chair | D12: Président | E12: Bérubé, Paul-Claude | F12: Meeting with Chief Executive Officer of Accessibility Stadards Canada | G12: Réunion avec le Président-directeur général de Normes d’accessibilité Canada | H12: 43880 | I12: 43880 | J12: Montreal, Quebec, Canada | K12: Montréal, Québec, Canada | Q12: 62.06 | R12: 0 | S12: 20.6 | U12: 82.66 | X12: casdo-ocena | Y12: Accessibility Standards Canada | Normes d’accessibilité Canada
A13: T-2020-P1-0002 | B13: SLE | C13: Chair | D13: Président | E13: Bérubé, Paul-Claude | F13: Meeting with Chief Executive Officer and Staff of of Accessibility Stadards Canada | G13: Réunion avec le Président-directeur général et employés de Normes d’accessibilité Canada | H13: 43885 | I13: 43885 | J13: Ottawa, Ontario, Canada | K13: Ottawa, Ontario, Canada | Q13: 276.06 | R13: 0 | S13: 91.5 | U13: 367.56 | X13: casdo-ocena | Y13: Accessibility Standards Canada | Normes d’accessibilité Canada
A14: T-2020-P1-0003 | B14: SLE | C14: Chief Executive Officer | D14: Président-directeur général | E14: Rizcallah, Philip | F14: Meetings with various Stakeholders | G14: Réunions avec divers intervenants | H14: 43851 | I14: 43855 | J14: Toronto, Ontario and Halifax, Nova Scotia, Canada | K14: Toronto, Ontario et Halifax, Nouvelle-Écosse, Canada | P14: 1190.86 | Q14: 359.36 | R14: 344.73 | S14: 394.25 | T14: 172.2 | U14: 2461.4 | X14: casdo-ocena | Y14: Accessibility Standards Canada | Normes d’accessibilité Canada
A15: T-2020-P2-0001 | B15: SLE | C15: Chief Executive Officer | D15: Président-directeur général | E15: Rizcallah, Philip | F15: To attend Canadian Accessibility Standards Development Organization business meetings | G15: Pour assister des réunions d'affaire de l'Organisation Canadienne d'élaboration de normes d'accessibilité | H15: 43900 | I15: 43900 | J15: Montréal, Quebec, Canada | K15: Montréal, Québec, Canada | P15: 0 | Q15: 339.57 | R15: 0 | S15: 71.15 | T15: 3.2 | U15: 413.92 | X15: casdo-ocena | Y15: Accessibility Standards Canada | Normes d’accessibilité Canada
A16: T-2020-P2-0002 | B16: SLE | C16: Chief Executive Officer | D16: Président-directeur général | E16: Rizcallah, Philip | F16: To attend meeting with Chair and Chief Operating Officer | G16: Pour assister à une réunion avec le Président et le Chef de l’exploitation | H16: 43880 | I16: 43880 | J16: Montréal, Quebec, Canada | K16: Montréal, Québec, Canada | P16: 0 | Q16: 267.25 | R16: 0 | S16: 20.6 | T16: 0 | U16: 287.85 | X16: casdo-ocena | Y16: Accessibility Standards Canada | Normes d’accessibilité Canada
A17: T-2020-P2-0003 | B17: SLE | C17: Chief Executive Officer | D17: Président-directeur général | E17: Rizcallah, Philip | F17: To attend meeting with Chair | G17: Pour assister à une réunion avec le Président | H17: 43867 | I17: 43868 | J17: Saint-Jean-sur-Richelieu, Quebec, Canada | K17: Saint-Jean-sur-Richelieu, Québec, Canada | P17: 0 | Q17: 315.28 | R17: 0 | S17: 91.5 | T17: 3.2 | U17: 409.98 | X17: casdo-ocena | Y17: Accessibility Standards Canada | Normes d’accessibilité Canada
A18: T-2020-P2-0004 | B18: SLE | C18: Chair | D18: Président | E18: Bérubé, Paul-Claude | F18: To attend meeting with Canadian Accessibility Standards Development Organization Chief Executive Officer and Vice-chair | G18: Pour assister à une réunion avec le Directeur général et le Vice-Président du Conseil d'administration de l'Organisation Canadienne d'élaboration de normes d'accessibilité | H18: 43858 | I18: 43858 | J18: Ottawa, Ontario, Canada | K18: Ottawa, Ontario, Canada | P18: 0 | Q18: 563.09 | R18: 0 | S18: 20.6 | T18: 0 | U18: 583.69 | X18: casdo-ocena | Y18: Accessibility Standards Canada | Normes d’accessibilité Canada
A19: T-2020-P2-0005 | B19: SLE | C19: Chair | D19: Président | E19: Bérubé, Paul-Claude | F19: Physical presence required for Canadian Accessibility Standards Development Organization board members meeting | G19: Participer à la réunion du conseil d'administration de l'Organisation canadienne d'élaboration de normes d'accessibilité | H19: 43851 | I19: 43851 | J19: Ottawa, Ontario, Canada | K19: Ottawa, Ontario, Canada | P19: 0 | Q19: 440.71 | R19: 0 | S19: 20.6 | T19: 0 | U19: 461.31 | X19: casdo-ocena | Y19: Accessibility Standards Canada | Normes d’accessibilité Canada
A20: T-2020-P2-0006 | B20: SLE | C20: Vice Chair | D20: Vice-Présidente | E20: Reid, Mary | F20: To attend meeting with Canadian Accessibility Standards Development Organization Chief Executive Officer and Chair | G20: Pour assister à une réunion avec le Directeur général du Conseil d'administration et le président de l'Organisation Canadienne d'élaboration de normes d'accessibilité | H20: 43899 | I20: 43900 | J20: Montréal, Quebec, Canada | K20: Montréal, Québec, Canada | P20: 1278.66 | Q20: 32 | R20: 50 | S20: 112.1 | T20: 0 | U20: 1472.76 | X20: casdo-ocena | Y20: Accessibility Standards Canada | Normes d’accessibilité Canada
A21: T-2020-P2-0007 | B21: SLE | C21: Vice Chair | D21: Vice-Présidente | E21: Reid, Mary | F21: To attend meeting with Canadian Accessibility Standards Development Organization Chief Executive Officer | G21: Pour assister à une réunion avec le Directeur général du Conseil d'administration de l'Organisation Canadienne d'élaboration de normes d'accessibilité | H21: 43849 | I21: 43850 | J21: Ottawa, Ontario, Canada | K21: Ottawa, Ontario, Canada | P21: 1210.74 | Q21: 70.25 | R21: 269.12 | S21: 197.25 | T21: 0 | U21: 1747.36 | X21: casdo-ocena | Y21: Accessibility Standards Canada | Normes d’accessibilité Canada
A22: T-2020-P2-0008 | B22: SLE | C22: Board Of Directors | D22: Membre du conseil d'administration | E22: Adair, William | F22: Physical presence required for Canadian Accessibility Standards Development Organization board members meeting | G22: Participer à la réunion du conseil d'administration de l'Organisation canadienne d'élaboration de normes d'accessibilité | H22: 43870 | I22: 43873 | J22: Vancouver, British Columbia, Canada | K22: Vancouver, Colombie-Britannique, Canada | P22: 894.55 | Q22: 163.15 | R22: 630.99 | S22: 353.05 | T22: 0 | U22: 2041.74 | X22: casdo-ocena | Y22: Accessibility Standards Canada | Normes d’accessibilité Canada
A23: T-2022-P5-0001 | B23: SLE | C23: Chief Executive Officer | D23: Président-directeur général | E23: Rizcallah, Philip | F23: Meeting with Government of Quebec | G23: Réunion avec le gouvernement du Québec | H23: 44518 | I23: 44519 | J23: Brossard, Quebec, Canada | K23: Brossard, Québec, Canada | P23: 0 | Q23: 324.3 | R23: 177.31 | S23: 183.55 | T23: 11.6 | U23: 696.76 | X23: casdo-ocena | Y23: Accessibility Standards Canada | Normes d’accessibilité Canada
A24: T-2022-P5-0002 | B24: SLE | C24: Chief Executive Officer | D24: Président-directeur général | E24: Rizcallah, Philip | F24: Meeting with the Office des personnes handicapées du Québec | G24: Réunion avec l'Office des personnes handicapées du Québec | H24: 44545 | I24: 44546 | J24: Québec, Quebec, Canada | K24: Québec, Québec, Canada | P24: 811.86 | Q24: 235.12 | R24: 154.7 | S24: 226.5 | T24: 0 | U24: 1428.18 | X24: casdo-ocena | Y24: Accessibility Standards Canada | Normes d’accessibilité Canada
A25: T-2022-P5-0004 | B25: SLE | C25: Chief Executive Officer | D25: Président-directeur général | E25: Rizcallah, Philip | F25: Stakeholder meetings in Atlantic Canada | G25: Réunions avec parties prenantes | H25: 44604 | I25: 44615 | J25: St. John's, NL | K25: St. John's, TN | P25: 1095.53 | Q25: 304.61 | R25: 553.43 | S25: 884.65 | T25: 253.04 | U25: 3091.26 | X25: casdo-ocena | Y25: Accessibility Standards Canada | Normes d’accessibilité Canada
A26: T-2022-P5-0005 | B26: SLE | C26: Chief Executive Officer | D26: Président-directeur général | E26: Rizcallah, Philip | F26: Meeting with Legislative Assembly of New Brunswick | G26: Réunion avec l'Assemblée législative due Nouveau-Brunswick | H26: 44620 | I26: 44621 | J26: Fredericton, NB | K26: Fredericton, NB | P26: 817.28 | Q26: 237.17 | R26: 151.17 | S26: 205.15 | T26: 0 | U26: 1410.77 | X26: casdo-ocena | Y26: Accessibility Standards Canada | Normes d’accessibilité Canada
A27: T-2023-P2-0001 | B27: SLE | C27: Chief Executive Officer | D27: Président-directeur général | E27: Rizcallah, Philip | F27: Stakeholder meetings in Toronto | G27: Réunions avec des parties prenantes à Toronto | H27: 44658 | I27: 44660 | J27: Toronto, Ontario, Canada | K27: Toronto, Ontario, Canada | P27: 721.22 | Q27: 193.16 | R27: 491.24 | S27: 292.85 | U27: 1698.47 | X27: casdo-ocena | Y27: Accessibility Standards Canada | Normes d’accessibilité Canada
A28: T-2023-P3-0001 | B28: SLE | C28: Chief Executive Officer | D28: Président-directeur général | E28: Rizcallah, Philip | F28: Stakeholder meetings in Halifax | G28: Réunions avec des parties prenantes à Halifax | H28: 44663 | I28: 44668 | J28: Halifax, Nova Scotia, Canada | K28: Halifax, Nouvelle-Ecosse, Canada | P28: 651.37 | Q28: 279.34 | R28: 594.72 | S28: 342.4 | T28: 14.27 | U28: 1882.1 | X28: casdo-ocena | Y28: Accessibility Standards Canada | Normes d’accessibilité Canada
A29: T-2023-P3-0002 | B29: SLE | C29: Chief Executive Officer | D29: Président-directeur général | E29: Rizcallah, Philip | F29: Stakeholder meetings in Edmonton | G29: Réunions avec des parties prenantes en Edmonton | H29: 44677 | I29: 44679 | J29: Edmonton, Alberta | K29: Edmonton, Alberta | P29: 1504.7 | Q29: 205.31 | R29: 334.56 | S29: 347.25 | T29: 0 | U29: 2391.82 | X29: casdo-ocena | Y29: Accessibility Standards Canada | Normes d’accessibilité Canada
A30: T-2023-P3-0003 | B30: SLE | C30: Chief Executive Officer | D30: Président-directeur général | E30: Rizcallah, Philip | F30: Stakeholder meetings in Victoria and Vancouver | G30: Réunions avec des parties prenantes à Victoria et Vancouver | H30: 44704 | I30: 44707 | J30: Victoria and Vancouver, British Columbia, Canada | K30: Victoria et Vancouver, Colombie-Britannique | P30: 1818.5 | Q30: 691.09 | R30: 900.59 | S30: 463 | T30: 0 | U30: 3873.18 | X30: casdo-ocena | Y30: Accessibility Standards Canada | Normes d’accessibilité Canada
A31: T-2023-P4-0001 | B31: SLE | C31: Chief Executive Officer | D31: Président-directeur général | E31: Rizcallah, Philip | F31: Stakeholder meetings in Moncton | G31: Réunions avec des parties prenantes à Moncton | H31: 44733 | I31: 44734 | J31: Moncton, New Brunswick, Canada | K31: Moncton, Nouveau Brunswick, Canada | P31: 986.9 | Q31: 182.9 | R31: 141.55 | S31: 231.5 | T31: 0 | U31: 1542.85 | X31: casdo-ocena | Y31: Accessibility Standards Canada | Normes d’accessibilité Canada
A32: T-2023-P4-0002 | B32: SLE | C32: Chief Executive Officer | D32: Président-directeur général | E32: Rizcallah, Philip | F32: Stakeholder meetings in Toronto | G32: Réunions avec des parties prenantes en Toronto | H32: 44735 | I32: 44736 | J32: Toronto, Ontario, Canada | K32: Toronto, Ontario, Canada | P32: 0 | Q32: 665.2 | R32: 404.27 | S32: 231.5 | T32: 23.73 | U32: 1324.7 | X32: casdo-ocena | Y32: Accessibility Standards Canada | Normes d’accessibilité Canada
A33: T-2023-P5-0001 | B33: SLE | C33: Chief Executive Officer | D33: Président-directeur général | E33: Rizcallah, Philip | F33: CACP CIPH Annual Meeting | G33: Réunion annuelle CACP CIPH | H33: 44787 | I33: 44790 | J33: Halifax, Nova Scotia, Canada | K33: Halifax, Nouvelle Ecosse, Canada | P33: 698.64 | Q33: 278.92 | R33: 443.4 | S33: 468.95 | T33: 0 | U33: 1889.91 | X33: casdo-ocena | Y33: Accessibility Standards Canada | Normes d’accessibilité Canada
A34: T-2023-P5-0002 | B34: SLE | C34: Chief Executive Officer | D34: Président-directeur général | E34: Rizcallah, Philip | F34: Standard and training review | G34: Formation des normes | H34: 44798 | I34: 44800 | J34: Peterborough, Ontario, Canada | K34: Peterborough, Ontario, Canada | P34: 0 | Q34: 336.6 | R34: 369.75 | S34: 270.95 | T34: 0 | U34: 977.3 | X34: casdo-ocena | Y34: Accessibility Standards Canada | Normes d’accessibilité Canada
A35: T-2023-P5-0003 | B35: SLE | C35: Chair | D35: Président | E35: Bérubé, Paul-Claude | F35: Meeting with CEO | G35: Réunion avec PDG | H35: 44769 | I35: 44769 | J35: Brossard, Quebec, Canada | K35: Brossard, Québec, Canada | P35: 0 | Q35: 41.25 | R35: 0 | S35: 22.15 | T35: 0 | U35: 63.4 | X35: casdo-ocena | Y35: Accessibility Standards Canada | Normes d’accessibilité Canada
A36: T-2023-P5-0004 | B36: SLE | C36: Chair | D36: Président | E36: Bérubé, Paul-Claude | F36: Meeting with Vie Autonome | G36: Réunion avec Vie Autonome | H36: 44779 | I36: 44779 | J36: Val d'Or, Quebec, Canada | K36: Val d'Or, Québec, Canada | P36: 1633.64 | Q36: 108.7 | R36: 0 | S36: 98.45 | T36: 0 | U36: 1840.79 | X36: casdo-ocena | Y36: Accessibility Standards Canada | Normes d’accessibilité Canada
A37: T-2023-P5-0005 | B37: SLE | C37: Chair | D37: Président | E37: Bérubé, Paul-Claude | F37: Meeting with CEO and co-Chair | G37: Réunion avec PDG et co-président | H37: 44752 | I37: 44754 | J37: Gatineau, Quebec, Canada | K37: Gatineau, Québec, Canada | P37: 0 | Q37: 296.04 | R37: 783.04 | S37: 259.4 | T37: 0 | U37: 1338.48 | X37: casdo-ocena | Y37: Accessibility Standards Canada | Normes d’accessibilité Canada
A38: T-2023-P5-0006 | B38: SLE | C38: Board Member | D38: Membre du conseil d'administration | E38: McLaughlin, Joseph | F38: Stakeholder meeting | G38: Réunion des parties prenantes | H38: 44706 | I38: 44706 | J38: Vancouver, British Columbia, Canada | K38: Vancouver, Colombie Britannique, Canada | P38: 0 | Q38: 49.68 | R38: 0 | S38: 0 | U38: 49.68 | X38: casdo-ocena | Y38: Accessibility Standards Canada | Normes d’accessibilité Canada
A39: T-2023-P6-0001 | B39: SLE | C39: Vice Chair | D39: Vice président | E39: Reid, Mary | F39: Meeting with CEO and Chair | G39: Réunion avec PDG et Président | H39: 44745 | I39: 44755 | J39: Gatineau, Quebec, Canada | K39: Gatineau, Québec, Canada | P39: 780.54 | Q39: 50 | R39: 371.32 | S39: 270.7 | T39: 0 | U39: 1472.56 | X39: casdo-ocena | Y39: Accessibility Standards Canada | Normes d’accessibilité Canada
A40: T-2023-P7-0001 | B40: SLE | C40: Chief Executive Officer | D40: Président-directeur général | E40: Rizcallah, Philip | F40: International conference on Universal Design | G40: Conférence internationale sur la conception universelle | H40: 44805 | I40: 44814 | J40: Venice, Italy | K40: Venise, Italie | P40: 12175.56 | Q40: 592.46 | R40: 996.34 | S40: 731.55 | T40: 0 | U40: 14495.91 | X40: casdo-ocena | Y40: Accessibility Standards Canada | Normes d’accessibilité Canada
A41: T-2023-P7-0002 | B41: SLE | C41: Chief Executive Officer | D41: Président-directeur général | E41: Rizcallah, Philip | F41: Presenter at International Code Conference | G41: Présenteur à la conférence internationale des codes | H41: 44816 | I41: 44818 | J41: Louisville, Kentucky | K41: Lousiville, Kentucky | P41: 1668.11 | Q41: 202.11 | R41: 400.4 | S41: 422.29 | T41: 0 | U41: 2692.91 | X41: casdo-ocena | Y41: Accessibility Standards Canada | Normes d’accessibilité Canada
A42: T-2023-P7-0003 | B42: SLE | C42: Chief Executive Officer | D42: Président-directeur général | E42: Rizcallah, Philip | F42: Board meeting | G42: Réunion du conseil d'administration | H42: 44822 | I42: 44825 | J42: Montreal, Quebec, Canada | K42: Montréal, Québec, Canada | P42: 0 | Q42: 671.27 | R42: 0 | S42: 418.95 | T42: 0 | U42: 1090.22 | X42: casdo-ocena | Y42: Accessibility Standards Canada | Normes d’accessibilité Canada
A43: T-2023-P7-0004 | B43: SLE | C43: Vice Chair | D43: Vice président | E43: Reid, Mary | F43: Board meeting | G43: Réunion du conseil d'administration | H43: 44822 | I43: 44825 | J43: Montreal, Quebec, Canada | K43: Montréal, Québec, Canada | P43: 670.23 | Q43: 106.34 | R43: 0 | S43: 396.8 | T43: 0 | U43: 1173.37 | X43: casdo-ocena | Y43: Accessibility Standards Canada | Normes d’accessibilité Canada
A44: T-2023-P7-0005 | B44: SLE | C44: Board Member | D44: Membre du conseil d'administration | E44: McLaughlin, Joseph | F44: Board meeting | G44: Réunion du conseil d'administration | H44: 44822 | I44: 44825 | J44: Montreal, Quebec, Canada | K44: Montréal, Québec, Canada | P44: 822.12 | Q44: 283.29 | R44: 1067.43 | S44: 418.7 | T44: 0 | U44: 2591.54 | X44: casdo-ocena | Y44: Accessibility Standards Canada | Normes d’accessibilité Canada
A45: T-2023-P8-0001 | B45: SLE | C45: Chief Executive Officer | D45: Président-directeur général | E45: Rizcallah, Philip | F45: Meeting with stakeholders | G45: Réunion avec les intervenants. | H45: 44714 | I45: 44717 | J45: Halifax, Nova Scotia, Canada | K45: Halifax, Nouvelle Ecosse, Canada | P45: 770.06 | Q45: 729.51 | R45: 466.86 | S45: 231.5 | T45: 0 | U45: 2197.93 | X45: casdo-ocena | Y45: Accessibility Standards Canada | Normes d’accessibilité Canada
A46: T-2023-P8-0002 | B46: SLE | C46: Board Member | D46: Membre du conseil d'administration | E46: Hartin, Penny | F46: Board meeting & APM. | G46: Réunion du conseil d'administration & APM. | H46: 44822 | I46: 44825 | J46: Montreal, Quebec, Canada | K46: Montréal, Québec, Canada | P46: 579.53 | Q46: 231.13 | R46: 0 | S46: 396.8 | T46: 0 | U46: 1207.46 | X46: casdo-ocena | Y46: Accessibility Standards Canada | Normes d’accessibilité Canada
A47: T-2023-P8-0003 | B47: SLE | C47: Board Member | D47: Membre du conseil d'administration | E47: Haan, Maureen | F47: Board meeting & APM. | G47: Réunion du conseil d'administration & APM. | H47: 44822 | I47: 44825 | J47: Montreal, Quebec, Canada | K47: Montréal, Québec, Canada | P47: 693.66 | Q47: 135 | R47: 0 | S47: 396.8 | T47: 0 | U47: 1225.46 | X47: casdo-ocena | Y47: Accessibility Standards Canada | Normes d’accessibilité Canada
A48: T-2023-P9-0001 | B48: SLE | C48: Chief Executive Officer | D48: Président-directeur général | E48: Rizcallah, Philip | F48: Intelligent Cities Summit. | G48: Sommet ''Intelligent Cities''. | H48: 44873 | I48: 44875 | J48: Toronto, Ontario, Canada | K48: Toronto, Ontario, Canada | P48: 591.5 | Q48: 246.49 | R48: 0 | S48: 250 | T48: 0 | U48: 1087.99 | X48: casdo-ocena | Y48: Accessibility Standards Canada | Normes d’accessibilité Canada
A49: T-2023-P9-0002 | B49: SLE | C49: Chief Executive Officer | D49: Président-directeur général | E49: Rizcallah, Philip | F49: NSBOA conference. | G49: Conférence NSBOA. | H49: 44879 | I49: 44881 | J49: Halifax, Nova Scotia, Canada | K49: Halifax, Nouvelle Écosse, Canada | P49: 331.07 | Q49: 180.2 | R49: 50 | S49: 119.75 | T49: 0 | U49: 681.02 | X49: casdo-ocena | Y49: Accessibility Standards Canada | Normes d’accessibilité Canada
A50: T-2023-P9-0003 | B50: SLE | C50: Chief Executive Officer | D50: Président-directeur général | E50: Rizcallah, Philip | F50: BCANDS conference. | G50: Évènement BCANDS. | H50: 44881 | I50: 44884 | J50: Victoria, Bristish Columbia, Canada | K50: Victoria, Colombie Britanique, Canada | P50: 1345.32 | Q50: 239.97 | R50: 419.42 | S50: 233.75 | T50: 0 | U50: 2238.46 | X50: casdo-ocena | Y50: Accessibility Standards Canada | Normes d’accessibilité Canada
... A91: T-2024-P5-0002 | B91: SLE | C91: Chief Executive Officer | D91: Président-directeur général | E91: Rizcallah, Philip | F91: Stakeholder meeting | G91: Réunions | H91: 45143 | I91: 45147 | J91: Halifax, Nova Scotia, Canada | K91: Halifax, Nouvelle-Ecosse, Canada | P91: 828.14 | Q91: 512.51 | R91: 731.41 | S91: 485 | T91: 0 | U91: 2557.06 | X91: casdo-ocena | Y91: Accessibility Standards Canada | Normes d’accessibilité Canada
A92: T-2024-P6-0001 | B92: SLE | C92: Chief Executive Officer | D92: Président-directeur général | E92: Rizcallah, Philip | F92: Board meeting | G92: Réunion du conseil d'administration | H92: 45178 | I92: 45184 | J92: St. John's, Newfoundland | K92: St. John's, Terre-Neuve | P92: 815.63 | Q92: 88.23 | R92: 2063.46 | S92: 578.9 | U92: 3546.22 | X92: casdo-ocena | Y92: Accessibility Standards Canada | Normes d’accessibilité Canada
A93: T-2024-P6-0002 | B93: SLE | C93: Chief Executive Officer | D93: Président-directeur général | E93: Rizcallah, Philip | F93: Operational activities | G93: Activités opérationels | H93: 45173 | I93: 45178 | J93: NY, NY, USA | K93: NY, NY, EU | P93: 989.77 | Q93: 476.06 | R93: 1536.69 | S93: 940.57 | T93: 0 | U93: 3943.09 | X93: casdo-ocena | Y93: Accessibility Standards Canada | Normes d’accessibilité Canada
A94: T-2024-P6-0003 | B94: SLE | C94: Chief Executive Officer | D94: Président-directeur général | E94: Rizcallah, Philip | F94: Operational activities | G94: Activités opérationels | H94: 45151 | I94: 45156 | J94: Calgary, Alberta, Canada | K94: Calgary, Alberta, Canada | P94: 1301.27 | Q94: 371.86 | R94: 1859.32 | S94: 640.9 | T94: 0 | U94: 4173.35 | X94: casdo-ocena | Y94: Accessibility Standards Canada | Normes d’accessibilité Canada
A95: T-2024-P7-0001 | B95: SLE | C95: Chief Executive Officer | D95: Président-directeur général | E95: Rizcallah, Philip | F95: Toronto conference | G95: Conférence Toronto | H95: 45196 | I95: 45199 | J95: Toronto, Ontario, Canada | K95: Toronto, Ontario, Canada | P95: 0 | Q95: 365.14 | R95: 952.26 | S95: 470 | T95: 0 | U95: 1787.4 | X95: casdo-ocena | Y95: Accessibility Standards Canada | Normes d’accessibilité Canada
A96: T-2024-P7-0002 | B96: SLE | C96: Chief Executive Officer | D96: Président-directeur général | E96: Rizcallah, Philip | F96: Australian International Sports Organization Meeting | G96: Reunions des sports internationales | H96: 45184 | I96: 45192 | J96: Brisbane, Australia | K96: Brisbane, Australie | P96: 11020.28 | Q96: 252.63 | R96: 1266.76 | S96: 1760.64 | T96: 17.47 | U96: 14317.78 | X96: casdo-ocena | Y96: Accessibility Standards Canada | Normes d’accessibilité Canada
A97: T-2024-P7-0003 | B97: SLE | C97: Chief Executive Officer | D97: Président-directeur général | E97: Rizcallah, Philip | F97: Red Deer Safety Code Conference | G97: Conférence pour code de sécurité Red Deer | H97: 45217 | I97: 45220 | J97: Edmonton, Alberta, Canada | K97: Edmonton, Alberta, Canada | P97: 840.18 | Q97: 187.1 | R97: 545.61 | S97: 372.9 | T97: 0 | U97: 1945.79 | X97: casdo-ocena | Y97: Accessibility Standards Canada | Normes d’accessibilité Canada
A98: T-2024-P7-0004 | B98: SLE | C98: Chief Executive Officer | D98: Président-directeur général | E98: Rizcallah, Philip | F98: Washington Enabling Summit | G98: Conférence pour code de sécurité Red Deer | H98: 45207 | I98: 45212 | J98: Washington DC, United States | K98: Washington DC, Etats Unis | P98: 923.11 | Q98: 106.17 | R98: 2026.24 | S98: 891.24 | T98: 0 | U98: 3946.76 | X98: casdo-ocena | Y98: Accessibility Standards Canada | Normes d’accessibilité Canada
A99: T-2024-P7-0005 | B99: SLE | C99: Vice Chair | D99: Vice-Présidente | E99: Reid, Mary | F99: Funeral Estey | G99: Funeral Estey | H99: 45187 | I99: 45188 | J99: Halifax, Nova Scotia, Canada | K99: Halifax, Nouvelle Ecosse, Canada | P99: 1006.13 | Q99: 287.42 | R99: 201.76 | S99: 199.3 | T99: 0 | U99: 1694.61 | X99: casdo-ocena | Y99: Accessibility Standards Canada | Normes d’accessibilité Canada
A100: T-2024-P7-0006 | B100: SLE | C100: Vice Chair | D100: Vice-Présidente | E100: Reid, Mary | F100: Board meeting | G100: Réunion du conseil d’administration à St-John | H100: 45209 | I100: 45213 | J100: St. John's, Newfoundland | K100: St. John's, Terre-Neuve | P100: 0 | Q100: 63.66 | R100: 1375.64 | S100: 363.3 | T100: 0 | U100: 1802.6 | X100: casdo-ocena | Y100: Accessibility Standards Canada | Normes d’accessibilité Canada
A101: T-2024-P7-0007 | B101: SLE | C101: Board Member | D101: Membre du conseil d'administration | E101: Kory, Earle | F101: Board meeting | G101: Réunion du conseil d’administration à St-John | H101: 45209 | I101: 45214 | J101: St. John's, Newfoundland | K101: St. John's, Terre-Neuve | P101: 1246.38 | Q101: 103.22 | R101: 1719.55 | S101: 504 | T101: 0 | U101: 3573.15 | X101: casdo-ocena | Y101: Accessibility Standards Canada | Normes d’accessibilité Canada
A102: T-2024-P7-0008 | B102: SLE | C102: Board Member | D102: Membre du conseil d'administration | E102: Ringaert, Laurie | F102: Board meeting | G102: Réunion du conseil d’administration à St-John | H102: 45176 | I102: 45184 | J102: St. John's, Newfoundland | K102: St. John's, Terre-Neuve | P102: 1125.78 | Q102: 91.39 | R102: 1719.55 | S102: 486.7 | T102: 0 | U102: 3423.42 | X102: casdo-ocena | Y102: Accessibility Standards Canada | Normes d’accessibilité Canada
A103: T-2024-P8-0001 | B103: SLE | C103: Chief Executive Officer | D103: Président-directeur général | E103: Rizcallah, Philip | F103: Christchurch Conference | G103: Conférence Christchurch | H103: 45226 | I103: 45233 | J103: Christchurch, New Zealand | K103: Christchurch, Nouvelle Zelande | P103: 7657.55 | Q103: 312.99 | R103: 1308.11 | S103: 1114.93 | T103: 16.23 | U103: 10409.81 | X103: casdo-ocena | Y103: Accessibility Standards Canada | Normes d’accessibilité Canada
A104: T-2024-P8-0002 | B104: SLE | C104: Chief Executive Officer | D104: Président-directeur général | E104: Rizcallah, Philip | F104: Intelligentcities Conference | G104: Conférence Intelligentcities | H104: 45222 | I104: 45225 | J104: Toronto, Ontario, Canada | K104: Toronto, Ontario, Canada | P104: 820.66 | Q104: 245.73 | R104: 801.49 | S104: 408.7 | T104: 0 | U104: 2276.58 | X104: casdo-ocena | Y104: Accessibility Standards Canada | Normes d’accessibilité Canada
... A157: T-2025-P11-0002 | B157: SLE | C157: Board Member | D157: Membre du conseil d'administration | E157: Sutton, Christopher | F157: Harkin Institute Conference | G157: Conférence de l'institut Harkin | H157: 45643 | I157: 45650 | J157: Washington DC, USA | K157: Washington DC, USA | P157: 0 | Q157: 290.96 | R157: 0 | S157: 767.5 | T157: 12.43 | U157: 1070.89 | X157: casdo-ocena | Y157: Accessibility Standards Canada | Normes d’accessibilité Canada
A158: T-2025-P12-0001 | B158: SLE | C158: Chief Executive Officer | D158: Président directeur-général | E158: Zuppa, Dino | F158: Training | G158: Formation | H158: 45699 | I158: 45702 | J158: Toronto, Ontario | K158: Toronto, Ontario | P158: 752.32 | Q158: 74 | R158: 786.96 | S158: 431.6 | U158: 2044.88 | X158: casdo-ocena | Y158: Accessibility Standards Canada | Normes d’accessibilité Canada
A159: T-2026-P1-0001 | B159: SLE | C159: Chief Executive Officer | D159: Président directeur-général | E159: Zuppa, Dino | F159: International Accessibility Conference | G159: Conférence internationale sur l'accessibilité | H159: 45786 | I159: 45795 | J159: Nice, France | K159: Nice, France | L159: Brussels, Belgium | M159: Bruxelles, Belgique | P159: 2907.37 | Q159: 173.18 | R159: 1926.16 | S159: 2321.95 | T159: 242.22 | U159: 7570.88 | X159: casdo-ocena | Y159: Accessibility Standards Canada | Normes d’accessibilité Canada
A160: T-2026-P7-0001 | B160: SLE | C160: Chief Executive Officer | D160: Président-directeur général | E160: Zuppa, Dino | F160: Meetings with concerned parties | G160: Réunions avec parties prenantes | H160: 45915 | I160: 45918 | J160: Toronto, Ontario | K160: Toronto, Ontario | P160: 415.03 | Q160: 57.83 | R160: 1173.33 | S160: 523.2 | T160: 0 | U160: 2169.39 | X160: casdo-ocena | Y160: Accessibility Standards Canada | Normes d’accessibilité Canada
A161: T-2026-P7-0002 | B161: SLE | C161: Chief Executive Officer | D161: Président-directeur général | E161: Zuppa, Dino | F161: Meetings with concerned parties | G161: Réunions avec parties prenantes | H161: 45923 | I161: 45924 | J161: Toronto, Ontario | K161: Toronto, Ontario | P161: 336.28 | Q161: 105.2 | R161: 633.54 | S161: 205.8 | T161: 0 | U161: 1280.82 | X161: casdo-ocena | Y161: Accessibility Standards Canada | Normes d’accessibilité Canada
A162: T-2026-P7-0003 | B162: SLE | C162: Chief Executive Officer | D162: Président-directeur général | E162: Zuppa, Dino | F162: Meetings with concerned parties | G162: Réunions avec parties prenantes | H162: 45926 | I162: 45927 | J162: Montreal, Quebec, Canada | K162: Montréal, Québec, Canada | P162: 0 | Q162: 281.27 | R162: 260.51 | S162: 233.2 | T162: 28.2 | U162: 803.18 | X162: casdo-ocena | Y162: Accessibility Standards Canada | Normes d’accessibilité Canada
A163: T-2026-P7-0004 | B163: SLE | C163: Chief Executive Officer | D163: Président-directeur général | E163: Zuppa, Dino | F163: Meetings with concerned parties | G163: Réunions avec parties prenantes | H163: 45940 | I163: 45948 | J163: Halifax, Nova Scotia | K163: Halifax, Nouvelle-Ecosse | P163: 676.19 | Q163: 572.66 | R163: 1682.3 | S163: 759.45 | T163: 0 | U163: 3690.6 | X163: casdo-ocena | Y163: Accessibility Standards Canada | Normes d’accessibilité Canada
A164: T-2026-P8-0001 | B164: SLE | C164: Board member | D164: Membre du conseil d'administration | E164: Seysan, Yazdani | F164: 9th anniversary of Canada VRS | G164: Célébration du 9e anniversaire de SRV Canada. | H164: 45927 | I164: 45927 | J164: Montreal, Quebec, Canada | K164: Montréal, Québec, Canada | P164: 0 | Q164: 28 | R164: 0 | S164: 0 | T164: 0 | U164: 28 | X164: casdo-ocena | Y164: Accessibility Standards Canada | Normes d’accessibilité Canada
A165: T-2026-P8-0002 | B165: SLE | C165: Board Member | D165: Membre du conseil d'administration | E165: Seysan, Yazdani | F165: COPHAN Event | G165: COPHAN évènement | H165: 45933 | I165: 45935 | J165: Quebec City, Quebec, Canada | K165: Québec, Québec, Canada | P165: 408.83 | Q165: 156.9 | R165: 307.04 | S165: 142.25 | T165: 0 | U165: 1015.02 | X165: casdo-ocena | Y165: Accessibility Standards Canada | Normes d’accessibilité Canada
A166: T-2026-P9-0001 | B166: SLE | C166: Board Member | D166: Membre du conseil d'administration | E166: McLaughlin, Joe | F166: Board meeting | G166: Réunion du conseil d'administration | H166: 45984 | I166: 45990 | J166: Ottawa, Ontario | K166: Ottawa, Ontario | P166: 478.83 | Q166: 263.12 | R166: 2242.5 | S166: 838.5 | T166: 0 | U166: 3822.95 | X166: casdo-ocena | Y166: Accessibility Standards Canada | Normes d’accessibilité Canada
A167: T-2026-P9-0002 | B167: SLE | C167: Board Member | D167: Membre du conseil d'administration | E167: Haan, Maureen | F167: Board meeting | G167: Réunion du conseil d'administration | H167: 45984 | I167: 45989 | J167: Ottawa, Ontario | K167: Ottawa, Ontario | P167: 604.96 | Q167: 251.62 | R167: 2242.5 | S167: 672.75 | T167: 0 | U167: 3771.83 | X167: casdo-ocena | Y167: Accessibility Standards Canada | Normes d’accessibilité Canada
A168: T-2026-P9-0003 | B168: SLE | C168: Board Member | D168: Membre du conseil d'administration | E168: Adair, Bill | F168: Board meeting | G168: Réunion du conseil d'administration | H168: 45984 | I168: 45990 | J168: Ottawa, Ontario | K168: Ottawa, Ontario | P168: 225.2 | Q168: 158.31 | R168: 2242.5 | S168: 809.45 | T168: 0 | U168: 3435.46 | X168: casdo-ocena | Y168: Accessibility Standards Canada | Normes d’accessibilité Canada
A169: T-2026-P9-0004 | B169: SLE | C169: Chairperson | D169: Président | E169: Walsh, J. Paul | F169: Board meeting | G169: Réunion du conseil d'administration | H169: 45984 | I169: 45997 | J169: Ottawa, Ontario | K169: Ottawa, Ontario | P169: 742.46 | Q169: 151.88 | R169: 4862.31 | S169: 1496.4 | T169: 402.5 | U169: 7655.55 | X169: casdo-ocena | Y169: Accessibility Standards Canada | Normes d’accessibilité Canada
A170: T-2026-P10-0001 | B170: SLE | C170: Chief Executive Officer | D170: Président-directeur général | E170: Zuppa, Dino | F170: Meetings with concerned parties | G170: Réunions avec parties prenantes | H170: 46034 | I170: 46037 | J170: Fredericton, New Brunswick | K170: Fredericton, Nouveau-Brunswick | P170: 630 | Q170: 170.3 | R170: 549.9 | S170: 488.15 | T170: 0 | U170: 1838.35 | X170: casdo-ocena | Y170: Accessibility Standards Canada | Normes d’accessibilité Canada
A171: T-2026-P10-0002 | B171: SLE | C171: Board Member | D171: Membre du conseil d'administration | E171: Yazdani-Seysan, Mojgan | F171: Board meeting | G171: Réunion du conseil d'administration | H171: 45985 | I171: 45989 | J171: Ottawa, Ontario | K171: Ottawa, Ontario | P171: 226.54 | Q171: 71.32 | R171: 2242.5 | S171: 689.5 | T171: 0 | U171: 3229.86 | X171: casdo-ocena | Y171: Accessibility Standards Canada | Normes d’accessibilité Canada
... A178: T-2027-P3-0001 | B178: SLE | C178: Chief Executive Officer | D178: Président-directeur général | E178: Zuppa, Dino | F178: Conference in Vancouver | G178: Conférence Vancouver | H178: 46168 | I178: 46170 | J178: Vancouver, BC, Canada | K178: Vancouve, CB, Canada | P178: 869.88 | Q178: 176.6 | R178: 1414.36 | S178: 731.25 | T178: 0 | U178: 3192.09 | X178: casdo-ocena | Y178: Accessibility Standards Canada | Normes d’accessibilité Canada
A179: T-2017-Q1-00001 | B179: SLE | C179: A/Executive Director and General Counsel, Secretariat to the Public Service Labour Relations and Employment Board | D179: Directrice générale et avocate générale par intérim, Secrétariat de la Commission des relations de travail et de l’emploi dans la fonction publique | E179: Virginia Adamson | F179: Visit Canadian Industrial relation Board's regional offices | G179: Visiter des bureaux régionaux du Conseil canadien des relations industrielles | H179: 42796 | I179: 42797 | J179: Vancouver, BC | K179: Vancouver, BC | P179: 315.13 | Q179: 117 | R179: 126.6 | S179: 97 | U179: 655.73 | X179: atssc-scdata | Y179: Administrative Tribunals Support Service of Canada | Service canadien d'appui aux tribunaux administratifs
A180: T-2017-Q1-00002 | B180: SLE | C180: A/Executive Director and General Counsel, Secretariat to the Public Service Labour Relations and Employment Board | D180: Directrice générale et avocate générale par intérim, Secrétariat de la Commission des relations de travail et de l’emploi dans la fonction publique | E180: Virginia Adamson | F180: To attend a meeting of the Association of Labour Relations Agencies | G180: Participer à une rencontre de la Association of Labour Relations Agencies | H180: 42797 | I180: 42800 | J180: Portland, Oregon | K180: Portland, Oregon | P180: 960.79 | Q180: 165.3 | R180: 553.91 | S180: 379.17 | U180: 2059.17 | X180: atssc-scdata | Y180: Administrative Tribunals Support Service of Canada | Service canadien d'appui aux tribunaux administratifs
A181: T-2017-Q1-00003 | B181: SLE | C181: A/Chairperson, Canadian International Trade Tribunal | D181: Président par intérim, Tribunal Canadien du commerce extérieur | E181: Bédard, Jean | F181: Attend the 38th Annual International Trade Update | G181: Participer à la 38e International Trade Update annuelle | H181: 42802 | I181: 42804 | J181: Washington, DC | K181: Washington, DC | P181: 609.66 | Q181: 73.61 | R181: 1071.85 | S181: 346.61 | U181: 2101.73 | X181: atssc-scdata | Y181: Administrative Tribunals Support Service of Canada | Service canadien d'appui aux tribunaux administratifs
A182: T-2017-Q1-00004 | B182: SLE | C182: A/Chairperson, Canadian International Trade Tribunal | D182: Président par intérim, Tribunal Canadien du commerce extérieur | E182: Bédard, Jean | F182: Attend the Chairperson's forum in Ottawa | G182: Assister au forum de la présidente à Ottawa | H182: 42818 | I182: 42818 | J182: Ottawa, ON | K182: Ottawa, ON | T182: 14 | U182: 14 | X182: atssc-scdata | Y182: Administrative Tribunals Support Service of Canada | Service canadien d'appui aux tribunaux administratifs
A183: T-2017-Q1-00005 | B183: SLE | C183: Executive Director, Secretariat to the Canadian Cultural Property Export Review Board | D183: Directrice exécutive, Secrétariat de la Commission canadienne d’examen des exportations de biens culturels | E183: Bishop, Delphine | F183: Attend a meeting with Executive Directors | G183: Participer à une rencontre avec les directeurs exécutifs | H183: 42740 | I183: 42740 | J183: Ottawa, ON | K183: Ottawa, ON | T183: 17.5 | U183: 17.5 | X183: atssc-scdata | Y183: Administrative Tribunals Support Service of Canada | Service canadien d'appui aux tribunaux administratifs
A184: T-2017-Q1-00006 | B184: SLE | C184: Executive Director, Secretariat to the Canadian Cultural Property Export Review Board | D184: Directrice exécutive, Secrétariat de la Commission canadienne d’examen des exportations de biens culturels | E184: Bishop, Delphine | F184: Attend a meeting with Executive Directors | G184: Participer à une rencontre avec les directeurs exécutifs | H184: 42746 | I184: 42746 | J184: Ottawa, ON | K184: Ottawa, ON | T184: 20 | U184: 20 | X184: atssc-scdata | Y184: Administrative Tribunals Support Service of Canada | Service canadien d'appui aux tribunaux administratifs
A185: T-2017-Q1-00007 | B185: SLE | C185: Executive Director, Secretariat to the Canadian Cultural Property Export Review Board | D185: Directrice exécutive, Secrétariat de la Commission canadienne d’examen des exportations de biens culturels | E185: Bishop, Delphine | F185: Attend a meeting with Executive Directors | G185: Participer à une rencontre avec les directeurs exécutifs | H185: 42783 | I185: 42783 | J185: Ottawa, ON | K185: Ottawa, ON | T185: 15 | U185: 15 | X185: atssc-scdata | Y185: Administrative Tribunals Support Service of Canada | Service canadien d'appui aux tribunaux administratifs
A186: T-2017-Q1-00008 | B186: SLE | C186: Executive Director, Secretariat to the Canadian Cultural Property Export Review Board | D186: Directrice exécutive, Secrétariat de la Commission canadienne d’examen des exportations de biens culturels | E186: Bishop, Delphine | F186: Attend a meeting with the Senior Project manager | G186: Participer à une rencontre avec la chef de l'initiative stratégique | H186: 42800 | I186: 42800 | J186: Ottawa, ON | K186: Ottawa, ON | T186: 11 | U186: 11 | X186: atssc-scdata | Y186: Administrative Tribunals Support Service of Canada | Service canadien d'appui aux tribunaux administratifs
A187: T-2017-Q1-00009 | B187: SLE | C187: Executive Director, Secretariat to the Canadian Cultural Property Export Review Board | D187: Directrice exécutive, Secrétariat de la Commission canadienne d’examen des exportations de biens culturels | E187: Bishop, Delphine | F187: Attend a Budget Allocation meeting | G187: Participer à une rencontre sur l'allocation budgétaire | H187: 42807 | I187: 42807 | J187: Ottawa, ON | K187: Ottawa, ON | T187: 12.5 | U187: 12.5 | X187: atssc-scdata | Y187: Administrative Tribunals Support Service of Canada | Service canadien d'appui aux tribunaux administratifs
A188: T-2017-Q1-00010 | B188: SLE | C188: Executive Director, Secretariat to the Canadian Cultural Property Export Review Board | D188: Directrice exécutive, Secrétariat de la Commission canadienne d’examen des exportations de biens culturels | E188: Bishop, Delphine | F188: Attend the CCPERB Board meeting | G188: Assister à la réunion des membres de la Commission CCEEBC | H188: 42808 | I188: 42811 | J188: Ottawa, ON | K188: Ottawa, ON | T188: 80 | U188: 80 | X188: atssc-scdata | Y188: Administrative Tribunals Support Service of Canada | Service canadien d'appui aux tribunaux administratifs
A189: T-2017-Q1-00011 | B189: SLE | C189: Executive Director, Secretariat to the Canadian Cultural Property Export Review Board | D189: Directrice exécutive, Secrétariat de la Commission canadienne d’examen des exportations de biens culturels | E189: Bishop, Delphine | F189: Attend the Classification Committee meeting | G189: Participer à une rencontre du comité de la classification | H189: 42816 | I189: 42816 | J189: Ottawa, ON | K189: Ottawa, ON | T189: 20 | U189: 20 | X189: atssc-scdata | Y189: Administrative Tribunals Support Service of Canada | Service canadien d'appui aux tribunaux administratifs
A190: T-2017-Q1-00012 | B190: SLE | C190: Executive Director, Secretariat to the Canadian Cultural Property Export Review Board | D190: Directrice exécutive, Secrétariat de la Commission canadienne d’examen des exportations de biens culturels | E190: Bishop, Delphine | F190: Attend a meeting with Executive Directors | G190: Participer à une rencontre avec les directeurs exécutifs | H190: 42823 | I190: 42823 | J190: Ottawa, ON | K190: Ottawa, ON | T190: 20 | U190: 20 | X190: atssc-scdata | Y190: Administrative Tribunals Support Service of Canada | Service canadien d'appui aux tribunaux administratifs
A191: T-2017-Q1-00013 | B191: SLE | C191: Chairperson, Canada Industrial Relations Board | D191: Présidente, Conseil canadien des relations industrielles | E191: Ginette Brazeau | F191: Attend a Regional Directors Meeting | G191: Participer à une rencontre des directeurs régionaux | H191: 42794 | I191: 42796 | J191: Vancouver, BC | K191: Vancouver, BC | P191: 340.88 | Q191: 40 | R191: 340.76 | S191: 257.8 | U191: 979.44 | X191: atssc-scdata | Y191: Administrative Tribunals Support Service of Canada | Service canadien d'appui aux tribunaux administratifs
A192: T-2017-Q1-00014 | B192: SLE | C192: Chairperson, Canada Industrial Relations Board | D192: Présidente, Conseil canadien des relations industrielles | E192: Ginette Brazeau | F192: To attend the Association of Labour Relations Agencies meeting | G192: Participer à une rencontre de la Association of Labour Relations Agencies | H192: 42797 | I192: 42799 | J192: Portland, Oregon | K192: Portland, Oregon | P192: 566.46 | Q192: 38.05 | R192: 852.08 | S192: 260.32 | T192: 120 | U192: 1836.91 | X192: atssc-scdata | Y192: Administrative Tribunals Support Service of Canada | Service canadien d'appui aux tribunaux administratifs
A193: T-2017-Q1-00015 | B193: SLE | C193: Chairperson, Canada Industrial Relations Board | D193: Présidente, Conseil canadien des relations industrielles | E193: Ginette Brazeau | F193: Hearing file # 31022-C | G193: Dossier d'audience no 31022-C | H193: 42801 | I193: 42804 | J193: Toronto, ON | K193: Toronto, ON | P193: 380.87 | Q193: 25 | R193: 611.36 | S193: 291.35 | T193: 131.16 | U193: 1439.74 | X193: atssc-scdata | Y193: Administrative Tribunals Support Service of Canada | Service canadien d'appui aux tribunaux administratifs
A194: T-2017-Q1-00016 | B194: SLE | C194: Chairperson, Canada Industrial Relations Board | D194: Présidente, Conseil canadien des relations industrielles | E194: Ginette Brazeau | F194: Hearing file # 31364-C | G194: Dossier d'audience no 31364-C | H194: 42822 | I194: 42825 | J194: Halifax, NS | K194: Halifax, NS | P194: 680.48 | Q194: 135 | R194: 612.3 | S194: 308.6 | T194: 92 | U194: 1828.38 | X194: atssc-scdata | Y194: Administrative Tribunals Support Service of Canada | Service canadien d'appui aux tribunaux administratifs
A195: T-2017-Q1-00017 | B195: SLE | C195: Chairperson, Canada Industrial Relations Board | D195: Présidente, Conseil canadien des relations industrielles | E195: Ginette Brazeau | F195: Hearing file # 31685 & 31696-C | G195: Dossiers d'audience nos 31685 et 31696-C | H195: 42828 | I195: 42832 | J195: Vancouver, BC | K195: Vancouver, BC | P195: 413.98 | Q195: 73.2 | R195: 700.32 | S195: 248.65 | T195: 102 | U195: 1538.15 | X195: atssc-scdata | Y195: Administrative Tribunals Support Service of Canada | Service canadien d'appui aux tribunaux administratifs
A196: T-2017-Q1-00018 | B196: SLE | C196: Chairperson, Canada Industrial Relations Board | D196: Présidente, Conseil canadien des relations industrielles | E196: Ginette Brazeau | F196: Attend a presentation | G196: Participer à une présentation | H196: 42846 | I196: 42846 | J196: Ottawa, ON | K196: Ottawa, ON | T196: 22 | U196: 22 | X196: atssc-scdata | Y196: Administrative Tribunals Support Service of Canada | Service canadien d'appui aux tribunaux administratifs
A197: T-2017-Q1-00019 | B197: SLE | C197: Chairperson, Canada Industrial Relations Board | D197: Présidente, Conseil canadien des relations industrielles | E197: Ginette Brazeau | F197: Hearing file # 31670-C & 31671-C | G197: Dossiers d'audience nos 31670-C et 31671-C | H197: 42856 | I197: 42859 | J197: Vancouver, BC | K197: Vancouver, BC | P197: 4074.14 | Q197: 74.5 | R197: 441.8 | S197: 150.95 | T197: 69 | U197: 4810.39 | X197: atssc-scdata | Y197: Administrative Tribunals Support Service of Canada | Service canadien d'appui aux tribunaux administratifs
A198: T-2017-Q1-00020 | B198: SLE | C198: Chairperson, Social Security Tribunal | D198: Présidente du Tribunal de la sécurité sociale | E198: Murielle, Brazeau | F198: To attend training | G198: Participer à une formation | H198: 42844 | I198: 42849 | J198: Vancouver, BC | K198: Vancouver, BC | P198: 1604.41 | Q198: 106.34 | R198: 479.39 | S198: 284 | T198: 138 | U198: 2612.14 | X198: atssc-scdata | Y198: Administrative Tribunals Support Service of Canada | Service canadien d'appui aux tribunaux administratifs
...

Sheet Cleaned_Data
A1: ref_number | B1: disclosure_group | C1: title_en | D1: title_fr | E1: name | F1: purpose_en | G1: purpose_fr | H1: start_date | I1: end_date | J1: destination_en | K1: destination_fr | L1: destination_2_en | M1: destination_2_fr | N1: destination_other_en | O1: destination_other_fr | P1: airfare | Q1: other_transport | R1: lodging | S1: meals | T1: other_expenses | U1: total | V1: additional_comments_en | W1: additional_comments_fr | X1: owner_org | Y1: owner_org_title | Z1: Travel_Days | AA1: Calculated_Total | AB1: Total_Difference | AC1: Duplicate_Flag | AD1: Data_Quality_Status | AE1: Total_Check
A2: T-20120-P11-001 | B2: SLE | C2: Chief Executive Officer | D2: Président directeur-général | E2: Philip Rizcallah | F2: To attend meeting with Saskatchewan Provincial Government | G2: Pour assister à une réunion avec le gouvernement provincial de la Saskatchewan | H2: 43864 | I2: 43865 | J2: Regina, Saskatchewan, Canada | K2: Regina, Saskatchewan, Canada | P2: 646.17 | Q2: 117.26 | R2: 157.78 | S2: 197.25 | T2: 0 | U2: 1118.46 | X2: casdo-ocena | Y2: Accessibility Standards Canada | Normes d’accessibilité Canada | Z2: 2 | AA2: 1118.46 | AB2: =ROUND(U2-AA2,2) | AC2: FALSE | AD2: =IF(U2="","MISSING_TOTAL",IF(ABS(AB2)<=0.01,"OK","CHECK")) | AE2: =IF(U2="","MISSING",IF(AND(AA2>0,U2/AA2>50),"POSSIBLE_SCALE_ERROR","OK"))
A3: T-2020-P11-0001 | B3: SLE | C3: Chair | D3: Président | E3: Bérubé, Paul-Claude | F3: Board members meeting | G3: Réunion du conseil | H3: 43870 | I3: 43874 | J3: Vancouver, British Columbia, Canada | K3: Vancouver, Colombie-Britannique | P3: 1104.27 | Q3: 189.72 | R3: 841.31 | S3: 461.84 | U3: 2597.14 | X3: casdo-ocena | Y3: Accessibility Standards Canada | Normes d’accessibilité Canada | Z3: 5 | AA3: 2597.14 | AB3: =ROUND(U3-AA3,2) | AC3: FALSE | AD3: =IF(U3="","MISSING_TOTAL",IF(ABS(AB3)<=0.01,"OK","CHECK")) | AE3: =IF(U3="","MISSING",IF(AND(AA3>0,U3/AA3>50),"POSSIBLE_SCALE_ERROR","OK"))
A4: T-2020-P11-0002 | B4: SLE | C4: Vice Chair | D4: vice-présidente | E4: Reid, Mary | F4: Board members meeting | G4: Réunion du conseil | H4: 43870 | I4: 43875 | J4: Vancouver, British Columbia, Canada | K4: Vancouver, Colombie-Britannique | P4: 2511.31 | Q4: 132.48 | R4: 785.65 | S4: 591 | T4: 108.3 | U4: 4128.74 | X4: casdo-ocena | Y4: Accessibility Standards Canada | Normes d’accessibilité Canada | Z4: 6 | AA4: 4128.74 | AB4: =ROUND(U4-AA4,2) | AC4: FALSE | AD4: =IF(U4="","MISSING_TOTAL",IF(ABS(AB4)<=0.01,"OK","CHECK")) | AE4: =IF(U4="","MISSING",IF(AND(AA4>0,U4/AA4>50),"POSSIBLE_SCALE_ERROR","OK"))
A5: T-2020-P11-0003 | B5: SLE | C5: Board Of Directors | D5: Membre du conseil de direction | E5: McLaughlin, Joseph | F5: Board members meeting | G5: Réunion du conseil | H5: 43870 | I5: 43873 | J5: Vancouver, British Columbia, Canada | K5: Vancouver, Colombie-Britannique | Q5: 58.32 | R5: 630.99 | S5: 264.6 | T5: 123 | U5: 1076.91 | X5: casdo-ocena | Y5: Accessibility Standards Canada | Normes d’accessibilité Canada | Z5: 4 | AA5: 1076.91 | AB5: =ROUND(U5-AA5,2) | AC5: FALSE | AD5: =IF(U5="","MISSING_TOTAL",IF(ABS(AB5)<=0.01,"OK","CHECK")) | AE5: =IF(U5="","MISSING",IF(AND(AA5>0,U5/AA5>50),"POSSIBLE_SCALE_ERROR","OK"))
A6: T-2020-P11-0004 | B6: SLE | C6: Board Of Directors | D6: Membre du conseil de direction | E6: Haan, Maureen | F6: Board members meeting | G6: Réunion du conseil | H6: 43870 | I6: 43873 | J6: Vancouver, British Columbia, Canada | K6: Vancouver, Colombie-Britannique | P6: 880.99 | Q6: 192.76 | R6: 630.99 | S6: 332.45 | U6: 2037.19 | X6: casdo-ocena | Y6: Accessibility Standards Canada | Normes d’accessibilité Canada | Z6: 4 | AA6: 2037.19 | AB6: =ROUND(U6-AA6,2) | AC6: FALSE | AD6: =IF(U6="","MISSING_TOTAL",IF(ABS(AB6)<=0.01,"OK","CHECK")) | AE6: =IF(U6="","MISSING",IF(AND(AA6>0,U6/AA6>50),"POSSIBLE_SCALE_ERROR","OK"))
A7: T-2020-P11-0005 | B7: SLE | C7: Board Of Directors | D7: Membre du conseil de direction | E7: Hartin, Penny | F7: Board members meeting | G7: Réunion du conseil | H7: 43870 | I7: 43873 | J7: Vancouver, British Columbia, Canada | K7: Vancouver, Colombie-Britannique | P7: 935.23 | Q7: 117.3 | R7: 630.99 | S7: 353.05 | U7: 2036.57 | X7: casdo-ocena | Y7: Accessibility Standards Canada | Normes d’accessibilité Canada | Z7: 4 | AA7: 2036.57 | AB7: =ROUND(U7-AA7,2) | AC7: FALSE | AD7: =IF(U7="","MISSING_TOTAL",IF(ABS(AB7)<=0.01,"OK","CHECK")) | AE7: =IF(U7="","MISSING",IF(AND(AA7>0,U7/AA7>50),"POSSIBLE_SCALE_ERROR","OK"))
A8: T-2020-P11-0006 | B8: SLE | C8: Board Of Directors | D8: Membre du conseil de direction | E8: Earle, Kory | F8: Board members meeting | G8: Réunion du conseil | H8: 43870 | I8: 43873 | J8: Vancouver, British Columbia, Canada | K8: Vancouver, Colombie-Britannique | P8: 949.11 | R8: 630.99 | S8: 373.4 | U8: 1953.5 | X8: casdo-ocena | Y8: Accessibility Standards Canada | Normes d’accessibilité Canada | Z8: 4 | AA8: 1953.5 | AB8: =ROUND(U8-AA8,2) | AC8: FALSE | AD8: =IF(U8="","MISSING_TOTAL",IF(ABS(AB8)<=0.01,"OK","CHECK")) | AE8: =IF(U8="","MISSING",IF(AND(AA8>0,U8/AA8>50),"POSSIBLE_SCALE_ERROR","OK"))
A9: T-2020-P11-0007 | B9: SLE | C9: Board Of Directors | D9: Membre du conseil de direction | E9: Ringaert, Laurie | F9: Board members meeting | G9: Réunion du conseil | H9: 43870 | I9: 43873 | J9: Vancouver, British Columbia, Canada | K9: Vancouver, Colombie-Britannique | P9: 662.91 | Q9: 128.43 | R9: 630.99 | S9: 332.45 | U9: 1754.78 | X9: casdo-ocena | Y9: Accessibility Standards Canada | Normes d’accessibilité Canada | Z9: 4 | AA9: 1754.78 | AB9: =ROUND(U9-AA9,2) | AC9: FALSE | AD9: =IF(U9="","MISSING_TOTAL",IF(ABS(AB9)<=0.01,"OK","CHECK")) | AE9: =IF(U9="","MISSING",IF(AND(AA9>0,U9/AA9>50),"POSSIBLE_SCALE_ERROR","OK"))
A10: T-2020-P11-0008 | B10: SLE | C10: Board Of Directors | D10: Membre du conseil de direction | E10: Khedr, Rabia | F10: Board members meeting | G10: Réunion du conseil | H10: 43870 | I10: 43873 | J10: Vancouver, British Columbia, Canada | K10: Vancouver, Colombie-Britannique | P10: 935.23 | Q10: 118.3 | R10: 630.99 | S10: 353.05 | U10: 2037.57 | X10: casdo-ocena | Y10: Accessibility Standards Canada | Normes d’accessibilité Canada | Z10: 4 | AA10: 2037.57 | AB10: =ROUND(U10-AA10,2) | AC10: FALSE | AD10: =IF(U10="","MISSING_TOTAL",IF(ABS(AB10)<=0.01,"OK","CHECK")) | AE10: =IF(U10="","MISSING",IF(AND(AA10>0,U10/AA10>50),"POSSIBLE_SCALE_ERROR","OK"))
A11: T-2020-P11-0009 | B11: SLE | C11: Chief Executive Officer | D11: Président-directeur général | E11: Rizcallah, Philip | F11: Board members meeting | G11: Réunion du conseil | H11: 43870 | I11: 43875 | J11: Vancouver, British Columbia, Canada | K11: Vancouver, Colombie-Britannique | P11: 1313.32 | Q11: 342.77 | R11: 970.75 | S11: 591 | T11: 313 | U11: 3530.84 | X11: casdo-ocena | Y11: Accessibility Standards Canada | Normes d’accessibilité Canada | Z11: 6 | AA11: 3530.84 | AB11: =ROUND(U11-AA11,2) | AC11: FALSE | AD11: =IF(U11="","MISSING_TOTAL",IF(ABS(AB11)<=0.01,"OK","CHECK")) | AE11: =IF(U11="","MISSING",IF(AND(AA11>0,U11/AA11>50),"POSSIBLE_SCALE_ERROR","OK"))
A12: T-2020-P1-0001 | B12: SLE | C12: Chair | D12: Président | E12: Bérubé, Paul-Claude | F12: Meeting with Chief Executive Officer of Accessibility Stadards Canada | G12: Réunion avec le Président-directeur général de Normes d’accessibilité Canada | H12: 43880 | I12: 43880 | J12: Montreal, Quebec, Canada | K12: Montréal, Québec, Canada | Q12: 62.06 | R12: 0 | S12: 20.6 | U12: 82.66 | X12: casdo-ocena | Y12: Accessibility Standards Canada | Normes d’accessibilité Canada | Z12: 1 | AA12: 82.66 | AB12: =ROUND(U12-AA12,2) | AC12: FALSE | AD12: =IF(U12="","MISSING_TOTAL",IF(ABS(AB12)<=0.01,"OK","CHECK")) | AE12: =IF(U12="","MISSING",IF(AND(AA12>0,U12/AA12>50),"POSSIBLE_SCALE_ERROR","OK"))
A13: T-2020-P1-0002 | B13: SLE | C13: Chair | D13: Président | E13: Bérubé, Paul-Claude | F13: Meeting with Chief Executive Officer and Staff of of Accessibility Stadards Canada | G13: Réunion avec le Président-directeur général et employés de Normes d’accessibilité Canada | H13: 43885 | I13: 43885 | J13: Ottawa, Ontario, Canada | K13: Ottawa, Ontario, Canada | Q13: 276.06 | R13: 0 | S13: 91.5 | U13: 367.56 | X13: casdo-ocena | Y13: Accessibility Standards Canada | Normes d’accessibilité Canada | Z13: 1 | AA13: 367.56 | AB13: =ROUND(U13-AA13,2) | AC13: FALSE | AD13: =IF(U13="","MISSING_TOTAL",IF(ABS(AB13)<=0.01,"OK","CHECK")) | AE13: =IF(U13="","MISSING",IF(AND(AA13>0,U13/AA13>50),"POSSIBLE_SCALE_ERROR","OK"))
A14: T-2020-P1-0003 | B14: SLE | C14: Chief Executive Officer | D14: Président-directeur général | E14: Rizcallah, Philip | F14: Meetings with various Stakeholders | G14: Réunions avec divers intervenants | H14: 43851 | I14: 43855 | J14: Toronto, Ontario and Halifax, Nova Scotia, Canada | K14: Toronto, Ontario et Halifax, Nouvelle-Écosse, Canada | P14: 1190.86 | Q14: 359.36 | R14: 344.73 | S14: 394.25 | T14: 172.2 | U14: 2461.4 | X14: casdo-ocena | Y14: Accessibility Standards Canada | Normes d’accessibilité Canada | Z14: 5 | AA14: 2461.4 | AB14: =ROUND(U14-AA14,2) | AC14: FALSE | AD14: =IF(U14="","MISSING_TOTAL",IF(ABS(AB14)<=0.01,"OK","CHECK")) | AE14: =IF(U14="","MISSING",IF(AND(AA14>0,U14/AA14>50),"POSSIBLE_SCALE_ERROR","OK"))
A15: T-2020-P2-0001 | B15: SLE | C15: Chief Executive Officer | D15: Président-directeur général | E15: Rizcallah, Philip | F15: To attend Canadian Accessibility Standards Development Organization business meetings | G15: Pour assister des réunions d'affaire de l'Organisation Canadienne d'élaboration de normes d'accessibilité | H15: 43900 | I15: 43900 | J15: Montréal, Quebec, Canada | K15: Montréal, Québec, Canada | P15: 0 | Q15: 339.57 | R15: 0 | S15: 71.15 | T15: 3.2 | U15: 413.92 | X15: casdo-ocena | Y15: Accessibility Standards Canada | Normes d’accessibilité Canada | Z15: 1 | AA15: 413.92 | AB15: =ROUND(U15-AA15,2) | AC15: FALSE | AD15: =IF(U15="","MISSING_TOTAL",IF(ABS(AB15)<=0.01,"OK","CHECK")) | AE15: =IF(U15="","MISSING",IF(AND(AA15>0,U15/AA15>50),"POSSIBLE_SCALE_ERROR","OK"))
A16: T-2020-P2-0002 | B16: SLE | C16: Chief Executive Officer | D16: Président-directeur général | E16: Rizcallah, Philip | F16: To attend meeting with Chair and Chief Operating Officer | G16: Pour assister à une réunion avec le Président et le Chef de l’exploitation | H16: 43880 | I16: 43880 | J16: Montréal, Quebec, Canada | K16: Montréal, Québec, Canada | P16: 0 | Q16: 267.25 | R16: 0 | S16: 20.6 | T16: 0 | U16: 287.85 | X16: casdo-ocena | Y16: Accessibility Standards Canada | Normes d’accessibilité Canada | Z16: 1 | AA16: 287.85 | AB16: =ROUND(U16-AA16,2) | AC16: FALSE | AD16: =IF(U16="","MISSING_TOTAL",IF(ABS(AB16)<=0.01,"OK","CHECK")) | AE16: =IF(U16="","MISSING",IF(AND(AA16>0,U16/AA16>50),"POSSIBLE_SCALE_ERROR","OK"))
A17: T-2020-P2-0003 | B17: SLE | C17: Chief Executive Officer | D17: Président-directeur général | E17: Rizcallah, Philip | F17: To attend meeting with Chair | G17: Pour assister à une réunion avec le Président | H17: 43867 | I17: 43868 | J17: Saint-Jean-sur-Richelieu, Quebec, Canada | K17: Saint-Jean-sur-Richelieu, Québec, Canada | P17: 0 | Q17: 315.28 | R17: 0 | S17: 91.5 | T17: 3.2 | U17: 409.98 | X17: casdo-ocena | Y17: Accessibility Standards Canada | Normes d’accessibilité Canada | Z17: 2 | AA17: 409.98 | AB17: =ROUND(U17-AA17,2) | AC17: FALSE | AD17: =IF(U17="","MISSING_TOTAL",IF(ABS(AB17)<=0.01,"OK","CHECK")) | AE17: =IF(U17="","MISSING",IF(AND(AA17>0,U17/AA17>50),"POSSIBLE_SCALE_ERROR","OK"))
A18: T-2020-P2-0004 | B18: SLE | C18: Chair | D18: Président | E18: Bérubé, Paul-Claude | F18: To attend meeting with Canadian Accessibility Standards Development Organization Chief Executive Officer and Vice-chair | G18: Pour assister à une réunion avec le Directeur général et le Vice-Président du Conseil d'administration de l'Organisation Canadienne d'élaboration de normes d'accessibilité | H18: 43858 | I18: 43858 | J18: Ottawa, Ontario, Canada | K18: Ottawa, Ontario, Canada | P18: 0 | Q18: 563.09 | R18: 0 | S18: 20.6 | T18: 0 | U18: 583.69 | X18: casdo-ocena | Y18: Accessibility Standards Canada | Normes d’accessibilité Canada | Z18: 1 | AA18: 583.69 | AB18: =ROUND(U18-AA18,2) | AC18: FALSE | AD18: =IF(U18="","MISSING_TOTAL",IF(ABS(AB18)<=0.01,"OK","CHECK")) | AE18: =IF(U18="","MISSING",IF(AND(AA18>0,U18/AA18>50),"POSSIBLE_SCALE_ERROR","OK"))
A19: T-2020-P2-0005 | B19: SLE | C19: Chair | D19: Président | E19: Bérubé, Paul-Claude | F19: Physical presence required for Canadian Accessibility Standards Development Organization board members meeting | G19: Participer à la réunion du conseil d'administration de l'Organisation canadienne d'élaboration de normes d'accessibilité | H19: 43851 | I19: 43851 | J19: Ottawa, Ontario, Canada | K19: Ottawa, Ontario, Canada | P19: 0 | Q19: 440.71 | R19: 0 | S19: 20.6 | T19: 0 | U19: 461.31 | X19: casdo-ocena | Y19: Accessibility Standards Canada | Normes d’accessibilité Canada | Z19: 1 | AA19: 461.31 | AB19: =ROUND(U19-AA19,2) | AC19: FALSE | AD19: =IF(U19="","MISSING_TOTAL",IF(ABS(AB19)<=0.01,"OK","CHECK")) | AE19: =IF(U19="","MISSING",IF(AND(AA19>0,U19/AA19>50),"POSSIBLE_SCALE_ERROR","OK"))
A20: T-2020-P2-0006 | B20: SLE | C20: Vice Chair | D20: Vice-Présidente | E20: Reid, Mary | F20: To attend meeting with Canadian Accessibility Standards Development Organization Chief Executive Officer and Chair | G20: Pour assister à une réunion avec le Directeur général du Conseil d'administration et le président de l'Organisation Canadienne d'élaboration de normes d'accessibilité | H20: 43899 | I20: 43900 | J20: Montréal, Quebec, Canada | K20: Montréal, Québec, Canada | P20: 1278.66 | Q20: 32 | R20: 50 | S20: 112.1 | T20: 0 | U20: 1472.76 | X20: casdo-ocena | Y20: Accessibility Standards Canada | Normes d’accessibilité Canada | Z20: 2 | AA20: 1472.76 | AB20: =ROUND(U20-AA20,2) | AC20: FALSE | AD20: =IF(U20="","MISSING_TOTAL",IF(ABS(AB20)<=0.01,"OK","CHECK")) | AE20: =IF(U20="","MISSING",IF(AND(AA20>0,U20/AA20>50),"POSSIBLE_SCALE_ERROR","OK"))
A21: T-2020-P2-0007 | B21: SLE | C21: Vice Chair | D21: Vice-Présidente | E21: Reid, Mary | F21: To attend meeting with Canadian Accessibility Standards Development Organization Chief Executive Officer | G21: Pour assister à une réunion avec le Directeur général du Conseil d'administration de l'Organisation Canadienne d'élaboration de normes d'accessibilité | H21: 43849 | I21: 43850 | J21: Ottawa, Ontario, Canada | K21: Ottawa, Ontario, Canada | P21: 1210.74 | Q21: 70.25 | R21: 269.12 | S21: 197.25 | T21: 0 | U21: 1747.36 | X21: casdo-ocena | Y21: Accessibility Standards Canada | Normes d’accessibilité Canada | Z21: 2 | AA21: 1747.36 | AB21: =ROUND(U21-AA21,2) | AC21: FALSE | AD21: =IF(U21="","MISSING_TOTAL",IF(ABS(AB21)<=0.01,"OK","CHECK")) | AE21: =IF(U21="","MISSING",IF(AND(AA21>0,U21/AA21>50),"POSSIBLE_SCALE_ERROR","OK"))
A22: T-2020-P2-0008 | B22: SLE | C22: Board Of Directors | D22: Membre du conseil d'administration | E22: Adair, William | F22: Physical presence required for Canadian Accessibility Standards Development Organization board members meeting | G22: Participer à la réunion du conseil d'administration de l'Organisation canadienne d'élaboration de normes d'accessibilité | H22: 43870 | I22: 43873 | J22: Vancouver, British Columbia, Canada | K22: Vancouver, Colombie-Britannique, Canada | P22: 894.55 | Q22: 163.15 | R22: 630.99 | S22: 353.05 | T22: 0 | U22: 2041.74 | X22: casdo-ocena | Y22: Accessibility Standards Canada | Normes d’accessibilité Canada | Z22: 4 | AA22: 2041.74 | AB22: =ROUND(U22-AA22,2) | AC22: FALSE | AD22: =IF(U22="","MISSING_TOTAL",IF(ABS(AB22)<=0.01,"OK","CHECK")) | AE22: =IF(U22="","MISSING",IF(AND(AA22>0,U22/AA22>50),"POSSIBLE_SCALE_ERROR","OK"))
A23: T-2022-P5-0001 | B23: SLE | C23: Chief Executive Officer | D23: Président-directeur général | E23: Rizcallah, Philip | F23: Meeting with Government of Quebec | G23: Réunion avec le gouvernement du Québec | H23: 44518 | I23: 44519 | J23: Brossard, Quebec, Canada | K23: Brossard, Québec, Canada | P23: 0 | Q23: 324.3 | R23: 177.31 | S23: 183.55 | T23: 11.6 | U23: 696.76 | X23: casdo-ocena | Y23: Accessibility Standards Canada | Normes d’accessibilité Canada | Z23: 2 | AA23: 696.76 | AB23: =ROUND(U23-AA23,2) | AC23: FALSE | AD23: =IF(U23="","MISSING_TOTAL",IF(ABS(AB23)<=0.01,"OK","CHECK")) | AE23: =IF(U23="","MISSING",IF(AND(AA23>0,U23/AA23>50),"POSSIBLE_SCALE_ERROR","OK"))
A24: T-2022-P5-0002 | B24: SLE | C24: Chief Executive Officer | D24: Président-directeur général | E24: Rizcallah, Philip | F24: Meeting with the Office des personnes handicapées du Québec | G24: Réunion avec l'Office des personnes handicapées du Québec | H24: 44545 | I24: 44546 | J24: Québec, Quebec, Canada | K24: Québec, Québec, Canada | P24: 811.86 | Q24: 235.12 | R24: 154.7 | S24: 226.5 | T24: 0 | U24: 1428.18 | X24: casdo-ocena | Y24: Accessibility Standards Canada | Normes d’accessibilité Canada | Z24: 2 | AA24: 1428.18 | AB24: =ROUND(U24-AA24,2) | AC24: FALSE | AD24: =IF(U24="","MISSING_TOTAL",IF(ABS(AB24)<=0.01,"OK","CHECK")) | AE24: =IF(U24="","MISSING",IF(AND(AA24>0,U24/AA24>50),"POSSIBLE_SCALE_ERROR","OK"))
A25: T-2022-P5-0004 | B25: SLE | C25: Chief Executive Officer | D25: Président-directeur général | E25: Rizcallah, Philip | F25: Stakeholder meetings in Atlantic Canada | G25: Réunions avec parties prenantes | H25: 44604 | I25: 44615 | J25: St. John's, NL | K25: St. John's, TN | P25: 1095.53 | Q25: 304.61 | R25: 553.43 | S25: 884.65 | T25: 253.04 | U25: 3091.26 | X25: casdo-ocena | Y25: Accessibility Standards Canada | Normes d’accessibilité Canada | Z25: 12 | AA25: 3091.26 | AB25: =ROUND(U25-AA25,2) | AC25: FALSE | AD25: =IF(U25="","MISSING_TOTAL",IF(ABS(AB25)<=0.01,"OK","CHECK")) | AE25: =IF(U25="","MISSING",IF(AND(AA25>0,U25/AA25>50),"POSSIBLE_SCALE_ERROR","OK"))
A26: T-2022-P5-0005 | B26: SLE | C26: Chief Executive Officer | D26: Président-directeur général | E26: Rizcallah, Philip | F26: Meeting with Legislative Assembly of New Brunswick | G26: Réunion avec l'Assemblée législative due Nouveau-Brunswick | H26: 44620 | I26: 44621 | J26: Fredericton, NB | K26: Fredericton, NB | P26: 817.28 | Q26: 237.17 | R26: 151.17 | S26: 205.15 | T26: 0 | U26: 1410.77 | X26: casdo-ocena | Y26: Accessibility Standards Canada | Normes d’accessibilité Canada | Z26: 2 | AA26: 1410.77 | AB26: =ROUND(U26-AA26,2) | AC26: FALSE | AD26: =IF(U26="","MISSING_TOTAL",IF(ABS(AB26)<=0.01,"OK","CHECK")) | AE26: =IF(U26="","MISSING",IF(AND(AA26>0,U26/AA26>50),"POSSIBLE_SCALE_ERROR","OK"))
A27: T-2023-P2-0001 | B27: SLE | C27: Chief Executive Officer | D27: Président-directeur général | E27: Rizcallah, Philip | F27: Stakeholder meetings in Toronto | G27: Réunions avec des parties prenantes à Toronto | H27: 44658 | I27: 44660 | J27: Toronto, Ontario, Canada | K27: Toronto, Ontario, Canada | P27: 721.22 | Q27: 193.16 | R27: 491.24 | S27: 292.85 | U27: 1698.47 | X27: casdo-ocena | Y27: Accessibility Standards Canada | Normes d’accessibilité Canada | Z27: 3 | AA27: 1698.47 | AB27: =ROUND(U27-AA27,2) | AC27: FALSE | AD27: =IF(U27="","MISSING_TOTAL",IF(ABS(AB27)<=0.01,"OK","CHECK")) | AE27: =IF(U27="","MISSING",IF(AND(AA27>0,U27/AA27>50),"POSSIBLE_SCALE_ERROR","OK"))
A28: T-2023-P3-0001 | B28: SLE | C28: Chief Executive Officer | D28: Président-directeur général | E28: Rizcallah, Philip | F28: Stakeholder meetings in Halifax | G28: Réunions avec des parties prenantes à Halifax | H28: 44663 | I28: 44668 | J28: Halifax, Nova Scotia, Canada | K28: Halifax, Nouvelle-Ecosse, Canada | P28: 651.37 | Q28: 279.34 | R28: 594.72 | S28: 342.4 | T28: 14.27 | U28: 1882.1 | X28: casdo-ocena | Y28: Accessibility Standards Canada | Normes d’accessibilité Canada | Z28: 6 | AA28: 1882.1 | AB28: =ROUND(U28-AA28,2) | AC28: FALSE | AD28: =IF(U28="","MISSING_TOTAL",IF(ABS(AB28)<=0.01,"OK","CHECK")) | AE28: =IF(U28="","MISSING",IF(AND(AA28>0,U28/AA28>50),"POSSIBLE_SCALE_ERROR","OK"))
A29: T-2023-P3-0002 | B29: SLE | C29: Chief Executive Officer | D29: Président-directeur général | E29: Rizcallah, Philip | F29: Stakeholder meetings in Edmonton | G29: Réunions avec des parties prenantes en Edmonton | H29: 44677 | I29: 44679 | J29: Edmonton, Alberta | K29: Edmonton, Alberta | P29: 1504.7 | Q29: 205.31 | R29: 334.56 | S29: 347.25 | T29: 0 | U29: 2391.82 | X29: casdo-ocena | Y29: Accessibility Standards Canada | Normes d’accessibilité Canada | Z29: 3 | AA29: 2391.82 | AB29: =ROUND(U29-AA29,2) | AC29: FALSE | AD29: =IF(U29="","MISSING_TOTAL",IF(ABS(AB29)<=0.01,"OK","CHECK")) | AE29: =IF(U29="","MISSING",IF(AND(AA29>0,U29/AA29>50),"POSSIBLE_SCALE_ERROR","OK"))
A30: T-2023-P3-0003 | B30: SLE | C30: Chief Executive Officer | D30: Président-directeur général | E30: Rizcallah, Philip | F30: Stakeholder meetings in Victoria and Vancouver | G30: Réunions avec des parties prenantes à Victoria et Vancouver | H30: 44704 | I30: 44707 | J30: Victoria and Vancouver, British Columbia, Canada | K30: Victoria et Vancouver, Colombie-Britannique | P30: 1818.5 | Q30: 691.09 | R30: 900.59 | S30: 463 | T30: 0 | U30: 3873.18 | X30: casdo-ocena | Y30: Accessibility Standards Canada | Normes d’accessibilité Canada | Z30: 4 | AA30: 3873.18 | AB30: =ROUND(U30-AA30,2) | AC30: FALSE | AD30: =IF(U30="","MISSING_TOTAL",IF(ABS(AB30)<=0.01,"OK","CHECK")) | AE30: =IF(U30="","MISSING",IF(AND(AA30>0,U30/AA30>50),"POSSIBLE_SCALE_ERROR","OK"))
A31: T-2023-P4-0001 | B31: SLE | C31: Chief Executive Officer | D31: Président-directeur général | E31: Rizcallah, Philip | F31: Stakeholder meetings in Moncton | G31: Réunions avec des parties prenantes à Moncton | H31: 44733 | I31: 44734 | J31: Moncton, New Brunswick, Canada | K31: Moncton, Nouveau Brunswick, Canada | P31: 986.9 | Q31: 182.9 | R31: 141.55 | S31: 231.5 | T31: 0 | U31: 1542.85 | X31: casdo-ocena | Y31: Accessibility Standards Canada | Normes d’accessibilité Canada | Z31: 2 | AA31: 1542.85 | AB31: =ROUND(U31-AA31,2) | AC31: FALSE | AD31: =IF(U31="","MISSING_TOTAL",IF(ABS(AB31)<=0.01,"OK","CHECK")) | AE31: =IF(U31="","MISSING",IF(AND(AA31>0,U31/AA31>50),"POSSIBLE_SCALE_ERROR","OK"))
A32: T-2023-P4-0002 | B32: SLE | C32: Chief Executive Officer | D32: Président-directeur général | E32: Rizcallah, Philip | F32: Stakeholder meetings in Toronto | G32: Réunions avec des parties prenantes en Toronto | H32: 44735 | I32: 44736 | J32: Toronto, Ontario, Canada | K32: Toronto, Ontario, Canada | P32: 0 | Q32: 665.2 | R32: 404.27 | S32: 231.5 | T32: 23.73 | U32: 1324.7 | X32: casdo-ocena | Y32: Accessibility Standards Canada | Normes d’accessibilité Canada | Z32: 2 | AA32: 1324.7 | AB32: =ROUND(U32-AA32,2) | AC32: FALSE | AD32: =IF(U32="","MISSING_TOTAL",IF(ABS(AB32)<=0.01,"OK","CHECK")) | AE32: =IF(U32="","MISSING",IF(AND(AA32>0,U32/AA32>50),"POSSIBLE_SCALE_ERROR","OK"))
A33: T-2023-P5-0001 | B33: SLE | C33: Chief Executive Officer | D33: Président-directeur général | E33: Rizcallah, Philip | F33: CACP CIPH Annual Meeting | G33: Réunion annuelle CACP CIPH | H33: 44787 | I33: 44790 | J33: Halifax, Nova Scotia, Canada | K33: Halifax, Nouvelle Ecosse, Canada | P33: 698.64 | Q33: 278.92 | R33: 443.4 | S33: 468.95 | T33: 0 | U33: 1889.91 | X33: casdo-ocena | Y33: Accessibility Standards Canada | Normes d’accessibilité Canada | Z33: 4 | AA33: 1889.91 | AB33: =ROUND(U33-AA33,2) | AC33: FALSE | AD33: =IF(U33="","MISSING_TOTAL",IF(ABS(AB33)<=0.01,"OK","CHECK")) | AE33: =IF(U33="","MISSING",IF(AND(AA33>0,U33/AA33>50),"POSSIBLE_SCALE_ERROR","OK"))
A34: T-2023-P5-0002 | B34: SLE | C34: Chief Executive Officer | D34: Président-directeur général | E34: Rizcallah, Philip | F34: Standard and training review | G34: Formation des normes | H34: 44798 | I34: 44800 | J34: Peterborough, Ontario, Canada | K34: Peterborough, Ontario, Canada | P34: 0 | Q34: 336.6 | R34: 369.75 | S34: 270.95 | T34: 0 | U34: 977.3 | X34: casdo-ocena | Y34: Accessibility Standards Canada | Normes d’accessibilité Canada | Z34: 3 | AA34: 977.3 | AB34: =ROUND(U34-AA34,2) | AC34: FALSE | AD34: =IF(U34="","MISSING_TOTAL",IF(ABS(AB34)<=0.01,"OK","CHECK")) | AE34: =IF(U34="","MISSING",IF(AND(AA34>0,U34/AA34>50),"POSSIBLE_SCALE_ERROR","OK"))
A35: T-2023-P5-0003 | B35: SLE | C35: Chair | D35: Président | E35: Bérubé, Paul-Claude | F35: Meeting with CEO | G35: Réunion avec PDG | H35: 44769 | I35: 44769 | J35: Brossard, Quebec, Canada | K35: Brossard, Québec, Canada | P35: 0 | Q35: 41.25 | R35: 0 | S35: 22.15 | T35: 0 | U35: 63.4 | X35: casdo-ocena | Y35: Accessibility Standards Canada | Normes d’accessibilité Canada | Z35: 1 | AA35: 63.4 | AB35: =ROUND(U35-AA35,2) | AC35: FALSE | AD35: =IF(U35="","MISSING_TOTAL",IF(ABS(AB35)<=0.01,"OK","CHECK")) | AE35: =IF(U35="","MISSING",IF(AND(AA35>0,U35/AA35>50),"POSSIBLE_SCALE_ERROR","OK"))
A36: T-2023-P5-0004 | B36: SLE | C36: Chair | D36: Président | E36: Bérubé, Paul-Claude | F36: Meeting with Vie Autonome | G36: Réunion avec Vie Autonome | H36: 44779 | I36: 44779 | J36: Val d'Or, Quebec, Canada | K36: Val d'Or, Québec, Canada | P36: 1633.64 | Q36: 108.7 | R36: 0 | S36: 98.45 | T36: 0 | U36: 1840.79 | X36: casdo-ocena | Y36: Accessibility Standards Canada | Normes d’accessibilité Canada | Z36: 1 | AA36: 1840.79 | AB36: =ROUND(U36-AA36,2) | AC36: FALSE | AD36: =IF(U36="","MISSING_TOTAL",IF(ABS(AB36)<=0.01,"OK","CHECK")) | AE36: =IF(U36="","MISSING",IF(AND(AA36>0,U36/AA36>50),"POSSIBLE_SCALE_ERROR","OK"))
A37: T-2023-P5-0005 | B37: SLE | C37: Chair | D37: Président | E37: Bérubé, Paul-Claude | F37: Meeting with CEO and co-Chair | G37: Réunion avec PDG et co-président | H37: 44752 | I37: 44754 | J37: Gatineau, Quebec, Canada | K37: Gatineau, Québec, Canada | P37: 0 | Q37: 296.04 | R37: 783.04 | S37: 259.4 | T37: 0 | U37: 1338.48 | X37: casdo-ocena | Y37: Accessibility Standards Canada | Normes d’accessibilité Canada | Z37: 3 | AA37: 1338.48 | AB37: =ROUND(U37-AA37,2) | AC37: FALSE | AD37: =IF(U37="","MISSING_TOTAL",IF(ABS(AB37)<=0.01,"OK","CHECK")) | AE37: =IF(U37="","MISSING",IF(AND(AA37>0,U37/AA37>50),"POSSIBLE_SCALE_ERROR","OK"))
A38: T-2023-P5-0006 | B38: SLE | C38: Board Member | D38: Membre du conseil d'administration | E38: McLaughlin, Joseph | F38: Stakeholder meeting | G38: Réunion des parties prenantes | H38: 44706 | I38: 44706 | J38: Vancouver, British Columbia, Canada | K38: Vancouver, Colombie Britannique, Canada | P38: 0 | Q38: 49.68 | R38: 0 | S38: 0 | U38: 49.68 | X38: casdo-ocena | Y38: Accessibility Standards Canada | Normes d’accessibilité Canada | Z38: 1 | AA38: 49.68 | AB38: =ROUND(U38-AA38,2) | AC38: FALSE | AD38: =IF(U38="","MISSING_TOTAL",IF(ABS(AB38)<=0.01,"OK","CHECK")) | AE38: =IF(U38="","MISSING",IF(AND(AA38>0,U38/AA38>50),"POSSIBLE_SCALE_ERROR","OK"))
A39: T-2023-P6-0001 | B39: SLE | C39: Vice Chair | D39: Vice président | E39: Reid, Mary | F39: Meeting with CEO and Chair | G39: Réunion avec PDG et Président | H39: 44745 | I39: 44755 | J39: Gatineau, Quebec, Canada | K39: Gatineau, Québec, Canada | P39: 780.54 | Q39: 50 | R39: 371.32 | S39: 270.7 | T39: 0 | U39: 1472.56 | X39: casdo-ocena | Y39: Accessibility Standards Canada | Normes d’accessibilité Canada | Z39: 11 | AA39: 1472.56 | AB39: =ROUND(U39-AA39,2) | AC39: FALSE | AD39: =IF(U39="","MISSING_TOTAL",IF(ABS(AB39)<=0.01,"OK","CHECK")) | AE39: =IF(U39="","MISSING",IF(AND(AA39>0,U39/AA39>50),"POSSIBLE_SCALE_ERROR","OK"))
A40: T-2023-P7-0001 | B40: SLE | C40: Chief Executive Officer | D40: Président-directeur général | E40: Rizcallah, Philip | F40: International conference on Universal Design | G40: Conférence internationale sur la conception universelle | H40: 44805 | I40: 44814 | J40: Venice, Italy | K40: Venise, Italie | P40: 12175.56 | Q40: 592.46 | R40: 996.34 | S40: 731.55 | T40: 0 | U40: 14495.91 | X40: casdo-ocena | Y40: Accessibility Standards Canada | Normes d’accessibilité Canada | Z40: 10 | AA40: 14495.91 | AB40: =ROUND(U40-AA40,2) | AC40: FALSE | AD40: =IF(U40="","MISSING_TOTAL",IF(ABS(AB40)<=0.01,"OK","CHECK")) | AE40: =IF(U40="","MISSING",IF(AND(AA40>0,U40/AA40>50),"POSSIBLE_SCALE_ERROR","OK"))
A41: T-2023-P7-0002 | B41: SLE | C41: Chief Executive Officer | D41: Président-directeur général | E41: Rizcallah, Philip | F41: Presenter at International Code Conference | G41: Présenteur à la conférence internationale des codes | H41: 44816 | I41: 44818 | J41: Louisville, Kentucky | K41: Lousiville, Kentucky | P41: 1668.11 | Q41: 202.11 | R41: 400.4 | S41: 422.29 | T41: 0 | U41: 2692.91 | X41: casdo-ocena | Y41: Accessibility Standards Canada | Normes d’accessibilité Canada | Z41: 3 | AA41: 2692.91 | AB41: =ROUND(U41-AA41,2) | AC41: FALSE | AD41: =IF(U41="","MISSING_TOTAL",IF(ABS(AB41)<=0.01,"OK","CHECK")) | AE41: =IF(U41="","MISSING",IF(AND(AA41>0,U41/AA41>50),"POSSIBLE_SCALE_ERROR","OK"))
A42: T-2023-P7-0003 | B42: SLE | C42: Chief Executive Officer | D42: Président-directeur général | E42: Rizcallah, Philip | F42: Board meeting | G42: Réunion du conseil d'administration | H42: 44822 | I42: 44825 | J42: Montreal, Quebec, Canada | K42: Montréal, Québec, Canada | P42: 0 | Q42: 671.27 | R42: 0 | S42: 418.95 | T42: 0 | U42: 1090.22 | X42: casdo-ocena | Y42: Accessibility Standards Canada | Normes d’accessibilité Canada | Z42: 4 | AA42: 1090.22 | AB42: =ROUND(U42-AA42,2) | AC42: FALSE | AD42: =IF(U42="","MISSING_TOTAL",IF(ABS(AB42)<=0.01,"OK","CHECK")) | AE42: =IF(U42="","MISSING",IF(AND(AA42>0,U42/AA42>50),"POSSIBLE_SCALE_ERROR","OK"))
A43: T-2023-P7-0004 | B43: SLE | C43: Vice Chair | D43: Vice président | E43: Reid, Mary | F43: Board meeting | G43: Réunion du conseil d'administration | H43: 44822 | I43: 44825 | J43: Montreal, Quebec, Canada | K43: Montréal, Québec, Canada | P43: 670.23 | Q43: 106.34 | R43: 0 | S43: 396.8 | T43: 0 | U43: 1173.37 | X43: casdo-ocena | Y43: Accessibility Standards Canada | Normes d’accessibilité Canada | Z43: 4 | AA43: 1173.37 | AB43: =ROUND(U43-AA43,2) | AC43: FALSE | AD43: =IF(U43="","MISSING_TOTAL",IF(ABS(AB43)<=0.01,"OK","CHECK")) | AE43: =IF(U43="","MISSING",IF(AND(AA43>0,U43/AA43>50),"POSSIBLE_SCALE_ERROR","OK"))
A44: T-2023-P7-0005 | B44: SLE | C44: Board Member | D44: Membre du conseil d'administration | E44: McLaughlin, Joseph | F44: Board meeting | G44: Réunion du conseil d'administration | H44: 44822 | I44: 44825 | J44: Montreal, Quebec, Canada | K44: Montréal, Québec, Canada | P44: 822.12 | Q44: 283.29 | R44: 1067.43 | S44: 418.7 | T44: 0 | U44: 2591.54 | X44: casdo-ocena | Y44: Accessibility Standards Canada | Normes d’accessibilité Canada | Z44: 4 | AA44: 2591.54 | AB44: =ROUND(U44-AA44,2) | AC44: FALSE | AD44: =IF(U44="","MISSING_TOTAL",IF(ABS(AB44)<=0.01,"OK","CHECK")) | AE44: =IF(U44="","MISSING",IF(AND(AA44>0,U44/AA44>50),"POSSIBLE_SCALE_ERROR","OK"))
A45: T-2023-P8-0001 | B45: SLE | C45: Chief Executive Officer | D45: Président-directeur général | E45: Rizcallah, Philip | F45: Meeting with stakeholders | G45: Réunion avec les intervenants. | H45: 44714 | I45: 44717 | J45: Halifax, Nova Scotia, Canada | K45: Halifax, Nouvelle Ecosse, Canada | P45: 770.06 | Q45: 729.51 | R45: 466.86 | S45: 231.5 | T45: 0 | U45: 2197.93 | X45: casdo-ocena | Y45: Accessibility Standards Canada | Normes d’accessibilité Canada | Z45: 4 | AA45: 2197.93 | AB45: =ROUND(U45-AA45,2) | AC45: FALSE | AD45: =IF(U45="","MISSING_TOTAL",IF(ABS(AB45)<=0.01,"OK","CHECK")) | AE45: =IF(U45="","MISSING",IF(AND(AA45>0,U45/AA45>50),"POSSIBLE_SCALE_ERROR","OK"))
A46: T-2023-P8-0002 | B46: SLE | C46: Board Member | D46: Membre du conseil d'administration | E46: Hartin, Penny | F46: Board meeting & APM. | G46: Réunion du conseil d'administration & APM. | H46: 44822 | I46: 44825 | J46: Montreal, Quebec, Canada | K46: Montréal, Québec, Canada | P46: 579.53 | Q46: 231.13 | R46: 0 | S46: 396.8 | T46: 0 | U46: 1207.46 | X46: casdo-ocena | Y46: Accessibility Standards Canada | Normes d’accessibilité Canada | Z46: 4 | AA46: 1207.46 | AB46: =ROUND(U46-AA46,2) | AC46: FALSE | AD46: =IF(U46="","MISSING_TOTAL",IF(ABS(AB46)<=0.01,"OK","CHECK")) | AE46: =IF(U46="","MISSING",IF(AND(AA46>0,U46/AA46>50),"POSSIBLE_SCALE_ERROR","OK"))
A47: T-2023-P8-0003 | B47: SLE | C47: Board Member | D47: Membre du conseil d'administration | E47: Haan, Maureen | F47: Board meeting & APM. | G47: Réunion du conseil d'administration & APM. | H47: 44822 | I47: 44825 | J47: Montreal, Quebec, Canada | K47: Montréal, Québec, Canada | P47: 693.66 | Q47: 135 | R47: 0 | S47: 396.8 | T47: 0 | U47: 1225.46 | X47: casdo-ocena | Y47: Accessibility Standards Canada | Normes d’accessibilité Canada | Z47: 4 | AA47: 1225.46 | AB47: =ROUND(U47-AA47,2) | AC47: FALSE | AD47: =IF(U47="","MISSING_TOTAL",IF(ABS(AB47)<=0.01,"OK","CHECK")) | AE47: =IF(U47="","MISSING",IF(AND(AA47>0,U47/AA47>50),"POSSIBLE_SCALE_ERROR","OK"))
A48: T-2023-P9-0001 | B48: SLE | C48: Chief Executive Officer | D48: Président-directeur général | E48: Rizcallah, Philip | F48: Intelligent Cities Summit. | G48: Sommet ''Intelligent Cities''. | H48: 44873 | I48: 44875 | J48: Toronto, Ontario, Canada | K48: Toronto, Ontario, Canada | P48: 591.5 | Q48: 246.49 | R48: 0 | S48: 250 | T48: 0 | U48: 1087.99 | X48: casdo-ocena | Y48: Accessibility Standards Canada | Normes d’accessibilité Canada | Z48: 3 | AA48: 1087.99 | AB48: =ROUND(U48-AA48,2) | AC48: FALSE | AD48: =IF(U48="","MISSING_TOTAL",IF(ABS(AB48)<=0.01,"OK","CHECK")) | AE48: =IF(U48="","MISSING",IF(AND(AA48>0,U48/AA48>50),"POSSIBLE_SCALE_ERROR","OK"))
A49: T-2023-P9-0002 | B49: SLE | C49: Chief Executive Officer | D49: Président-directeur général | E49: Rizcallah, Philip | F49: NSBOA conference. | G49: Conférence NSBOA. | H49: 44879 | I49: 44881 | J49: Halifax, Nova Scotia, Canada | K49: Halifax, Nouvelle Écosse, Canada | P49: 331.07 | Q49: 180.2 | R49: 50 | S49: 119.75 | T49: 0 | U49: 681.02 | X49: casdo-ocena | Y49: Accessibility Standards Canada | Normes d’accessibilité Canada | Z49: 3 | AA49: 681.02 | AB49: =ROUND(U49-AA49,2) | AC49: FALSE | AD49: =IF(U49="","MISSING_TOTAL",IF(ABS(AB49)<=0.01,"OK","CHECK")) | AE49: =IF(U49="","MISSING",IF(AND(AA49>0,U49/AA49>50),"POSSIBLE_SCALE_ERROR","OK"))
A50: T-2023-P9-0003 | B50: SLE | C50: Chief Executive Officer | D50: Président-directeur général | E50: Rizcallah, Philip | F50: BCANDS conference. | G50: Évènement BCANDS. | H50: 44881 | I50: 44884 | J50: Victoria, Bristish Columbia, Canada | K50: Victoria, Colombie Britanique, Canada | P50: 1345.32 | Q50: 239.97 | R50: 419.42 | S50: 233.75 | T50: 0 | U50: 2238.46 | X50: casdo-ocena | Y50: Accessibility Standards Canada | Normes d’accessibilité Canada | Z50: 4 | AA50: 2238.46 | AB50: =ROUND(U50-AA50,2) | AC50: FALSE | AD50: =IF(U50="","MISSING_TOTAL",IF(ABS(AB50)<=0.01,"OK","CHECK")) | AE50: =IF(U50="","MISSING",IF(AND(AA50>0,U50/AA50>50),"POSSIBLE_SCALE_ERROR","OK"))
... A91: T-2024-P5-0002 | B91: SLE | C91: Chief Executive Officer | D91: Président-directeur général | E91: Rizcallah, Philip | F91: Stakeholder meeting | G91: Réunions | H91: 45143 | I91: 45147 | J91: Halifax, Nova Scotia, Canada | K91: Halifax, Nouvelle-Ecosse, Canada | P91: 828.14 | Q91: 512.51 | R91: 731.41 | S91: 485 | T91: 0 | U91: 2557.06 | X91: casdo-ocena | Y91: Accessibility Standards Canada | Normes d’accessibilité Canada | Z91: 5 | AA91: 2557.06 | AB91: =ROUND(U91-AA91,2) | AC91: FALSE | AD91: =IF(U91="","MISSING_TOTAL",IF(ABS(AB91)<=0.01,"OK","CHECK")) | AE91: =IF(U91="","MISSING",IF(AND(AA91>0,U91/AA91>50),"POSSIBLE_SCALE_ERROR","OK"))
A92: T-2024-P6-0001 | B92: SLE | C92: Chief Executive Officer | D92: Président-directeur général | E92: Rizcallah, Philip | F92: Board meeting | G92: Réunion du conseil d'administration | H92: 45178 | I92: 45184 | J92: St. John's, Newfoundland | K92: St. John's, Terre-Neuve | P92: 815.63 | Q92: 88.23 | R92: 2063.46 | S92: 578.9 | U92: 3546.22 | X92: casdo-ocena | Y92: Accessibility Standards Canada | Normes d’accessibilité Canada | Z92: 7 | AA92: 3546.22 | AB92: =ROUND(U92-AA92,2) | AC92: FALSE | AD92: =IF(U92="","MISSING_TOTAL",IF(ABS(AB92)<=0.01,"OK","CHECK")) | AE92: =IF(U92="","MISSING",IF(AND(AA92>0,U92/AA92>50),"POSSIBLE_SCALE_ERROR","OK"))
A93: T-2024-P6-0002 | B93: SLE | C93: Chief Executive Officer | D93: Président-directeur général | E93: Rizcallah, Philip | F93: Operational activities | G93: Activités opérationels | H93: 45173 | I93: 45178 | J93: NY, NY, USA | K93: NY, NY, EU | P93: 989.77 | Q93: 476.06 | R93: 1536.69 | S93: 940.57 | T93: 0 | U93: 3943.09 | X93: casdo-ocena | Y93: Accessibility Standards Canada | Normes d’accessibilité Canada | Z93: 6 | AA93: 3943.09 | AB93: =ROUND(U93-AA93,2) | AC93: FALSE | AD93: =IF(U93="","MISSING_TOTAL",IF(ABS(AB93)<=0.01,"OK","CHECK")) | AE93: =IF(U93="","MISSING",IF(AND(AA93>0,U93/AA93>50),"POSSIBLE_SCALE_ERROR","OK"))
A94: T-2024-P6-0003 | B94: SLE | C94: Chief Executive Officer | D94: Président-directeur général | E94: Rizcallah, Philip | F94: Operational activities | G94: Activités opérationels | H94: 45151 | I94: 45156 | J94: Calgary, Alberta, Canada | K94: Calgary, Alberta, Canada | P94: 1301.27 | Q94: 371.86 | R94: 1859.32 | S94: 640.9 | T94: 0 | U94: 4173.35 | X94: casdo-ocena | Y94: Accessibility Standards Canada | Normes d’accessibilité Canada | Z94: 6 | AA94: 4173.35 | AB94: =ROUND(U94-AA94,2) | AC94: FALSE | AD94: =IF(U94="","MISSING_TOTAL",IF(ABS(AB94)<=0.01,"OK","CHECK")) | AE94: =IF(U94="","MISSING",IF(AND(AA94>0,U94/AA94>50),"POSSIBLE_SCALE_ERROR","OK"))
A95: T-2024-P7-0001 | B95: SLE | C95: Chief Executive Officer | D95: Président-directeur général | E95: Rizcallah, Philip | F95: Toronto conference | G95: Conférence Toronto | H95: 45196 | I95: 45199 | J95: Toronto, Ontario, Canada | K95: Toronto, Ontario, Canada | P95: 0 | Q95: 365.14 | R95: 952.26 | S95: 470 | T95: 0 | U95: 1787.4 | X95: casdo-ocena | Y95: Accessibility Standards Canada | Normes d’accessibilité Canada | Z95: 4 | AA95: 1787.4 | AB95: =ROUND(U95-AA95,2) | AC95: FALSE | AD95: =IF(U95="","MISSING_TOTAL",IF(ABS(AB95)<=0.01,"OK","CHECK")) | AE95: =IF(U95="","MISSING",IF(AND(AA95>0,U95/AA95>50),"POSSIBLE_SCALE_ERROR","OK"))
A96: T-2024-P7-0002 | B96: SLE | C96: Chief Executive Officer | D96: Président-directeur général | E96: Rizcallah, Philip | F96: Australian International Sports Organization Meeting | G96: Reunions des sports internationales | H96: 45184 | I96: 45192 | J96: Brisbane, Australia | K96: Brisbane, Australie | P96: 11020.28 | Q96: 252.63 | R96: 1266.76 | S96: 1760.64 | T96: 17.47 | U96: 14317.78 | X96: casdo-ocena | Y96: Accessibility Standards Canada | Normes d’accessibilité Canada | Z96: 9 | AA96: 14317.78 | AB96: =ROUND(U96-AA96,2) | AC96: FALSE | AD96: =IF(U96="","MISSING_TOTAL",IF(ABS(AB96)<=0.01,"OK","CHECK")) | AE96: =IF(U96="","MISSING",IF(AND(AA96>0,U96/AA96>50),"POSSIBLE_SCALE_ERROR","OK"))
A97: T-2024-P7-0003 | B97: SLE | C97: Chief Executive Officer | D97: Président-directeur général | E97: Rizcallah, Philip | F97: Red Deer Safety Code Conference | G97: Conférence pour code de sécurité Red Deer | H97: 45217 | I97: 45220 | J97: Edmonton, Alberta, Canada | K97: Edmonton, Alberta, Canada | P97: 840.18 | Q97: 187.1 | R97: 545.61 | S97: 372.9 | T97: 0 | U97: 1945.79 | X97: casdo-ocena | Y97: Accessibility Standards Canada | Normes d’accessibilité Canada | Z97: 4 | AA97: 1945.79 | AB97: =ROUND(U97-AA97,2) | AC97: FALSE | AD97: =IF(U97="","MISSING_TOTAL",IF(ABS(AB97)<=0.01,"OK","CHECK")) | AE97: =IF(U97="","MISSING",IF(AND(AA97>0,U97/AA97>50),"POSSIBLE_SCALE_ERROR","OK"))
A98: T-2024-P7-0004 | B98: SLE | C98: Chief Executive Officer | D98: Président-directeur général | E98: Rizcallah, Philip | F98: Washington Enabling Summit | G98: Conférence pour code de sécurité Red Deer | H98: 45207 | I98: 45212 | J98: Washington DC, United States | K98: Washington DC, Etats Unis | P98: 923.11 | Q98: 106.17 | R98: 2026.24 | S98: 891.24 | T98: 0 | U98: 3946.76 | X98: casdo-ocena | Y98: Accessibility Standards Canada | Normes d’accessibilité Canada | Z98: 6 | AA98: 3946.76 | AB98: =ROUND(U98-AA98,2) | AC98: FALSE | AD98: =IF(U98="","MISSING_TOTAL",IF(ABS(AB98)<=0.01,"OK","CHECK")) | AE98: =IF(U98="","MISSING",IF(AND(AA98>0,U98/AA98>50),"POSSIBLE_SCALE_ERROR","OK"))
A99: T-2024-P7-0005 | B99: SLE | C99: Vice Chair | D99: Vice-Présidente | E99: Reid, Mary | F99: Funeral Estey | G99: Funeral Estey | H99: 45187 | I99: 45188 | J99: Halifax, Nova Scotia, Canada | K99: Halifax, Nouvelle Ecosse, Canada | P99: 1006.13 | Q99: 287.42 | R99: 201.76 | S99: 199.3 | T99: 0 | U99: 1694.61 | X99: casdo-ocena | Y99: Accessibility Standards Canada | Normes d’accessibilité Canada | Z99: 2 | AA99: 1694.61 | AB99: =ROUND(U99-AA99,2) | AC99: FALSE | AD99: =IF(U99="","MISSING_TOTAL",IF(ABS(AB99)<=0.01,"OK","CHECK")) | AE99: =IF(U99="","MISSING",IF(AND(AA99>0,U99/AA99>50),"POSSIBLE_SCALE_ERROR","OK"))
A100: T-2024-P7-0006 | B100: SLE | C100: Vice Chair | D100: Vice-Présidente | E100: Reid, Mary | F100: Board meeting | G100: Réunion du conseil d’administration à St-John | H100: 45209 | I100: 45213 | J100: St. John's, Newfoundland | K100: St. John's, Terre-Neuve | P100: 0 | Q100: 63.66 | R100: 1375.64 | S100: 363.3 | T100: 0 | U100: 1802.6 | X100: casdo-ocena | Y100: Accessibility Standards Canada | Normes d’accessibilité Canada | Z100: 5 | AA100: 1802.6 | AB100: =ROUND(U100-AA100,2) | AC100: FALSE | AD100: =IF(U100="","MISSING_TOTAL",IF(ABS(AB100)<=0.01,"OK","CHECK")) | AE100: =IF(U100="","MISSING",IF(AND(AA100>0,U100/AA100>50),"POSSIBLE_SCALE_ERROR","OK"))
A101: T-2024-P7-0007 | B101: SLE | C101: Board Member | D101: Membre du conseil d'administration | E101: Kory, Earle | F101: Board meeting | G101: Réunion du conseil d’administration à St-John | H101: 45209 | I101: 45214 | J101: St. John's, Newfoundland | K101: St. John's, Terre-Neuve | P101: 1246.38 | Q101: 103.22 | R101: 1719.55 | S101: 504 | T101: 0 | U101: 3573.15 | X101: casdo-ocena | Y101: Accessibility Standards Canada | Normes d’accessibilité Canada | Z101: 6 | AA101: 3573.15 | AB101: =ROUND(U101-AA101,2) | AC101: FALSE | AD101: =IF(U101="","MISSING_TOTAL",IF(ABS(AB101)<=0.01,"OK","CHECK")) | AE101: =IF(U101="","MISSING",IF(AND(AA101>0,U101/AA101>50),"POSSIBLE_SCALE_ERROR","OK"))
A102: T-2024-P7-0008 | B102: SLE | C102: Board Member | D102: Membre du conseil d'administration | E102: Ringaert, Laurie | F102: Board meeting | G102: Réunion du conseil d’administration à St-John | H102: 45176 | I102: 45184 | J102: St. John's, Newfoundland | K102: St. John's, Terre-Neuve | P102: 1125.78 | Q102: 91.39 | R102: 1719.55 | S102: 486.7 | T102: 0 | U102: 3423.42 | X102: casdo-ocena | Y102: Accessibility Standards Canada | Normes d’accessibilité Canada | Z102: 9 | AA102: 3423.42 | AB102: =ROUND(U102-AA102,2) | AC102: FALSE | AD102: =IF(U102="","MISSING_TOTAL",IF(ABS(AB102)<=0.01,"OK","CHECK")) | AE102: =IF(U102="","MISSING",IF(AND(AA102>0,U102/AA102>50),"POSSIBLE_SCALE_ERROR","OK"))
A103: T-2024-P8-0001 | B103: SLE | C103: Chief Executive Officer | D103: Président-directeur général | E103: Rizcallah, Philip | F103: Christchurch Conference | G103: Conférence Christchurch | H103: 45226 | I103: 45233 | J103: Christchurch, New Zealand | K103: Christchurch, Nouvelle Zelande | P103: 7657.55 | Q103: 312.99 | R103: 1308.11 | S103: 1114.93 | T103: 16.23 | U103: 10409.81 | X103: casdo-ocena | Y103: Accessibility Standards Canada | Normes d’accessibilité Canada | Z103: 8 | AA103: 10409.81 | AB103: =ROUND(U103-AA103,2) | AC103: FALSE | AD103: =IF(U103="","MISSING_TOTAL",IF(ABS(AB103)<=0.01,"OK","CHECK")) | AE103: =IF(U103="","MISSING",IF(AND(AA103>0,U103/AA103>50),"POSSIBLE_SCALE_ERROR","OK"))
A104: T-2024-P8-0002 | B104: SLE | C104: Chief Executive Officer | D104: Président-directeur général | E104: Rizcallah, Philip | F104: Intelligentcities Conference | G104: Conférence Intelligentcities | H104: 45222 | I104: 45225 | J104: Toronto, Ontario, Canada | K104: Toronto, Ontario, Canada | P104: 820.66 | Q104: 245.73 | R104: 801.49 | S104: 408.7 | T104: 0 | U104: 2276.58 | X104: casdo-ocena | Y104: Accessibility Standards Canada | Normes d’accessibilité Canada | Z104: 4 | AA104: 2276.58 | AB104: =ROUND(U104-AA104,2) | AC104: FALSE | AD104: =IF(U104="","MISSING_TOTAL",IF(ABS(AB104)<=0.01,"OK","CHECK")) | AE104: =IF(U104="","MISSING",IF(AND(AA104>0,U104/AA104>50),"POSSIBLE_SCALE_ERROR","OK"))
... A153: T-2025-P6-0001 | B153: SLE | C153: Board Member | D153: Membre du conseil d'administration | E153: McLaughlin, Joseph | F153: Stakeholder meetings | G153: Réunions avec parties prenantes | H153: 45528 | I153: 45528 | J153: Victoria, BC | K153: Victoria, CB | P153: 0 | Q153: 302.54 | R153: 0 | S153: 86.75 | T153: 0 | U153: 389.29 | X153: casdo-ocena | Y153: Accessibility Standards Canada | Normes d’accessibilité Canada | Z153: 1 | AA153: 389.29 | AB153: =ROUND(U153-AA153,2) | AC153: FALSE | AD153: =IF(U153="","MISSING_TOTAL",IF(ABS(AB153)<=0.01,"OK","CHECK")) | AE153: =IF(U153="","MISSING",IF(AND(AA153>0,U153/AA153>50),"POSSIBLE_SCALE_ERROR","OK"))
A154: T-2026-P11-00030 | B154: SLE | C154: Chief of the Defence Staff (CDS) | D154: Chef d'état-major de la Defense (CEMD) | E154: Jennie Carignan | F154: General Carignan, Chief of the Defence Staff (CDS) travelled to Yellowknife NWT, Anchorage Alaska, Prestwick Scotland for Holiday troop visit with minister of national defense | G154: Le général Carignan, chef d'état-major de la Défense, s'est rendu à Yellowknife (Territoires du Nord-Ouest), à Anchorage (Alaska) et à Prestwick (Écosse) pour une visite aux troupes pendant les fêtes, en compagnie du ministre de la Défense nationale. | H154: 46007 | I154: 46011 | J154: Yellowknife, NWT | K154: Yellowknife, NWT | L154: Anchorage, Alaska | M154: Anchorage, Alaska | N154: Prestick, Scotland | O154: Prestick, Écosse | R154: 1137.68 | S154: 627 | T154: 0 | U154: 176468 | X154: dnd-mdn | Y154: National Defence | Défense nationale | Z154: 5 | AA154: 1764.68 | AB154: =ROUND(U154-AA154,2) | AC154: FALSE | AD154: =IF(U154="","MISSING_TOTAL",IF(ABS(AB154)<=0.01,"OK","CHECK")) | AE154: =IF(U154="","MISSING",IF(AND(AA154>0,U154/AA154>50),"POSSIBLE_SCALE_ERROR","OK"))
A155: T-2025-P9-0002 | B155: SLE | C155: Chair | D155: Président | E155: Walsh, James | F155: Symposium on Accessibility in International Civil Aviation | G155: Symposium sur l'accessibilité dans l'aviation civile internationale | H155: 45627 | I155: 45631 | J155: Montreal, Quebec, Canada | K155: Montréal, Québec, Canada | P155: 1835.13 | Q155: 151.88 | R155: 638.35 | S155: 423.8 | T155: 12.43 | U155: 3061.59 | X155: casdo-ocena | Y155: Accessibility Standards Canada | Normes d’accessibilité Canada | Z155: 5 | AA155: 3061.59 | AB155: =ROUND(U155-AA155,2) | AC155: FALSE | AD155: =IF(U155="","MISSING_TOTAL",IF(ABS(AB155)<=0.01,"OK","CHECK")) | AE155: =IF(U155="","MISSING",IF(AND(AA155>0,U155/AA155>50),"POSSIBLE_SCALE_ERROR","OK"))
A156: T-2025-P11-0001 | B156: SLE | C156: Chief Executive Officer | D156: Président directeur-général | E156: Zuppa, Dino | F156: Meeting with DAWN | G156: Réunion avec DAWN | H156: 45678 | I156: 45680 | J156: Montreal, Quebec, Canada | K156: Montréal, Québec, Canada | P156: 131.59 | Q156: 43.12 | R156: 566.55 | S156: 387.3 | T156: 36.5 | U156: 1165.06 | X156: casdo-ocena | Y156: Accessibility Standards Canada | Normes d’accessibilité Canada | Z156: 3 | AA156: 1165.06 | AB156: =ROUND(U156-AA156,2) | AC156: FALSE | AD156: =IF(U156="","MISSING_TOTAL",IF(ABS(AB156)<=0.01,"OK","CHECK")) | AE156: =IF(U156="","MISSING",IF(AND(AA156>0,U156/AA156>50),"POSSIBLE_SCALE_ERROR","OK"))
A157: T-2025-P11-0002 | B157: SLE | C157: Board Member | D157: Membre du conseil d'administration | E157: Sutton, Christopher | F157: Harkin Institute Conference | G157: Conférence de l'institut Harkin | H157: 45643 | I157: 45650 | J157: Washington DC, USA | K157: Washington DC, USA | P157: 0 | Q157: 290.96 | R157: 0 | S157: 767.5 | T157: 12.43 | U157: 1070.89 | X157: casdo-ocena | Y157: Accessibility Standards Canada | Normes d’accessibilité Canada | Z157: 8 | AA157: 1070.89 | AB157: =ROUND(U157-AA157,2) | AC157: FALSE | AD157: =IF(U157="","MISSING_TOTAL",IF(ABS(AB157)<=0.01,"OK","CHECK")) | AE157: =IF(U157="","MISSING",IF(AND(AA157>0,U157/AA157>50),"POSSIBLE_SCALE_ERROR","OK"))
A158: T-2025-P12-0001 | B158: SLE | C158: Chief Executive Officer | D158: Président directeur-général | E158: Zuppa, Dino | F158: Training | G158: Formation | H158: 45699 | I158: 45702 | J158: Toronto, Ontario | K158: Toronto, Ontario | P158: 752.32 | Q158: 74 | R158: 786.96 | S158: 431.6 | U158: 2044.88 | X158: casdo-ocena | Y158: Accessibility Standards Canada | Normes d’accessibilité Canada | Z158: 4 | AA158: 2044.88 | AB158: =ROUND(U158-AA158,2) | AC158: FALSE | AD158: =IF(U158="","MISSING_TOTAL",IF(ABS(AB158)<=0.01,"OK","CHECK")) | AE158: =IF(U158="","MISSING",IF(AND(AA158>0,U158/AA158>50),"POSSIBLE_SCALE_ERROR","OK"))
A159: T-2026-P1-0001 | B159: SLE | C159: Chief Executive Officer | D159: Président directeur-général | E159: Zuppa, Dino | F159: International Accessibility Conference | G159: Conférence internationale sur l'accessibilité | H159: 45786 | I159: 45795 | J159: Nice, France | K159: Nice, France | L159: Brussels, Belgium | M159: Bruxelles, Belgique | P159: 2907.37 | Q159: 173.18 | R159: 1926.16 | S159: 2321.95 | T159: 242.22 | U159: 7570.88 | X159: casdo-ocena | Y159: Accessibility Standards Canada | Normes d’accessibilité Canada | Z159: 10 | AA159: 7570.88 | AB159: =ROUND(U159-AA159,2) | AC159: FALSE | AD159: =IF(U159="","MISSING_TOTAL",IF(ABS(AB159)<=0.01,"OK","CHECK")) | AE159: =IF(U159="","MISSING",IF(AND(AA159>0,U159/AA159>50),"POSSIBLE_SCALE_ERROR","OK"))
A160: T-2026-P7-0001 | B160: SLE | C160: Chief Executive Officer | D160: Président-directeur général | E160: Zuppa, Dino | F160: Meetings with concerned parties | G160: Réunions avec parties prenantes | H160: 45915 | I160: 45918 | J160: Toronto, Ontario | K160: Toronto, Ontario | P160: 415.03 | Q160: 57.83 | R160: 1173.33 | S160: 523.2 | T160: 0 | U160: 2169.39 | X160: casdo-ocena | Y160: Accessibility Standards Canada | Normes d’accessibilité Canada | Z160: 4 | AA160: 2169.39 | AB160: =ROUND(U160-AA160,2) | AC160: FALSE | AD160: =IF(U160="","MISSING_TOTAL",IF(ABS(AB160)<=0.01,"OK","CHECK")) | AE160: =IF(U160="","MISSING",IF(AND(AA160>0,U160/AA160>50),"POSSIBLE_SCALE_ERROR","OK"))
A161: T-2026-P7-0002 | B161: SLE | C161: Chief Executive Officer | D161: Président-directeur général | E161: Zuppa, Dino | F161: Meetings with concerned parties | G161: Réunions avec parties prenantes | H161: 45923 | I161: 45924 | J161: Toronto, Ontario | K161: Toronto, Ontario | P161: 336.28 | Q161: 105.2 | R161: 633.54 | S161: 205.8 | T161: 0 | U161: 1280.82 | X161: casdo-ocena | Y161: Accessibility Standards Canada | Normes d’accessibilité Canada | Z161: 2 | AA161: 1280.82 | AB161: =ROUND(U161-AA161,2) | AC161: FALSE | AD161: =IF(U161="","MISSING_TOTAL",IF(ABS(AB161)<=0.01,"OK","CHECK")) | AE161: =IF(U161="","MISSING",IF(AND(AA161>0,U161/AA161>50),"POSSIBLE_SCALE_ERROR","OK"))
A162: T-2026-P7-0003 | B162: SLE | C162: Chief Executive Officer | D162: Président-directeur général | E162: Zuppa, Dino | F162: Meetings with concerned parties | G162: Réunions avec parties prenantes | H162: 45926 | I162: 45927 | J162: Montreal, Quebec, Canada | K162: Montréal, Québec, Canada | P162: 0 | Q162: 281.27 | R162: 260.51 | S162: 233.2 | T162: 28.2 | U162: 803.18 | X162: casdo-ocena | Y162: Accessibility Standards Canada | Normes d’accessibilité Canada | Z162: 2 | AA162: 803.18 | AB162: =ROUND(U162-AA162,2) | AC162: FALSE | AD162: =IF(U162="","MISSING_TOTAL",IF(ABS(AB162)<=0.01,"OK","CHECK")) | AE162: =IF(U162="","MISSING",IF(AND(AA162>0,U162/AA162>50),"POSSIBLE_SCALE_ERROR","OK"))
A163: T-2026-P7-0004 | B163: SLE | C163: Chief Executive Officer | D163: Président-directeur général | E163: Zuppa, Dino | F163: Meetings with concerned parties | G163: Réunions avec parties prenantes | H163: 45940 | I163: 45948 | J163: Halifax, Nova Scotia | K163: Halifax, Nouvelle-Ecosse | P163: 676.19 | Q163: 572.66 | R163: 1682.3 | S163: 759.45 | T163: 0 | U163: 3690.6 | X163: casdo-ocena | Y163: Accessibility Standards Canada | Normes d’accessibilité Canada | Z163: 9 | AA163: 3690.6 | AB163: =ROUND(U163-AA163,2) | AC163: FALSE | AD163: =IF(U163="","MISSING_TOTAL",IF(ABS(AB163)<=0.01,"OK","CHECK")) | AE163: =IF(U163="","MISSING",IF(AND(AA163>0,U163/AA163>50),"POSSIBLE_SCALE_ERROR","OK"))
A164: T-2026-P8-0001 | B164: SLE | C164: Board member | D164: Membre du conseil d'administration | E164: Seysan, Yazdani | F164: 9th anniversary of Canada VRS | G164: Célébration du 9e anniversaire de SRV Canada. | H164: 45927 | I164: 45927 | J164: Montreal, Quebec, Canada | K164: Montréal, Québec, Canada | P164: 0 | Q164: 28 | R164: 0 | S164: 0 | T164: 0 | U164: 28 | X164: casdo-ocena | Y164: Accessibility Standards Canada | Normes d’accessibilité Canada | Z164: 1 | AA164: 28 | AB164: =ROUND(U164-AA164,2) | AC164: FALSE | AD164: =IF(U164="","MISSING_TOTAL",IF(ABS(AB164)<=0.01,"OK","CHECK")) | AE164: =IF(U164="","MISSING",IF(AND(AA164>0,U164/AA164>50),"POSSIBLE_SCALE_ERROR","OK"))
A165: T-2026-P8-0002 | B165: SLE | C165: Board Member | D165: Membre du conseil d'administration | E165: Seysan, Yazdani | F165: COPHAN Event | G165: COPHAN évènement | H165: 45933 | I165: 45935 | J165: Quebec City, Quebec, Canada | K165: Québec, Québec, Canada | P165: 408.83 | Q165: 156.9 | R165: 307.04 | S165: 142.25 | T165: 0 | U165: 1015.02 | X165: casdo-ocena | Y165: Accessibility Standards Canada | Normes d’accessibilité Canada | Z165: 3 | AA165: 1015.02 | AB165: =ROUND(U165-AA165,2) | AC165: FALSE | AD165: =IF(U165="","MISSING_TOTAL",IF(ABS(AB165)<=0.01,"OK","CHECK")) | AE165: =IF(U165="","MISSING",IF(AND(AA165>0,U165/AA165>50),"POSSIBLE_SCALE_ERROR","OK"))
A166: T-2026-P9-0001 | B166: SLE | C166: Board Member | D166: Membre du conseil d'administration | E166: McLaughlin, Joe | F166: Board meeting | G166: Réunion du conseil d'administration | H166: 45984 | I166: 45990 | J166: Ottawa, Ontario | K166: Ottawa, Ontario | P166: 478.83 | Q166: 263.12 | R166: 2242.5 | S166: 838.5 | T166: 0 | U166: 3822.95 | X166: casdo-ocena | Y166: Accessibility Standards Canada | Normes d’accessibilité Canada | Z166: 7 | AA166: 3822.95 | AB166: =ROUND(U166-AA166,2) | AC166: FALSE | AD166: =IF(U166="","MISSING_TOTAL",IF(ABS(AB166)<=0.01,"OK","CHECK")) | AE166: =IF(U166="","MISSING",IF(AND(AA166>0,U166/AA166>50),"POSSIBLE_SCALE_ERROR","OK"))
A167: T-2026-P9-0002 | B167: SLE | C167: Board Member | D167: Membre du conseil d'administration | E167: Haan, Maureen | F167: Board meeting | G167: Réunion du conseil d'administration | H167: 45984 | I167: 45989 | J167: Ottawa, Ontario | K167: Ottawa, Ontario | P167: 604.96 | Q167: 251.62 | R167: 2242.5 | S167: 672.75 | T167: 0 | U167: 3771.83 | X167: casdo-ocena | Y167: Accessibility Standards Canada | Normes d’accessibilité Canada | Z167: 6 | AA167: 3771.83 | AB167: =ROUND(U167-AA167,2) | AC167: FALSE | AD167: =IF(U167="","MISSING_TOTAL",IF(ABS(AB167)<=0.01,"OK","CHECK")) | AE167: =IF(U167="","MISSING",IF(AND(AA167>0,U167/AA167>50),"POSSIBLE_SCALE_ERROR","OK"))
A168: T-2026-P9-0003 | B168: SLE | C168: Board Member | D168: Membre du conseil d'administration | E168: Adair, Bill | F168: Board meeting | G168: Réunion du conseil d'administration | H168: 45984 | I168: 45990 | J168: Ottawa, Ontario | K168: Ottawa, Ontario | P168: 225.2 | Q168: 158.31 | R168: 2242.5 | S168: 809.45 | T168: 0 | U168: 3435.46 | X168: casdo-ocena | Y168: Accessibility Standards Canada | Normes d’accessibilité Canada | Z168: 7 | AA168: 3435.46 | AB168: =ROUND(U168-AA168,2) | AC168: FALSE | AD168: =IF(U168="","MISSING_TOTAL",IF(ABS(AB168)<=0.01,"OK","CHECK")) | AE168: =IF(U168="","MISSING",IF(AND(AA168>0,U168/AA168>50),"POSSIBLE_SCALE_ERROR","OK"))
A169: T-2026-P9-0004 | B169: SLE | C169: Chairperson | D169: Président | E169: Walsh, J. Paul | F169: Board meeting | G169: Réunion du conseil d'administration | H169: 45984 | I169: 45997 | J169: Ottawa, Ontario | K169: Ottawa, Ontario | P169: 742.46 | Q169: 151.88 | R169: 4862.31 | S169: 1496.4 | T169: 402.5 | U169: 7655.55 | X169: casdo-ocena | Y169: Accessibility Standards Canada | Normes d’accessibilité Canada | Z169: 14 | AA169: 7655.55 | AB169: =ROUND(U169-AA169,2) | AC169: FALSE | AD169: =IF(U169="","MISSING_TOTAL",IF(ABS(AB169)<=0.01,"OK","CHECK")) | AE169: =IF(U169="","MISSING",IF(AND(AA169>0,U169/AA169>50),"POSSIBLE_SCALE_ERROR","OK"))
A170: T-2026-P10-0001 | B170: SLE | C170: Chief Executive Officer | D170: Président-directeur général | E170: Zuppa, Dino | F170: Meetings with concerned parties | G170: Réunions avec parties prenantes | H170: 46034 | I170: 46037 | J170: Fredericton, New Brunswick | K170: Fredericton, Nouveau-Brunswick | P170: 630 | Q170: 170.3 | R170: 549.9 | S170: 488.15 | T170: 0 | U170: 1838.35 | X170: casdo-ocena | Y170: Accessibility Standards Canada | Normes d’accessibilité Canada | Z170: 4 | AA170: 1838.35 | AB170: =ROUND(U170-AA170,2) | AC170: FALSE | AD170: =IF(U170="","MISSING_TOTAL",IF(ABS(AB170)<=0.01,"OK","CHECK")) | AE170: =IF(U170="","MISSING",IF(AND(AA170>0,U170/AA170>50),"POSSIBLE_SCALE_ERROR","OK"))
A171: T-2026-P10-0002 | B171: SLE | C171: Board Member | D171: Membre du conseil d'administration | E171: Yazdani-Seysan, Mojgan | F171: Board meeting | G171: Réunion du conseil d'administration | H171: 45985 | I171: 45989 | J171: Ottawa, Ontario | K171: Ottawa, Ontario | P171: 226.54 | Q171: 71.32 | R171: 2242.5 | S171: 689.5 | T171: 0 | U171: 3229.86 | X171: casdo-ocena | Y171: Accessibility Standards Canada | Normes d’accessibilité Canada | Z171: 5 | AA171: 3229.86 | AB171: =ROUND(U171-AA171,2) | AC171: FALSE | AD171: =IF(U171="","MISSING_TOTAL",IF(ABS(AB171)<=0.01,"OK","CHECK")) | AE171: =IF(U171="","MISSING",IF(AND(AA171>0,U171/AA171>50),"POSSIBLE_SCALE_ERROR","OK"))
... A178: T-2027-P3-0001 | B178: SLE | C178: Chief Executive Officer | D178: Président-directeur général | E178: Zuppa, Dino | F178: Conference in Vancouver | G178: Conférence Vancouver | H178: 46168 | I178: 46170 | J178: Vancouver, BC, Canada | K178: Vancouve, CB, Canada | P178: 869.88 | Q178: 176.6 | R178: 1414.36 | S178: 731.25 | T178: 0 | U178: 3192.09 | X178: casdo-ocena | Y178: Accessibility Standards Canada | Normes d’accessibilité Canada | Z178: 3 | AA178: 3192.09 | AB178: =ROUND(U178-AA178,2) | AC178: FALSE | AD178: =IF(U178="","MISSING_TOTAL",IF(ABS(AB178)<=0.01,"OK","CHECK")) | AE178: =IF(U178="","MISSING",IF(AND(AA178>0,U178/AA178>50),"POSSIBLE_SCALE_ERROR","OK"))
A179: T-2017-Q1-00001 | B179: SLE | C179: A/Executive Director and General Counsel, Secretariat to the Public Service Labour Relations and Employment Board | D179: Directrice générale et avocate générale par intérim, Secrétariat de la Commission des relations de travail et de l’emploi dans la fonction publique | E179: Virginia Adamson | F179: Visit Canadian Industrial relation Board's regional offices | G179: Visiter des bureaux régionaux du Conseil canadien des relations industrielles | H179: 42796 | I179: 42797 | J179: Vancouver, BC | K179: Vancouver, BC | P179: 315.13 | Q179: 117 | R179: 126.6 | S179: 97 | U179: 655.73 | X179: atssc-scdata | Y179: Administrative Tribunals Support Service of Canada | Service canadien d'appui aux tribunaux administratifs | Z179: 2 | AA179: 655.73 | AB179: =ROUND(U179-AA179,2) | AC179: FALSE | AD179: =IF(U179="","MISSING_TOTAL",IF(ABS(AB179)<=0.01,"OK","CHECK")) | AE179: =IF(U179="","MISSING",IF(AND(AA179>0,U179/AA179>50),"POSSIBLE_SCALE_ERROR","OK"))
A180: T-2017-Q1-00002 | B180: SLE | C180: A/Executive Director and General Counsel, Secretariat to the Public Service Labour Relations and Employment Board | D180: Directrice générale et avocate générale par intérim, Secrétariat de la Commission des relations de travail et de l’emploi dans la fonction publique | E180: Virginia Adamson | F180: To attend a meeting of the Association of Labour Relations Agencies | G180: Participer à une rencontre de la Association of Labour Relations Agencies | H180: 42797 | I180: 42800 | J180: Portland, Oregon | K180: Portland, Oregon | P180: 960.79 | Q180: 165.3 | R180: 553.91 | S180: 379.17 | U180: 2059.17 | X180: atssc-scdata | Y180: Administrative Tribunals Support Service of Canada | Service canadien d'appui aux tribunaux administratifs | Z180: 4 | AA180: 2059.17 | AB180: =ROUND(U180-AA180,2) | AC180: FALSE | AD180: =IF(U180="","MISSING_TOTAL",IF(ABS(AB180)<=0.01,"OK","CHECK")) | AE180: =IF(U180="","MISSING",IF(AND(AA180>0,U180/AA180>50),"POSSIBLE_SCALE_ERROR","OK"))
A181: T-2017-Q1-00003 | B181: SLE | C181: A/Chairperson, Canadian International Trade Tribunal | D181: Président par intérim, Tribunal Canadien du commerce extérieur | E181: Bédard, Jean | F181: Attend the 38th Annual International Trade Update | G181: Participer à la 38e International Trade Update annuelle | H181: 42802 | I181: 42804 | J181: Washington, DC | K181: Washington, DC | P181: 609.66 | Q181: 73.61 | R181: 1071.85 | S181: 346.61 | U181: 2101.73 | X181: atssc-scdata | Y181: Administrative Tribunals Support Service of Canada | Service canadien d'appui aux tribunaux administratifs | Z181: 3 | AA181: 2101.73 | AB181: =ROUND(U181-AA181,2) | AC181: FALSE | AD181: =IF(U181="","MISSING_TOTAL",IF(ABS(AB181)<=0.01,"OK","CHECK")) | AE181: =IF(U181="","MISSING",IF(AND(AA181>0,U181/AA181>50),"POSSIBLE_SCALE_ERROR","OK"))
A182: T-2017-Q1-00004 | B182: SLE | C182: A/Chairperson, Canadian International Trade Tribunal | D182: Président par intérim, Tribunal Canadien du commerce extérieur | E182: Bédard, Jean | F182: Attend the Chairperson's forum in Ottawa | G182: Assister au forum de la présidente à Ottawa | H182: 42818 | I182: 42818 | J182: Ottawa, ON | K182: Ottawa, ON | T182: 14 | U182: 14 | X182: atssc-scdata | Y182: Administrative Tribunals Support Service of Canada | Service canadien d'appui aux tribunaux administratifs | Z182: 1 | AA182: 14 | AB182: =ROUND(U182-AA182,2) | AC182: FALSE | AD182: =IF(U182="","MISSING_TOTAL",IF(ABS(AB182)<=0.01,"OK","CHECK")) | AE182: =IF(U182="","MISSING",IF(AND(AA182>0,U182/AA182>50),"POSSIBLE_SCALE_ERROR","OK"))
A183: T-2017-Q1-00005 | B183: SLE | C183: Executive Director, Secretariat to the Canadian Cultural Property Export Review Board | D183: Directrice exécutive, Secrétariat de la Commission canadienne d’examen des exportations de biens culturels | E183: Bishop, Delphine | F183: Attend a meeting with Executive Directors | G183: Participer à une rencontre avec les directeurs exécutifs | H183: 42740 | I183: 42740 | J183: Ottawa, ON | K183: Ottawa, ON | T183: 17.5 | U183: 17.5 | X183: atssc-scdata | Y183: Administrative Tribunals Support Service of Canada | Service canadien d'appui aux tribunaux administratifs | Z183: 1 | AA183: 17.5 | AB183: =ROUND(U183-AA183,2) | AC183: FALSE | AD183: =IF(U183="","MISSING_TOTAL",IF(ABS(AB183)<=0.01,"OK","CHECK")) | AE183: =IF(U183="","MISSING",IF(AND(AA183>0,U183/AA183>50),"POSSIBLE_SCALE_ERROR","OK"))
A184: T-2017-Q1-00006 | B184: SLE | C184: Executive Director, Secretariat to the Canadian Cultural Property Export Review Board | D184: Directrice exécutive, Secrétariat de la Commission canadienne d’examen des exportations de biens culturels | E184: Bishop, Delphine | F184: Attend a meeting with Executive Directors | G184: Participer à une rencontre avec les directeurs exécutifs | H184: 42746 | I184: 42746 | J184: Ottawa, ON | K184: Ottawa, ON | T184: 20 | U184: 20 | X184: atssc-scdata | Y184: Administrative Tribunals Support Service of Canada | Service canadien d'appui aux tribunaux administratifs | Z184: 1 | AA184: 20 | AB184: =ROUND(U184-AA184,2) | AC184: FALSE | AD184: =IF(U184="","MISSING_TOTAL",IF(ABS(AB184)<=0.01,"OK","CHECK")) | AE184: =IF(U184="","MISSING",IF(AND(AA184>0,U184/AA184>50),"POSSIBLE_SCALE_ERROR","OK"))
A185: T-2017-Q1-00007 | B185: SLE | C185: Executive Director, Secretariat to the Canadian Cultural Property Export Review Board | D185: Directrice exécutive, Secrétariat de la Commission canadienne d’examen des exportations de biens culturels | E185: Bishop, Delphine | F185: Attend a meeting with Executive Directors | G185: Participer à une rencontre avec les directeurs exécutifs | H185: 42783 | I185: 42783 | J185: Ottawa, ON | K185: Ottawa, ON | T185: 15 | U185: 15 | X185: atssc-scdata | Y185: Administrative Tribunals Support Service of Canada | Service canadien d'appui aux tribunaux administratifs | Z185: 1 | AA185: 15 | AB185: =ROUND(U185-AA185,2) | AC185: FALSE | AD185: =IF(U185="","MISSING_TOTAL",IF(ABS(AB185)<=0.01,"OK","CHECK")) | AE185: =IF(U185="","MISSING",IF(AND(AA185>0,U185/AA185>50),"POSSIBLE_SCALE_ERROR","OK"))
A186: T-2017-Q1-00008 | B186: SLE | C186: Executive Director, Secretariat to the Canadian Cultural Property Export Review Board | D186: Directrice exécutive, Secrétariat de la Commission canadienne d’examen des exportations de biens culturels | E186: Bishop, Delphine | F186: Attend a meeting with the Senior Project manager | G186: Participer à une rencontre avec la chef de l'initiative stratégique | H186: 42800 | I186: 42800 | J186: Ottawa, ON | K186: Ottawa, ON | T186: 11 | U186: 11 | X186: atssc-scdata | Y186: Administrative Tribunals Support Service of Canada | Service canadien d'appui aux tribunaux administratifs | Z186: 1 | AA186: 11 | AB186: =ROUND(U186-AA186,2) | AC186: FALSE | AD186: =IF(U186="","MISSING_TOTAL",IF(ABS(AB186)<=0.01,"OK","CHECK")) | AE186: =IF(U186="","MISSING",IF(AND(AA186>0,U186/AA186>50),"POSSIBLE_SCALE_ERROR","OK"))
A187: T-2017-Q1-00009 | B187: SLE | C187: Executive Director, Secretariat to the Canadian Cultural Property Export Review Board | D187: Directrice exécutive, Secrétariat de la Commission canadienne d’examen des exportations de biens culturels | E187: Bishop, Delphine | F187: Attend a Budget Allocation meeting | G187: Participer à une rencontre sur l'allocation budgétaire | H187: 42807 | I187: 42807 | J187: Ottawa, ON | K187: Ottawa, ON | T187: 12.5 | U187: 12.5 | X187: atssc-scdata | Y187: Administrative Tribunals Support Service of Canada | Service canadien d'appui aux tribunaux administratifs | Z187: 1 | AA187: 12.5 | AB187: =ROUND(U187-AA187,2) | AC187: FALSE | AD187: =IF(U187="","MISSING_TOTAL",IF(ABS(AB187)<=0.01,"OK","CHECK")) | AE187: =IF(U187="","MISSING",IF(AND(AA187>0,U187/AA187>50),"POSSIBLE_SCALE_ERROR","OK"))
A188: T-2017-Q1-00010 | B188: SLE | C188: Executive Director, Secretariat to the Canadian Cultural Property Export Review Board | D188: Directrice exécutive, Secrétariat de la Commission canadienne d’examen des exportations de biens culturels | E188: Bishop, Delphine | F188: Attend the CCPERB Board meeting | G188: Assister à la réunion des membres de la Commission CCEEBC | H188: 42808 | I188: 42811 | J188: Ottawa, ON | K188: Ottawa, ON | T188: 80 | U188: 80 | X188: atssc-scdata | Y188: Administrative Tribunals Support Service of Canada | Service canadien d'appui aux tribunaux administratifs | Z188: 4 | AA188: 80 | AB188: =ROUND(U188-AA188,2) | AC188: FALSE | AD188: =IF(U188="","MISSING_TOTAL",IF(ABS(AB188)<=0.01,"OK","CHECK")) | AE188: =IF(U188="","MISSING",IF(AND(AA188>0,U188/AA188>50),"POSSIBLE_SCALE_ERROR","OK"))
A189: T-2017-Q1-00011 | B189: SLE | C189: Executive Director, Secretariat to the Canadian Cultural Property Export Review Board | D189: Directrice exécutive, Secrétariat de la Commission canadienne d’examen des exportations de biens culturels | E189: Bishop, Delphine | F189: Attend the Classification Committee meeting | G189: Participer à une rencontre du comité de la classification | H189: 42816 | I189: 42816 | J189: Ottawa, ON | K189: Ottawa, ON | T189: 20 | U189: 20 | X189: atssc-scdata | Y189: Administrative Tribunals Support Service of Canada | Service canadien d'appui aux tribunaux administratifs | Z189: 1 | AA189: 20 | AB189: =ROUND(U189-AA189,2) | AC189: FALSE | AD189: =IF(U189="","MISSING_TOTAL",IF(ABS(AB189)<=0.01,"OK","CHECK")) | AE189: =IF(U189="","MISSING",IF(AND(AA189>0,U189/AA189>50),"POSSIBLE_SCALE_ERROR","OK"))
A190: T-2017-Q1-00012 | B190: SLE | C190: Executive Director, Secretariat to the Canadian Cultural Property Export Review Board | D190: Directrice exécutive, Secrétariat de la Commission canadienne d’examen des exportations de biens culturels | E190: Bishop, Delphine | F190: Attend a meeting with Executive Directors | G190: Participer à une rencontre avec les directeurs exécutifs | H190: 42823 | I190: 42823 | J190: Ottawa, ON | K190: Ottawa, ON | T190: 20 | U190: 20 | X190: atssc-scdata | Y190: Administrative Tribunals Support Service of Canada | Service canadien d'appui aux tribunaux administratifs | Z190: 1 | AA190: 20 | AB190: =ROUND(U190-AA190,2) | AC190: FALSE | AD190: =IF(U190="","MISSING_TOTAL",IF(ABS(AB190)<=0.01,"OK","CHECK")) | AE190: =IF(U190="","MISSING",IF(AND(AA190>0,U190/AA190>50),"POSSIBLE_SCALE_ERROR","OK"))
A191: T-2017-Q1-00013 | B191: SLE | C191: Chairperson, Canada Industrial Relations Board | D191: Présidente, Conseil canadien des relations industrielles | E191: Ginette Brazeau | F191: Attend a Regional Directors Meeting | G191: Participer à une rencontre des directeurs régionaux | H191: 42794 | I191: 42796 | J191: Vancouver, BC | K191: Vancouver, BC | P191: 340.88 | Q191: 40 | R191: 340.76 | S191: 257.8 | U191: 979.44 | X191: atssc-scdata | Y191: Administrative Tribunals Support Service of Canada | Service canadien d'appui aux tribunaux administratifs | Z191: 3 | AA191: 979.44 | AB191: =ROUND(U191-AA191,2) | AC191: FALSE | AD191: =IF(U191="","MISSING_TOTAL",IF(ABS(AB191)<=0.01,"OK","CHECK")) | AE191: =IF(U191="","MISSING",IF(AND(AA191>0,U191/AA191>50),"POSSIBLE_SCALE_ERROR","OK"))
A192: T-2017-Q1-00014 | B192: SLE | C192: Chairperson, Canada Industrial Relations Board | D192: Présidente, Conseil canadien des relations industrielles | E192: Ginette Brazeau | F192: To attend the Association of Labour Relations Agencies meeting | G192: Participer à une rencontre de la Association of Labour Relations Agencies | H192: 42797 | I192: 42799 | J192: Portland, Oregon | K192: Portland, Oregon | P192: 566.46 | Q192: 38.05 | R192: 852.08 | S192: 260.32 | T192: 120 | U192: 1836.91 | X192: atssc-scdata | Y192: Administrative Tribunals Support Service of Canada | Service canadien d'appui aux tribunaux administratifs | Z192: 3 | AA192: 1836.91 | AB192: =ROUND(U192-AA192,2) | AC192: FALSE | AD192: =IF(U192="","MISSING_TOTAL",IF(ABS(AB192)<=0.01,"OK","CHECK")) | AE192: =IF(U192="","MISSING",IF(AND(AA192>0,U192/AA192>50),"POSSIBLE_SCALE_ERROR","OK"))
A193: T-2017-Q1-00015 | B193: SLE | C193: Chairperson, Canada Industrial Relations Board | D193: Présidente, Conseil canadien des relations industrielles | E193: Ginette Brazeau | F193: Hearing file # 31022-C | G193: Dossier d'audience no 31022-C | H193: 42801 | I193: 42804 | J193: Toronto, ON | K193: Toronto, ON | P193: 380.87 | Q193: 25 | R193: 611.36 | S193: 291.35 | T193: 131.16 | U193: 1439.74 | X193: atssc-scdata | Y193: Administrative Tribunals Support Service of Canada | Service canadien d'appui aux tribunaux administratifs | Z193: 4 | AA193: 1439.74 | AB193: =ROUND(U193-AA193,2) | AC193: FALSE | AD193: =IF(U193="","MISSING_TOTAL",IF(ABS(AB193)<=0.01,"OK","CHECK")) | AE193: =IF(U193="","MISSING",IF(AND(AA193>0,U193/AA193>50),"POSSIBLE_SCALE_ERROR","OK"))
A194: T-2017-Q1-00016 | B194: SLE | C194: Chairperson, Canada Industrial Relations Board | D194: Présidente, Conseil canadien des relations industrielles | E194: Ginette Brazeau | F194: Hearing file # 31364-C | G194: Dossier d'audience no 31364-C | H194: 42822 | I194: 42825 | J194: Halifax, NS | K194: Halifax, NS | P194: 680.48 | Q194: 135 | R194: 612.3 | S194: 308.6 | T194: 92 | U194: 1828.38 | X194: atssc-scdata | Y194: Administrative Tribunals Support Service of Canada | Service canadien d'appui aux tribunaux administratifs | Z194: 4 | AA194: 1828.38 | AB194: =ROUND(U194-AA194,2) | AC194: FALSE | AD194: =IF(U194="","MISSING_TOTAL",IF(ABS(AB194)<=0.01,"OK","CHECK")) | AE194: =IF(U194="","MISSING",IF(AND(AA194>0,U194/AA194>50),"POSSIBLE_SCALE_ERROR","OK"))
...

Sheet Data_Quality_Summary
A1: Data Quality Metric | B1: COUNT
A2: Total Records | B2: =COUNTA(Cleaned_Data!A2:A152901)
A3: Missing Airfare | B3: =COUNTBLANK(Cleaned_Data!P2:P152901)
A4: Missing Other Transport | B4: =COUNTBLANK(Cleaned_Data!Q2:Q152901)
A5: Missing Lodging | B5: =COUNTBLANK(Cleaned_Data!R2:R152901)
A6: Missing Meals | B6: =COUNTBLANK(Cleaned_Data!S2:S152901)
A7: Missing Other Expenses | B7: =COUNTBLANK(Cleaned_Data!T2:T152901)
A8: Missing Total | B8: =COUNTBLANK(Cleaned_Data!U2:U152901)
A9: Duplicate Records | B9: =COUNTIF(Cleaned_Data!AC2:AC152901,TRUE)
A10: Possible Scale Errors | B10: =COUNTIF(Cleaned_Data!AE2:AE152901,"POSSIBLE_SCALE_ERROR")

Sheet Analysis
A1: KPI | B1: Value | D1: Year | E1: Total Expense | G1: Department | H1: Total Expense | J1: Destination | K1: Total Expense | M1: Expense Category | N1: Total Expense
A2: Total Travel Records | B2: =COUNTA(Cleaned_Data!A2:A152901) | D2: =IFERROR(__xludf.DUMMYFUNCTION("QUERY({ARRAYFORMULA(YEAR(Cleaned_Data!H2:H22699)),Cleaned_Data!U2:U22699},""select Col1, sum(Col2) where Col1 is not null and Col2 is not null group by Col1 order by Col1"",0)"),"") | E2: =IFERROR(__xludf.DUMMYFUNCTION("""COMPUTED_VALUE"""),"sum ") | G2: =IFERROR(__xludf.DUMMYFUNCTION("QUERY({Cleaned_Data!Y2:Y22699,Cleaned_Data!U2:U22699},""select Col1, sum(Col2) where Col1 is not null and Col2 is not null group by Col1 order by sum(Col2) desc label Col1 'Department', sum(Col2) 'Total Expense'"",0)"),"Department") | H2: =IFERROR(__xludf.DUMMYFUNCTION("""COMPUTED_VALUE"""),"Total Expense") | J2: =IFERROR(__xludf.DUMMYFUNCTION("QUERY({Cleaned_Data!J2:J22699,Cleaned_Data!U2:U22699},""select Col1, sum(Col2) where Col1 is not null and Col2 is not null group by Col1 order by sum(Col2) desc label Col1 'Destination', sum(Col2) 'Total Expense'"",0)"),"Destination") | K2: =IFERROR(__xludf.DUMMYFUNCTION("""COMPUTED_VALUE"""),"Total Expense") | M2: {="Airfare"} | N2: Airfare
A3: Total Travel Expense | B3: =SUM(Cleaned_Data!U2:U152901) | D3: =IFERROR(__xludf.DUMMYFUNCTION("""COMPUTED_VALUE"""),1999) | E3: =IFERROR(__xludf.DUMMYFUNCTION("""COMPUTED_VALUE"""),0) | G3: =IFERROR(__xludf.DUMMYFUNCTION("""COMPUTED_VALUE"""),"Global Affairs Canada | Affaires mondiales Canada") | H3: =IFERROR(__xludf.DUMMYFUNCTION("""COMPUTED_VALUE"""),63848705.3699997) | J3: =IFERROR(__xludf.DUMMYFUNCTION("""COMPUTED_VALUE"""),"Toronto, Ontario, Canada") | K3: =IFERROR(__xludf.DUMMYFUNCTION("""COMPUTED_VALUE"""),13178794.05) | M3: Airfare | N3: Airfare
A4: Average Travel Expense | B4: =AVERAGE(Cleaned_Data!U2:U22699) | D4: =IFERROR(__xludf.DUMMYFUNCTION("""COMPUTED_VALUE"""),2003) | E4: =IFERROR(__xludf.DUMMYFUNCTION("""COMPUTED_VALUE"""),67137.58) | G4: =IFERROR(__xludf.DUMMYFUNCTION("""COMPUTED_VALUE"""),"Employment and Social Development Canada | Emploi et Développement social Canada") | H4: =IFERROR(__xludf.DUMMYFUNCTION("""COMPUTED_VALUE"""),23424267.77) | J4: =IFERROR(__xludf.DUMMYFUNCTION("""COMPUTED_VALUE"""),"Ottawa, Ontario, Canada") | K4: =IFERROR(__xludf.DUMMYFUNCTION("""COMPUTED_VALUE"""),13173293.9) | M4: Airfare | N4: Airfare
A5: Maximum Travel Expense | B5: =MAX(Cleaned_Data!U2:U22699) | D5: =IFERROR(__xludf.DUMMYFUNCTION("""COMPUTED_VALUE"""),2004) | E5: =IFERROR(__xludf.DUMMYFUNCTION("""COMPUTED_VALUE"""),4540905.82) | G5: =IFERROR(__xludf.DUMMYFUNCTION("""COMPUTED_VALUE"""),"National Defence | Défense nationale") | H5: =IFERROR(__xludf.DUMMYFUNCTION("""COMPUTED_VALUE"""),22382126.4799999) | J5: =IFERROR(__xludf.DUMMYFUNCTION("""COMPUTED_VALUE"""),"Vancouver, British Columbia, Canada") | K5: =IFERROR(__xludf.DUMMYFUNCTION("""COMPUTED_VALUE"""),6812316.72) | M5: Airfare | N5: Airfare
A6: Minimum Travel Expense | B6: =MIN(Cleaned_Data!U2:U22699) | D6: =IFERROR(__xludf.DUMMYFUNCTION("""COMPUTED_VALUE"""),2005) | E6: =IFERROR(__xludf.DUMMYFUNCTION("""COMPUTED_VALUE"""),5272765.43) | G6: =IFERROR(__xludf.DUMMYFUNCTION("""COMPUTED_VALUE"""),"Department of Finance Canada | Ministère des Finances Canada") | H6: =IFERROR(__xludf.DUMMYFUNCTION("""COMPUTED_VALUE"""),18165295.0799999) | J6: =IFERROR(__xludf.DUMMYFUNCTION("""COMPUTED_VALUE"""),"Paris, France") | K6: =IFERROR(__xludf.DUMMYFUNCTION("""COMPUTED_VALUE"""),6136294.43) | M6: Airfare | N6: Airfare
A7: Total Airfare | B7: =SUM(Cleaned_Data!P2:P22699) | D7: =IFERROR(__xludf.DUMMYFUNCTION("""COMPUTED_VALUE"""),2006) | E7: =IFERROR(__xludf.DUMMYFUNCTION("""COMPUTED_VALUE"""),4938243.25000001) | G7: =IFERROR(__xludf.DUMMYFUNCTION("""COMPUTED_VALUE"""),"Innovation, Science and Economic Development Canada | Innovation, Sciences et Développement économique Canada") | H7: =IFERROR(__xludf.DUMMYFUNCTION("""COMPUTED_VALUE"""),12558238.84) | J7: =IFERROR(__xludf.DUMMYFUNCTION("""COMPUTED_VALUE"""),"Montreal, Quebec, Canada") | K7: =IFERROR(__xludf.DUMMYFUNCTION("""COMPUTED_VALUE"""),5001970.51000001)
A8: Total Other Transport | B8: =SUM(Cleaned_Data!Q2:Q22699) | D8: =IFERROR(__xludf.DUMMYFUNCTION("""COMPUTED_VALUE"""),2007) | E8: =IFERROR(__xludf.DUMMYFUNCTION("""COMPUTED_VALUE"""),6196268.95) | G8: =IFERROR(__xludf.DUMMYFUNCTION("""COMPUTED_VALUE"""),"Privy Council Office | Bureau du Conseil privé") | H8: =IFERROR(__xludf.DUMMYFUNCTION("""COMPUTED_VALUE"""),10296318.65) | J8: =IFERROR(__xludf.DUMMYFUNCTION("""COMPUTED_VALUE"""),"Ottawa, Ontario") | K8: =IFERROR(__xludf.DUMMYFUNCTION("""COMPUTED_VALUE"""),4531891.71)
A9: Total Lodging | B9: =SUM(Cleaned_Data!R2:R22699) | D9: =IFERROR(__xludf.DUMMYFUNCTION("""COMPUTED_VALUE"""),2008) | E9: =IFERROR(__xludf.DUMMYFUNCTION("""COMPUTED_VALUE"""),6073208.93) | G9: =IFERROR(__xludf.DUMMYFUNCTION("""COMPUTED_VALUE"""),"Natural Resources Canada | Ressources naturelles Canada") | H9: =IFERROR(__xludf.DUMMYFUNCTION("""COMPUTED_VALUE"""),8618916.91) | J9: =IFERROR(__xludf.DUMMYFUNCTION("""COMPUTED_VALUE"""),"Ottawa, ON") | K9: =IFERROR(__xludf.DUMMYFUNCTION("""COMPUTED_VALUE"""),4267074.72999999)
A10: Total Meals | B10: =SUM(Cleaned_Data!S2:S22699) | D10: =IFERROR(__xludf.DUMMYFUNCTION("""COMPUTED_VALUE"""),2009) | E10: =IFERROR(__xludf.DUMMYFUNCTION("""COMPUTED_VALUE"""),7694189.17) | G10: =IFERROR(__xludf.DUMMYFUNCTION("""COMPUTED_VALUE"""),"Canada Revenue Agency | Agence du revenu du Canada") | H10: =IFERROR(__xludf.DUMMYFUNCTION("""COMPUTED_VALUE"""),7277975.67) | J10: =IFERROR(__xludf.DUMMYFUNCTION("""COMPUTED_VALUE"""),"Toronto, ON") | K10: =IFERROR(__xludf.DUMMYFUNCTION("""COMPUTED_VALUE"""),3927901.39999999)
A11: Total Other Expenses | B11: =SUM(Cleaned_Data!T2:T22699) | D11: =IFERROR(__xludf.DUMMYFUNCTION("""COMPUTED_VALUE"""),2010) | E11: =IFERROR(__xludf.DUMMYFUNCTION("""COMPUTED_VALUE"""),7828816.55) | G11: =IFERROR(__xludf.DUMMYFUNCTION("""COMPUTED_VALUE"""),"Canadian Heritage | Patrimoine canadien") | H11: =IFERROR(__xludf.DUMMYFUNCTION("""COMPUTED_VALUE"""),7084876.46) | J11: =IFERROR(__xludf.DUMMYFUNCTION("""COMPUTED_VALUE"""),"Calgary, Alberta, Canada") | K11: =IFERROR(__xludf.DUMMYFUNCTION("""COMPUTED_VALUE"""),3506254.52999999)
A12: Total Travel Days | B12: =SUM(Cleaned_Data!Z2:Z22699) | D12: =IFERROR(__xludf.DUMMYFUNCTION("""COMPUTED_VALUE"""),2011) | E12: =IFERROR(__xludf.DUMMYFUNCTION("""COMPUTED_VALUE"""),8151691.18) | G12: =IFERROR(__xludf.DUMMYFUNCTION("""COMPUTED_VALUE"""),"Transport Canada | Transports Canada") | H12: =IFERROR(__xludf.DUMMYFUNCTION("""COMPUTED_VALUE"""),6703932.18) | J12: =IFERROR(__xludf.DUMMYFUNCTION("""COMPUTED_VALUE"""),"Halifax, Nova Scotia, Canada") | K12: =IFERROR(__xludf.DUMMYFUNCTION("""COMPUTED_VALUE"""),3328456.59)
A13: Average Travel Days | B13: =AVERAGE(Cleaned_Data!Z2:Z22699) | D13: =IFERROR(__xludf.DUMMYFUNCTION("""COMPUTED_VALUE"""),2012) | E13: =IFERROR(__xludf.DUMMYFUNCTION("""COMPUTED_VALUE"""),8875390.37000001) | G13: =IFERROR(__xludf.DUMMYFUNCTION("""COMPUTED_VALUE"""),"Veterans Affairs Canada | Anciens Combattants Canada") | H13: =IFERROR(__xludf.DUMMYFUNCTION("""COMPUTED_VALUE"""),6294153.4) | J13: =IFERROR(__xludf.DUMMYFUNCTION("""COMPUTED_VALUE"""),"London, United Kingdom") | K13: =IFERROR(__xludf.DUMMYFUNCTION("""COMPUTED_VALUE"""),3265268.56)
A14: Maximum Travel Days | B14: =MAX(Cleaned_Data!Z2:Z22699) | D14: =IFERROR(__xludf.DUMMYFUNCTION("""COMPUTED_VALUE"""),2013) | E14: =IFERROR(__xludf.DUMMYFUNCTION("""COMPUTED_VALUE"""),8552043.13999999) | G14: =IFERROR(__xludf.DUMMYFUNCTION("""COMPUTED_VALUE"""),"Environment and Climate Change Canada | Environnement et Changement climatique Canada") | H14: =IFERROR(__xludf.DUMMYFUNCTION("""COMPUTED_VALUE"""),5863791.55000001) | J14: =IFERROR(__xludf.DUMMYFUNCTION("""COMPUTED_VALUE"""),"Geneva, Switzerland") | K14: =IFERROR(__xludf.DUMMYFUNCTION("""COMPUTED_VALUE"""),3115396.61)
A15: Records with Missing Total | B15: =COUNTIFS(Cleaned_Data!A2:A22699,"<>",Cleaned_Data!U2:U22699,"") | D15: =IFERROR(__xludf.DUMMYFUNCTION("""COMPUTED_VALUE"""),2014) | E15: =IFERROR(__xludf.DUMMYFUNCTION("""COMPUTED_VALUE"""),9872197.84999997) | G15: =IFERROR(__xludf.DUMMYFUNCTION("""COMPUTED_VALUE"""),"Immigration, Refugees and Citizenship Canada | Immigration, Réfugiés et Citoyenneté Canada") | H15: =IFERROR(__xludf.DUMMYFUNCTION("""COMPUTED_VALUE"""),5643369.53999999) | J15: =IFERROR(__xludf.DUMMYFUNCTION("""COMPUTED_VALUE"""),"Tokyo, Japan") | K15: =IFERROR(__xludf.DUMMYFUNCTION("""COMPUTED_VALUE"""),2898174.22999999)
A16: Records with Missing Airfare | B16: =COUNTIFS(Cleaned_Data!A2:A22699,"<>",Cleaned_Data!P2:P22699,"") | D16: =IFERROR(__xludf.DUMMYFUNCTION("""COMPUTED_VALUE"""),2015) | E16: =IFERROR(__xludf.DUMMYFUNCTION("""COMPUTED_VALUE"""),9543954.88999999) | G16: =IFERROR(__xludf.DUMMYFUNCTION("""COMPUTED_VALUE"""),"National Research Council Canada | Conseil national de recherches Canada") | H16: =IFERROR(__xludf.DUMMYFUNCTION("""COMPUTED_VALUE"""),5333036.58) | J16: =IFERROR(__xludf.DUMMYFUNCTION("""COMPUTED_VALUE"""),"Toronto, Ontario") | K16: =IFERROR(__xludf.DUMMYFUNCTION("""COMPUTED_VALUE"""),2777159.74)
A17: Records with Missing Lodging | B17: =COUNTIFS(Cleaned_Data!A2:A22699,"<>",Cleaned_Data!R2:R22699,"") | D17: =IFERROR(__xludf.DUMMYFUNCTION("""COMPUTED_VALUE"""),2016) | E17: =IFERROR(__xludf.DUMMYFUNCTION("""COMPUTED_VALUE"""),13455707.96) | G17: =IFERROR(__xludf.DUMMYFUNCTION("""COMPUTED_VALUE"""),"Parks Canada | Parcs Canada") | H17: =IFERROR(__xludf.DUMMYFUNCTION("""COMPUTED_VALUE"""),5234603.90999999) | J17: =IFERROR(__xludf.DUMMYFUNCTION("""COMPUTED_VALUE"""),"Winnipeg, Manitoba, Canada") | K17: =IFERROR(__xludf.DUMMYFUNCTION("""COMPUTED_VALUE"""),2652310.01)
A18: Records with Missing Meals | B18: =COUNTIFS(Cleaned_Data!A2:A22699,"<>",Cleaned_Data!S2:S22699,"") | D18: =IFERROR(__xludf.DUMMYFUNCTION("""COMPUTED_VALUE"""),2017) | E18: =IFERROR(__xludf.DUMMYFUNCTION("""COMPUTED_VALUE"""),20512941.39) | G18: =IFERROR(__xludf.DUMMYFUNCTION("""COMPUTED_VALUE"""),"Fisheries and Oceans Canada | Pêches et Océans Canada") | H18: =IFERROR(__xludf.DUMMYFUNCTION("""COMPUTED_VALUE"""),5036499.06999999) | J18: =IFERROR(__xludf.DUMMYFUNCTION("""COMPUTED_VALUE"""),"Brussels, Belgium") | K18: =IFERROR(__xludf.DUMMYFUNCTION("""COMPUTED_VALUE"""),2632637.81999999)
A19: Records with Missing Other Expenses | B19: =COUNTIFS(Cleaned_Data!A2:A22699,"<>",Cleaned_Data!T2:T22699,"") | D19: =IFERROR(__xludf.DUMMYFUNCTION("""COMPUTED_VALUE"""),2018) | E19: =IFERROR(__xludf.DUMMYFUNCTION("""COMPUTED_VALUE"""),24835584.7699999) | G19: =IFERROR(__xludf.DUMMYFUNCTION("""COMPUTED_VALUE"""),"Farm Credit Canada | Financement agricole Canada") | H19: =IFERROR(__xludf.DUMMYFUNCTION("""COMPUTED_VALUE"""),5005716.26999999) | J19: =IFERROR(__xludf.DUMMYFUNCTION("""COMPUTED_VALUE"""),"Regina, Saskatchewan, Canada") | K19: =IFERROR(__xludf.DUMMYFUNCTION("""COMPUTED_VALUE"""),2285521.33)
A20: Duplicate Records | B20: =COUNTIF(Cleaned_Data!AC2:AC22699,TRUE) | D20: =IFERROR(__xludf.DUMMYFUNCTION("""COMPUTED_VALUE"""),2019) | E20: =IFERROR(__xludf.DUMMYFUNCTION("""COMPUTED_VALUE"""),23693199.4099999) | G20: =IFERROR(__xludf.DUMMYFUNCTION("""COMPUTED_VALUE"""),"Agriculture and Agri-Food Canada | Agriculture et Agroalimentaire Canada") | H20: =IFERROR(__xludf.DUMMYFUNCTION("""COMPUTED_VALUE"""),4470756.54) | J20: =IFERROR(__xludf.DUMMYFUNCTION("""COMPUTED_VALUE"""),"Vancouver, BC") | K20: =IFERROR(__xludf.DUMMYFUNCTION("""COMPUTED_VALUE"""),2179139.43)
A21: Records Needing Check | B21: =COUNTIF(Cleaned_Data!AD2:AD22699,"CHECK") | D21: =IFERROR(__xludf.DUMMYFUNCTION("""COMPUTED_VALUE"""),2020) | E21: =IFERROR(__xludf.DUMMYFUNCTION("""COMPUTED_VALUE"""),5310597.3) | G21: =IFERROR(__xludf.DUMMYFUNCTION("""COMPUTED_VALUE"""),"Atlantic Canada Opportunities Agency | Agence de promotion économique du Canada atlantique") | H21: =IFERROR(__xludf.DUMMYFUNCTION("""COMPUTED_VALUE"""),4339524.80999999) | J21: =IFERROR(__xludf.DUMMYFUNCTION("""COMPUTED_VALUE"""),"Ottawa") | K21: =IFERROR(__xludf.DUMMYFUNCTION("""COMPUTED_VALUE"""),2076596.09999999)
A22: Possible Scale Issues | B22: =COUNTIF(Cleaned_Data!AE2:AE22699,"POSSIBLE_SCALE*") | D22: =IFERROR(__xludf.DUMMYFUNCTION("""COMPUTED_VALUE"""),2021) | E22: =IFERROR(__xludf.DUMMYFUNCTION("""COMPUTED_VALUE"""),4064375.22) | G22: =IFERROR(__xludf.DUMMYFUNCTION("""COMPUTED_VALUE"""),"Crown-Indigenous Relations and Northern Affairs Canada | Relations Couronne-Autochtones et Affaires du Nord Canada") | H22: =IFERROR(__xludf.DUMMYFUNCTION("""COMPUTED_VALUE"""),4031363.35000001) | J22: =IFERROR(__xludf.DUMMYFUNCTION("""COMPUTED_VALUE"""),"Vancouver, British Columbia") | K22: =IFERROR(__xludf.DUMMYFUNCTION("""COMPUTED_VALUE"""),1986704.38)
D23: =IFERROR(__xludf.DUMMYFUNCTION("""COMPUTED_VALUE"""),2022) | E23: =IFERROR(__xludf.DUMMYFUNCTION("""COMPUTED_VALUE"""),23148885.6199999) | G23: =IFERROR(__xludf.DUMMYFUNCTION("""COMPUTED_VALUE"""),"Royal Canadian Mounted Police | Gendarmerie royale du Canada") | H23: =IFERROR(__xludf.DUMMYFUNCTION("""COMPUTED_VALUE"""),3936661.7) | J23: =IFERROR(__xludf.DUMMYFUNCTION("""COMPUTED_VALUE"""),"Edmonton, Alberta, Canada") | K23: =IFERROR(__xludf.DUMMYFUNCTION("""COMPUTED_VALUE"""),1962846.41)
D24: =IFERROR(__xludf.DUMMYFUNCTION("""COMPUTED_VALUE"""),2023) | E24: =IFERROR(__xludf.DUMMYFUNCTION("""COMPUTED_VALUE"""),33126165.5) | G24: =IFERROR(__xludf.DUMMYFUNCTION("""COMPUTED_VALUE"""),"Public Sector Pension Investment Board | Office d’investissement des régimes de pensions du secteur public") | H24: =IFERROR(__xludf.DUMMYFUNCTION("""COMPUTED_VALUE"""),3594913.30999999) | J24: =IFERROR(__xludf.DUMMYFUNCTION("""COMPUTED_VALUE"""),"Toronto") | K24: =IFERROR(__xludf.DUMMYFUNCTION("""COMPUTED_VALUE"""),1938869.84999999)
D25: =IFERROR(__xludf.DUMMYFUNCTION("""COMPUTED_VALUE"""),2024) | E25: =IFERROR(__xludf.DUMMYFUNCTION("""COMPUTED_VALUE"""),36490649.42) | G25: =IFERROR(__xludf.DUMMYFUNCTION("""COMPUTED_VALUE"""),"Public Safety Canada | Sécurité publique Canada") | H25: =IFERROR(__xludf.DUMMYFUNCTION("""COMPUTED_VALUE"""),3297990.98999999) | J25: =IFERROR(__xludf.DUMMYFUNCTION("""COMPUTED_VALUE"""),"Beijing, China") | K25: =IFERROR(__xludf.DUMMYFUNCTION("""COMPUTED_VALUE"""),1691936.02)
D26: =IFERROR(__xludf.DUMMYFUNCTION("""COMPUTED_VALUE"""),2025) | E26: =IFERROR(__xludf.DUMMYFUNCTION("""COMPUTED_VALUE"""),35321861.4399998) | G26: =IFERROR(__xludf.DUMMYFUNCTION("""COMPUTED_VALUE"""),"Health Canada | Santé Canada") | H26: =IFERROR(__xludf.DUMMYFUNCTION("""COMPUTED_VALUE"""),3262570.93999999) | J26: =IFERROR(__xludf.DUMMYFUNCTION("""COMPUTED_VALUE"""),"Berlin, Germany") | K26: =IFERROR(__xludf.DUMMYFUNCTION("""COMPUTED_VALUE"""),1658434.39)
D27: =IFERROR(__xludf.DUMMYFUNCTION("""COMPUTED_VALUE"""),2026) | E27: =IFERROR(__xludf.DUMMYFUNCTION("""COMPUTED_VALUE"""),20337323.36) | G27: =IFERROR(__xludf.DUMMYFUNCTION("""COMPUTED_VALUE"""),"Correctional Service of Canada | Service correctionnel du Canada") | H27: =IFERROR(__xludf.DUMMYFUNCTION("""COMPUTED_VALUE"""),3078291.75000001) | J27: =IFERROR(__xludf.DUMMYFUNCTION("""COMPUTED_VALUE"""),"Washington, DC") | K27: =IFERROR(__xludf.DUMMYFUNCTION("""COMPUTED_VALUE"""),1488494.22)
G28: =IFERROR(__xludf.DUMMYFUNCTION("""COMPUTED_VALUE"""),"Department of Housing, Infrastructure and Communities | Ministère du Logement, de l’Infrastructure et des Collectivités") | H28: =IFERROR(__xludf.DUMMYFUNCTION("""COMPUTED_VALUE"""),2943821.02) | J28: =IFERROR(__xludf.DUMMYFUNCTION("""COMPUTED_VALUE"""),"London, England") | K28: =IFERROR(__xludf.DUMMYFUNCTION("""COMPUTED_VALUE"""),1379832.99)
G29: =IFERROR(__xludf.DUMMYFUNCTION("""COMPUTED_VALUE"""),"Department of Justice Canada | Ministère de la Justice Canada") | H29: =IFERROR(__xludf.DUMMYFUNCTION("""COMPUTED_VALUE"""),2434894.58999999) | J29: =IFERROR(__xludf.DUMMYFUNCTION("""COMPUTED_VALUE"""),"London, UK") | K29: =IFERROR(__xludf.DUMMYFUNCTION("""COMPUTED_VALUE"""),1354410.12)
G30: =IFERROR(__xludf.DUMMYFUNCTION("""COMPUTED_VALUE"""),"Indigenous Services Canada | Services aux Autochtones Canada") | H30: =IFERROR(__xludf.DUMMYFUNCTION("""COMPUTED_VALUE"""),2428640.96) | J30: =IFERROR(__xludf.DUMMYFUNCTION("""COMPUTED_VALUE"""),"Halifax, Nova Scotia") | K30: =IFERROR(__xludf.DUMMYFUNCTION("""COMPUTED_VALUE"""),1317554.2)
G31: =IFERROR(__xludf.DUMMYFUNCTION("""COMPUTED_VALUE"""),"Public Services and Procurement Canada | Services publics et Approvisionnement Canada") | H31: =IFERROR(__xludf.DUMMYFUNCTION("""COMPUTED_VALUE"""),2289529.21) | J31: =IFERROR(__xludf.DUMMYFUNCTION("""COMPUTED_VALUE"""),"Iqaluit, Nunavut, Canada") | K31: =IFERROR(__xludf.DUMMYFUNCTION("""COMPUTED_VALUE"""),1311936.63999999)
G32: =IFERROR(__xludf.DUMMYFUNCTION("""COMPUTED_VALUE"""),"Atomic Energy of Canada Limited | Énergie atomique du Canada, Limitée") | H32: =IFERROR(__xludf.DUMMYFUNCTION("""COMPUTED_VALUE"""),2203663.44999999) | J32: =IFERROR(__xludf.DUMMYFUNCTION("""COMPUTED_VALUE"""),"Washington, District of Columbia, United States") | K32: =IFERROR(__xludf.DUMMYFUNCTION("""COMPUTED_VALUE"""),1186346.98)
G33: =IFERROR(__xludf.DUMMYFUNCTION("""COMPUTED_VALUE"""),"Western Economic Diversification Canada | Diversification de l'économie de l'Ouest Canada") | H33: =IFERROR(__xludf.DUMMYFUNCTION("""COMPUTED_VALUE"""),2096963.64) | J33: =IFERROR(__xludf.DUMMYFUNCTION("""COMPUTED_VALUE"""),"Vienna, Austria") | K33: =IFERROR(__xludf.DUMMYFUNCTION("""COMPUTED_VALUE"""),1161377.72999999)
G34: =IFERROR(__xludf.DUMMYFUNCTION("""COMPUTED_VALUE"""),"Canadian Air Transport Security Authority | Administration canadienne de la sûreté du transport aérien") | H34: =IFERROR(__xludf.DUMMYFUNCTION("""COMPUTED_VALUE"""),2077643.63) | J34: =IFERROR(__xludf.DUMMYFUNCTION("""COMPUTED_VALUE"""),"Sydney, Australia") | K34: =IFERROR(__xludf.DUMMYFUNCTION("""COMPUTED_VALUE"""),1136684.57)
G35: =IFERROR(__xludf.DUMMYFUNCTION("""COMPUTED_VALUE"""),"Export Development Canada | Exportation et développement Canada") | H35: =IFERROR(__xludf.DUMMYFUNCTION("""COMPUTED_VALUE"""),2004276.67999999) | J35: =IFERROR(__xludf.DUMMYFUNCTION("""COMPUTED_VALUE"""),"New York, New York, United States") | K35: =IFERROR(__xludf.DUMMYFUNCTION("""COMPUTED_VALUE"""),1131588.94)
G36: =IFERROR(__xludf.DUMMYFUNCTION("""COMPUTED_VALUE"""),"Canadian Nuclear Safety Commission | Commission canadienne de sûreté nucléaire") | H36: =IFERROR(__xludf.DUMMYFUNCTION("""COMPUTED_VALUE"""),1973460.65) | J36: =IFERROR(__xludf.DUMMYFUNCTION("""COMPUTED_VALUE"""),"Gatineau, Quebec, Canada") | K36: =IFERROR(__xludf.DUMMYFUNCTION("""COMPUTED_VALUE"""),1127996.53999999)
G37: =IFERROR(__xludf.DUMMYFUNCTION("""COMPUTED_VALUE"""),"Treasury Board of Canada Secretariat | Secrétariat du Conseil du Trésor du Canada") | H37: =IFERROR(__xludf.DUMMYFUNCTION("""COMPUTED_VALUE"""),1918420.58999999) | J37: =IFERROR(__xludf.DUMMYFUNCTION("""COMPUTED_VALUE"""),"Vancouver") | K37: =IFERROR(__xludf.DUMMYFUNCTION("""COMPUTED_VALUE"""),1119550.02999999)
G38: =IFERROR(__xludf.DUMMYFUNCTION("""COMPUTED_VALUE"""),"Federal Economic Development Agency for Southern Ontario | Agence fédérale de développement économique pour le Sud de l'Ontario") | H38: =IFERROR(__xludf.DUMMYFUNCTION("""COMPUTED_VALUE"""),1895793.45) | J38: =IFERROR(__xludf.DUMMYFUNCTION("""COMPUTED_VALUE"""),"Charlottetown, Prince Edward Island, Canada") | K38: =IFERROR(__xludf.DUMMYFUNCTION("""COMPUTED_VALUE"""),1115488.27)
G39: =IFERROR(__xludf.DUMMYFUNCTION("""COMPUTED_VALUE"""),"Canada Economic Development for Quebec Regions | Développement économique Canada pour les régions du Québec") | H39: =IFERROR(__xludf.DUMMYFUNCTION("""COMPUTED_VALUE"""),1886311.4) | J39: =IFERROR(__xludf.DUMMYFUNCTION("""COMPUTED_VALUE"""),"Rome, Italy") | K39: =IFERROR(__xludf.DUMMYFUNCTION("""COMPUTED_VALUE"""),1111691.52)
G40: =IFERROR(__xludf.DUMMYFUNCTION("""COMPUTED_VALUE"""),"Canada Border Services Agency | Agence des services frontaliers du Canada") | H40: =IFERROR(__xludf.DUMMYFUNCTION("""COMPUTED_VALUE"""),1884681.02999999) | J40: =IFERROR(__xludf.DUMMYFUNCTION("""COMPUTED_VALUE"""),"St. John's, Newfoundland and Labrador, Canada") | K40: =IFERROR(__xludf.DUMMYFUNCTION("""COMPUTED_VALUE"""),1100126.92)
G41: =IFERROR(__xludf.DUMMYFUNCTION("""COMPUTED_VALUE"""),"Financial Transactions and Reports Analysis Centre of Canada | Centre d'analyse des opérations et déclarations financières du Canada") | H41: =IFERROR(__xludf.DUMMYFUNCTION("""COMPUTED_VALUE"""),1856871.52) | J41: =IFERROR(__xludf.DUMMYFUNCTION("""COMPUTED_VALUE"""),"Saskatoon, Saskatchewan, Canada") | K41: =IFERROR(__xludf.DUMMYFUNCTION("""COMPUTED_VALUE"""),1077465.32999999)
G42: =IFERROR(__xludf.DUMMYFUNCTION("""COMPUTED_VALUE"""),"Public Health Agency of Canada | Agence de la santé publique du Canada") | H42: =IFERROR(__xludf.DUMMYFUNCTION("""COMPUTED_VALUE"""),1777279.49999999) | J42: =IFERROR(__xludf.DUMMYFUNCTION("""COMPUTED_VALUE"""),"OTTAWA, ON") | K42: =IFERROR(__xludf.DUMMYFUNCTION("""COMPUTED_VALUE"""),1047319.82999999)
G43: =IFERROR(__xludf.DUMMYFUNCTION("""COMPUTED_VALUE"""),"Canadian Institutes of Health Research | Instituts de recherche en santé du Canada") | H43: =IFERROR(__xludf.DUMMYFUNCTION("""COMPUTED_VALUE"""),1736796.2) | J43: =IFERROR(__xludf.DUMMYFUNCTION("""COMPUTED_VALUE"""),"Montréal, Quebec, Canada") | K43: =IFERROR(__xludf.DUMMYFUNCTION("""COMPUTED_VALUE"""),1028895.57)
G44: =IFERROR(__xludf.DUMMYFUNCTION("""COMPUTED_VALUE"""),"Canada Energy Regulator | La Régie de l’énergie du Canada") | H44: =IFERROR(__xludf.DUMMYFUNCTION("""COMPUTED_VALUE"""),1386472.06) | J44: =IFERROR(__xludf.DUMMYFUNCTION("""COMPUTED_VALUE"""),"Ottawa (Ontario) Canada") | K44: =IFERROR(__xludf.DUMMYFUNCTION("""COMPUTED_VALUE"""),1004723.33)
G45: =IFERROR(__xludf.DUMMYFUNCTION("""COMPUTED_VALUE"""),"Office of the Superintendent of Financial Institutions Canada | Bureau du surintendant des institutions financières Canada") | H45: =IFERROR(__xludf.DUMMYFUNCTION("""COMPUTED_VALUE"""),1276013.75999999) | J45: =IFERROR(__xludf.DUMMYFUNCTION("""COMPUTED_VALUE"""),"Calgary, AB") | K45: =IFERROR(__xludf.DUMMYFUNCTION("""COMPUTED_VALUE"""),983173.26)
G46: =IFERROR(__xludf.DUMMYFUNCTION("""COMPUTED_VALUE"""),"Canada Mortgage and Housing Corporation | Société canadienne d'hypothèques et de logement") | H46: =IFERROR(__xludf.DUMMYFUNCTION("""COMPUTED_VALUE"""),1267319.70999999) | J46: =IFERROR(__xludf.DUMMYFUNCTION("""COMPUTED_VALUE"""),"Victoria, British Columbia, Canada") | K46: =IFERROR(__xludf.DUMMYFUNCTION("""COMPUTED_VALUE"""),917540.16)
G47: =IFERROR(__xludf.DUMMYFUNCTION("""COMPUTED_VALUE"""),"Canadian Food Inspection Agency | Agence canadienne d'inspection des aliments") | H47: =IFERROR(__xludf.DUMMYFUNCTION("""COMPUTED_VALUE"""),1252491.83999999) | J47: =IFERROR(__xludf.DUMMYFUNCTION("""COMPUTED_VALUE"""),"Washington") | K47: =IFERROR(__xludf.DUMMYFUNCTION("""COMPUTED_VALUE"""),906736.84)
G48: =IFERROR(__xludf.DUMMYFUNCTION("""COMPUTED_VALUE"""),"Financial Consumer Agency of Canada | Agence de la consommation en matière financière du Canada") | H48: =IFERROR(__xludf.DUMMYFUNCTION("""COMPUTED_VALUE"""),1158257.19999999) | J48: =IFERROR(__xludf.DUMMYFUNCTION("""COMPUTED_VALUE"""),"Montreal, Quebec") | K48: =IFERROR(__xludf.DUMMYFUNCTION("""COMPUTED_VALUE"""),858373.899999997)
G49: =IFERROR(__xludf.DUMMYFUNCTION("""COMPUTED_VALUE"""),"Women and Gender Equality Canada | Femmes et Égalité des genres Canada") | H49: =IFERROR(__xludf.DUMMYFUNCTION("""COMPUTED_VALUE"""),1136775.22999999) | J49: =IFERROR(__xludf.DUMMYFUNCTION("""COMPUTED_VALUE"""),"New York") | K49: =IFERROR(__xludf.DUMMYFUNCTION("""COMPUTED_VALUE"""),823546.03)
G50: =IFERROR(__xludf.DUMMYFUNCTION("""COMPUTED_VALUE"""),"Public Service Commission of Canada | Commission de la fonction publique du Canada") | H50: =IFERROR(__xludf.DUMMYFUNCTION("""COMPUTED_VALUE"""),1131901.96) | J50: =IFERROR(__xludf.DUMMYFUNCTION("""COMPUTED_VALUE"""),"Seoul, South Korea") | K50: =IFERROR(__xludf.DUMMYFUNCTION("""COMPUTED_VALUE"""),786436.26)
G51: =IFERROR(__xludf.DUMMYFUNCTION("""COMPUTED_VALUE"""),"Canadian Space Agency | Agence spatiale canadienne") | H51: =IFERROR(__xludf.DUMMYFUNCTION("""COMPUTED_VALUE"""),1121690.68999999) | J51: =IFERROR(__xludf.DUMMYFUNCTION("""COMPUTED_VALUE"""),"Mexico City, Mexico") | K51: =IFERROR(__xludf.DUMMYFUNCTION("""COMPUTED_VALUE"""),774623.2)
G52: =IFERROR(__xludf.DUMMYFUNCTION("""COMPUTED_VALUE"""),"Canadian Radio-television and Telecommunications Commission | Conseil de la radiodiffusion et des télécommunications canadiennes") | H52: =IFERROR(__xludf.DUMMYFUNCTION("""COMPUTED_VALUE"""),1120436.00999999) | J52: =IFERROR(__xludf.DUMMYFUNCTION("""COMPUTED_VALUE"""),"Quebec, Quebec, Canada") | K52: =IFERROR(__xludf.DUMMYFUNCTION("""COMPUTED_VALUE"""),761059.739999999)
G53: =IFERROR(__xludf.DUMMYFUNCTION("""COMPUTED_VALUE"""),"Statistics Canada | Statistique Canada") | H53: =IFERROR(__xludf.DUMMYFUNCTION("""COMPUTED_VALUE"""),1098604.81999999) | J53: =IFERROR(__xludf.DUMMYFUNCTION("""COMPUTED_VALUE"""),"Yellowknife, Northwest Territories, Canada") | K53: =IFERROR(__xludf.DUMMYFUNCTION("""COMPUTED_VALUE"""),750619.43)
G54: =IFERROR(__xludf.DUMMYFUNCTION("""COMPUTED_VALUE"""),"Invest in Canada | Investir Au Canada") | H54: =IFERROR(__xludf.DUMMYFUNCTION("""COMPUTED_VALUE"""),1095905.52999999) | J54: =IFERROR(__xludf.DUMMYFUNCTION("""COMPUTED_VALUE"""),"Whitehorse, Yukon, Canada") | K54: =IFERROR(__xludf.DUMMYFUNCTION("""COMPUTED_VALUE"""),747084.74)
G55: =IFERROR(__xludf.DUMMYFUNCTION("""COMPUTED_VALUE"""),"Farm Products Council of Canada | Conseil des produits agricoles du Canada") | H55: =IFERROR(__xludf.DUMMYFUNCTION("""COMPUTED_VALUE"""),1026602.34) | J55: =IFERROR(__xludf.DUMMYFUNCTION("""COMPUTED_VALUE"""),"Edmonton, Alberta") | K55: =IFERROR(__xludf.DUMMYFUNCTION("""COMPUTED_VALUE"""),741439.74)
G56: =IFERROR(__xludf.DUMMYFUNCTION("""COMPUTED_VALUE"""),"VIA HFR - VIA TGF Inc. | VIA HFR - VIA TGF Inc.") | H56: =IFERROR(__xludf.DUMMYFUNCTION("""COMPUTED_VALUE"""),1015203.92) | J56: =IFERROR(__xludf.DUMMYFUNCTION("""COMPUTED_VALUE"""),"Canberra, Australia") | K56: =IFERROR(__xludf.DUMMYFUNCTION("""COMPUTED_VALUE"""),733715.909999999)
G57: =IFERROR(__xludf.DUMMYFUNCTION("""COMPUTED_VALUE"""),"Canada Deposit Insurance Corporation | Société d'assurance-dépôts du Canada") | H57: =IFERROR(__xludf.DUMMYFUNCTION("""COMPUTED_VALUE"""),960913.82) | J57: =IFERROR(__xludf.DUMMYFUNCTION("""COMPUTED_VALUE"""),"Halifax, NS") | K57: =IFERROR(__xludf.DUMMYFUNCTION("""COMPUTED_VALUE"""),722683.89)
G58: =IFERROR(__xludf.DUMMYFUNCTION("""COMPUTED_VALUE"""),"Veterans Review and Appeal Board | Tribunal des anciens combattants (révision et appel)") | H58: =IFERROR(__xludf.DUMMYFUNCTION("""COMPUTED_VALUE"""),844987.11) | J58: =IFERROR(__xludf.DUMMYFUNCTION("""COMPUTED_VALUE"""),"Moncton, New Brunswick, Canada") | K58: =IFERROR(__xludf.DUMMYFUNCTION("""COMPUTED_VALUE"""),715744.139999999)
G59: =IFERROR(__xludf.DUMMYFUNCTION("""COMPUTED_VALUE"""),"Defence Construction Canada | Construction de Défense Canada") | H59: =IFERROR(__xludf.DUMMYFUNCTION("""COMPUTED_VALUE"""),831971.849999999) | J59: =IFERROR(__xludf.DUMMYFUNCTION("""COMPUTED_VALUE"""),"Calgary, Alberta") | K59: =IFERROR(__xludf.DUMMYFUNCTION("""COMPUTED_VALUE"""),698834.750000001)
G60: =IFERROR(__xludf.DUMMYFUNCTION("""COMPUTED_VALUE"""),"Canadian Human Rights Commission | Commission canadienne des droits de la personne") | H60: =IFERROR(__xludf.DUMMYFUNCTION("""COMPUTED_VALUE"""),813698.54) | J60: =IFERROR(__xludf.DUMMYFUNCTION("""COMPUTED_VALUE"""),"Singapore, Singapore") | K60: =IFERROR(__xludf.DUMMYFUNCTION("""COMPUTED_VALUE"""),691302.48)
G61: =IFERROR(__xludf.DUMMYFUNCTION("""COMPUTED_VALUE"""),"Social Sciences and Humanities Research Council of Canada | Conseil de recherches en sciences humaines du Canada") | H61: =IFERROR(__xludf.DUMMYFUNCTION("""COMPUTED_VALUE"""),813573.57) | J61: =IFERROR(__xludf.DUMMYFUNCTION("""COMPUTED_VALUE"""),"Paris") | K61: =IFERROR(__xludf.DUMMYFUNCTION("""COMPUTED_VALUE"""),675150.38)
G62: =IFERROR(__xludf.DUMMYFUNCTION("""COMPUTED_VALUE"""),"Standards Council of Canada | Conseil canadien des normes") | H62: =IFERROR(__xludf.DUMMYFUNCTION("""COMPUTED_VALUE"""),807731.009999999) | J62: =IFERROR(__xludf.DUMMYFUNCTION("""COMPUTED_VALUE"""),"Moncton, New Brunswick") | K62: =IFERROR(__xludf.DUMMYFUNCTION("""COMPUTED_VALUE"""),666057.62)
G63: =IFERROR(__xludf.DUMMYFUNCTION("""COMPUTED_VALUE"""),"Office of the Auditor General of Canada | Bureau du vérificateur général du Canada") | H63: =IFERROR(__xludf.DUMMYFUNCTION("""COMPUTED_VALUE"""),783631.44) | J63: =IFERROR(__xludf.DUMMYFUNCTION("""COMPUTED_VALUE"""),"Dubai, United Arab Emirates") | K63: =IFERROR(__xludf.DUMMYFUNCTION("""COMPUTED_VALUE"""),665320.04)
G64: =IFERROR(__xludf.DUMMYFUNCTION("""COMPUTED_VALUE"""),"Canadian Grain Commission | Commission canadienne des grains") | H64: =IFERROR(__xludf.DUMMYFUNCTION("""COMPUTED_VALUE"""),765899.83) | J64: =IFERROR(__xludf.DUMMYFUNCTION("""COMPUTED_VALUE"""),"Edmonton, AB") | K64: =IFERROR(__xludf.DUMMYFUNCTION("""COMPUTED_VALUE"""),663024.41)
G65: =IFERROR(__xludf.DUMMYFUNCTION("""COMPUTED_VALUE"""),"Administrative Tribunals Support Service of Canada | Service canadien d'appui aux tribunaux administratifs") | H65: =IFERROR(__xludf.DUMMYFUNCTION("""COMPUTED_VALUE"""),764636.999999999) | J65: =IFERROR(__xludf.DUMMYFUNCTION("""COMPUTED_VALUE"""),"Singapore") | K65: =IFERROR(__xludf.DUMMYFUNCTION("""COMPUTED_VALUE"""),625231.559999999)
G66: =IFERROR(__xludf.DUMMYFUNCTION("""COMPUTED_VALUE"""),"Prairies Economic Development Canada | Développement économique Canada pour les Prairies") | H66: =IFERROR(__xludf.DUMMYFUNCTION("""COMPUTED_VALUE"""),744459.16) | J66: =IFERROR(__xludf.DUMMYFUNCTION("""COMPUTED_VALUE"""),"Ottawa, Canada") | K66: =IFERROR(__xludf.DUMMYFUNCTION("""COMPUTED_VALUE"""),622261.979999999)
G67: =IFERROR(__xludf.DUMMYFUNCTION("""COMPUTED_VALUE"""),"Canada Foundation for Innovation | Fondation canadienne pour l’innovation") | H67: =IFERROR(__xludf.DUMMYFUNCTION("""COMPUTED_VALUE"""),739258.709999999) | J67: =IFERROR(__xludf.DUMMYFUNCTION("""COMPUTED_VALUE"""),"Winnipeg, Manitoba") | K67: =IFERROR(__xludf.DUMMYFUNCTION("""COMPUTED_VALUE"""),602993.07)
G68: =IFERROR(__xludf.DUMMYFUNCTION("""COMPUTED_VALUE"""),"Parole Board of Canada | Commission des libérations conditionnelles du Canada") | H68: =IFERROR(__xludf.DUMMYFUNCTION("""COMPUTED_VALUE"""),727288.96) | J68: =IFERROR(__xludf.DUMMYFUNCTION("""COMPUTED_VALUE"""),"London, England, United Kingdom") | K68: =IFERROR(__xludf.DUMMYFUNCTION("""COMPUTED_VALUE"""),576690.679999999)
G69: =IFERROR(__xludf.DUMMYFUNCTION("""COMPUTED_VALUE"""),"Shared Services Canada | Services partagés Canada") | H69: =IFERROR(__xludf.DUMMYFUNCTION("""COMPUTED_VALUE"""),709825.94) | J69: =IFERROR(__xludf.DUMMYFUNCTION("""COMPUTED_VALUE"""),"New York, United States") | K69: =IFERROR(__xludf.DUMMYFUNCTION("""COMPUTED_VALUE"""),561383.899999999)
G70: =IFERROR(__xludf.DUMMYFUNCTION("""COMPUTED_VALUE"""),"National Film Board | Office national du film") | H70: =IFERROR(__xludf.DUMMYFUNCTION("""COMPUTED_VALUE"""),697668.21) | J70: =IFERROR(__xludf.DUMMYFUNCTION("""COMPUTED_VALUE"""),"Ottawa, ON, Canada") | K70: =IFERROR(__xludf.DUMMYFUNCTION("""COMPUTED_VALUE"""),543382.45)
G71: =IFERROR(__xludf.DUMMYFUNCTION("""COMPUTED_VALUE"""),"National Capital Commission | Commission de la capitale nationale") | H71: =IFERROR(__xludf.DUMMYFUNCTION("""COMPUTED_VALUE"""),684832.65) | J71: =IFERROR(__xludf.DUMMYFUNCTION("""COMPUTED_VALUE"""),"Winnipeg, MB") | K71: =IFERROR(__xludf.DUMMYFUNCTION("""COMPUTED_VALUE"""),543227.61)
G72: =IFERROR(__xludf.DUMMYFUNCTION("""COMPUTED_VALUE"""),"Natural Sciences and Engineering Research Council of Canada | Conseil de recherches en sciences naturelles et en génie du Canada") | H72: =IFERROR(__xludf.DUMMYFUNCTION("""COMPUTED_VALUE"""),681679.08) | J72: =IFERROR(__xludf.DUMMYFUNCTION("""COMPUTED_VALUE"""),"Stockholm, Sweden") | K72: =IFERROR(__xludf.DUMMYFUNCTION("""COMPUTED_VALUE"""),541216.919999999)
G73: =IFERROR(__xludf.DUMMYFUNCTION("""COMPUTED_VALUE"""),"International Joint Commission | Commission mixte internationale") | H73: =IFERROR(__xludf.DUMMYFUNCTION("""COMPUTED_VALUE"""),639541.98) | J73: =IFERROR(__xludf.DUMMYFUNCTION("""COMPUTED_VALUE"""),"Quebec City, Quebec, Canada") | K73: =IFERROR(__xludf.DUMMYFUNCTION("""COMPUTED_VALUE"""),534647.3)
G74: =IFERROR(__xludf.DUMMYFUNCTION("""COMPUTED_VALUE"""),"Polar Knowledge Canada | Savoir polaire Canada") | H74: =IFERROR(__xludf.DUMMYFUNCTION("""COMPUTED_VALUE"""),635907.79) | J74: =IFERROR(__xludf.DUMMYFUNCTION("""COMPUTED_VALUE"""),"Ontario") | K74: =IFERROR(__xludf.DUMMYFUNCTION("""COMPUTED_VALUE"""),532163.35)
G75: =IFERROR(__xludf.DUMMYFUNCTION("""COMPUTED_VALUE"""),"College of Immigration and Citizenship Consultants | Collège des Consultants en Immigration et en Citoyenneté") | H75: =IFERROR(__xludf.DUMMYFUNCTION("""COMPUTED_VALUE"""),628241.14) | J75: =IFERROR(__xludf.DUMMYFUNCTION("""COMPUTED_VALUE"""),"Washington, United States") | K75: =IFERROR(__xludf.DUMMYFUNCTION("""COMPUTED_VALUE"""),529910.25)
G76: =IFERROR(__xludf.DUMMYFUNCTION("""COMPUTED_VALUE"""),"Telefilm Canada | Téléfilm Canada") | H76: =IFERROR(__xludf.DUMMYFUNCTION("""COMPUTED_VALUE"""),615046.41) | J76: =IFERROR(__xludf.DUMMYFUNCTION("""COMPUTED_VALUE"""),"Banff, Alberta, Canada") | K76: =IFERROR(__xludf.DUMMYFUNCTION("""COMPUTED_VALUE"""),509022.36)
G77: =IFERROR(__xludf.DUMMYFUNCTION("""COMPUTED_VALUE"""),"Office of the Privacy Commissioner of Canada | Commissariat à la protection de la vie privée du Canada") | H77: =IFERROR(__xludf.DUMMYFUNCTION("""COMPUTED_VALUE"""),587677.45) | J77: =IFERROR(__xludf.DUMMYFUNCTION("""COMPUTED_VALUE"""),"Montreal") | K77: =IFERROR(__xludf.DUMMYFUNCTION("""COMPUTED_VALUE"""),502576.569999999)
G78: =IFERROR(__xludf.DUMMYFUNCTION("""COMPUTED_VALUE"""),"Prince Rupert Port Authority | L’Administration portuaire de Prince Rupert") | H78: =IFERROR(__xludf.DUMMYFUNCTION("""COMPUTED_VALUE"""),585769.219999999) | J78: =IFERROR(__xludf.DUMMYFUNCTION("""COMPUTED_VALUE"""),"Riga, Latvia") | K78: =IFERROR(__xludf.DUMMYFUNCTION("""COMPUTED_VALUE"""),496457.969999999)
G79: =IFERROR(__xludf.DUMMYFUNCTION("""COMPUTED_VALUE"""),"Impact Assessment Agency of Canada | Agence d'évaluation d'impact du Canada") | H79: =IFERROR(__xludf.DUMMYFUNCTION("""COMPUTED_VALUE"""),523225.73) | J79: =IFERROR(__xludf.DUMMYFUNCTION("""COMPUTED_VALUE"""),"Montreal, QC") | K79: =IFERROR(__xludf.DUMMYFUNCTION("""COMPUTED_VALUE"""),493802.25)
G80: =IFERROR(__xludf.DUMMYFUNCTION("""COMPUTED_VALUE"""),"Public Prosecution Service of Canada | Service des poursuites pénales du Canada") | H80: =IFERROR(__xludf.DUMMYFUNCTION("""COMPUTED_VALUE"""),486743.279999999) | J80: =IFERROR(__xludf.DUMMYFUNCTION("""COMPUTED_VALUE"""),"Fredericton, New Brunswick, Canada") | K80: =IFERROR(__xludf.DUMMYFUNCTION("""COMPUTED_VALUE"""),478483.2)
G81: =IFERROR(__xludf.DUMMYFUNCTION("""COMPUTED_VALUE"""),"Canada Infrastructure Bank | La Banque de l’infrastructure du Canada") | H81: =IFERROR(__xludf.DUMMYFUNCTION("""COMPUTED_VALUE"""),483054) | J81: =IFERROR(__xludf.DUMMYFUNCTION("""COMPUTED_VALUE"""),"Québec, Quebec, Canada") | K81: =IFERROR(__xludf.DUMMYFUNCTION("""COMPUTED_VALUE"""),477799.78)
G82: =IFERROR(__xludf.DUMMYFUNCTION("""COMPUTED_VALUE"""),"Courts Administration Service | Service administratif des tribunaux judiciaires") | H82: =IFERROR(__xludf.DUMMYFUNCTION("""COMPUTED_VALUE"""),478299.67) | J82: =IFERROR(__xludf.DUMMYFUNCTION("""COMPUTED_VALUE"""),"Brussels") | K82: =IFERROR(__xludf.DUMMYFUNCTION("""COMPUTED_VALUE"""),468217.81)
G83: =IFERROR(__xludf.DUMMYFUNCTION("""COMPUTED_VALUE"""),"Pacific Economic Development Canada | Développement économique Canada pour le Pacifique") | H83: =IFERROR(__xludf.DUMMYFUNCTION("""COMPUTED_VALUE"""),476062.94) | J83: =IFERROR(__xludf.DUMMYFUNCTION("""COMPUTED_VALUE"""),"London") | K83: =IFERROR(__xludf.DUMMYFUNCTION("""COMPUTED_VALUE"""),464609.11)
G84: =IFERROR(__xludf.DUMMYFUNCTION("""COMPUTED_VALUE"""),"Royal Canadian Mint | Monnaie royale canadienne") | H84: =IFERROR(__xludf.DUMMYFUNCTION("""COMPUTED_VALUE"""),475621.99) | J84: =IFERROR(__xludf.DUMMYFUNCTION("""COMPUTED_VALUE"""),"Buenos Aires, Argentina") | K84: =IFERROR(__xludf.DUMMYFUNCTION("""COMPUTED_VALUE"""),460590.43)
G85: =IFERROR(__xludf.DUMMYFUNCTION("""COMPUTED_VALUE"""),"VIA Rail Canada Inc. | VIA Rail Canada Inc.") | H85: =IFERROR(__xludf.DUMMYFUNCTION("""COMPUTED_VALUE"""),469287.05) | J85: =IFERROR(__xludf.DUMMYFUNCTION("""COMPUTED_VALUE"""),"Davos, Switzerland") | K85: =IFERROR(__xludf.DUMMYFUNCTION("""COMPUTED_VALUE"""),459172.949999999)
G86: =IFERROR(__xludf.DUMMYFUNCTION("""COMPUTED_VALUE"""),"Canada School of Public Service | École de la fonction publique du Canada") | H86: =IFERROR(__xludf.DUMMYFUNCTION("""COMPUTED_VALUE"""),463606.48) | J86: =IFERROR(__xludf.DUMMYFUNCTION("""COMPUTED_VALUE"""),"Santiago, Chile") | K86: =IFERROR(__xludf.DUMMYFUNCTION("""COMPUTED_VALUE"""),456116.25)
G87: =IFERROR(__xludf.DUMMYFUNCTION("""COMPUTED_VALUE"""),"National Gallery of Canada | Musée des beaux-arts du Canada") | H87: =IFERROR(__xludf.DUMMYFUNCTION("""COMPUTED_VALUE"""),461638.43) | J87: =IFERROR(__xludf.DUMMYFUNCTION("""COMPUTED_VALUE"""),"Regina, Saskatchewan") | K87: =IFERROR(__xludf.DUMMYFUNCTION("""COMPUTED_VALUE"""),454700.92)
G88: =IFERROR(__xludf.DUMMYFUNCTION("""COMPUTED_VALUE"""),"Office of the Administrator of the Ship-source Oil Pollution Fund; (operating under the name) Ship and Rail Compensation Canada | Bureau de l’administrateur de la Caisse d’indemnisation des dommages dus à la pollution par les hydrocarbures causée par les "&"navires; (qui mène ses activités sous le nom de) Indemnisation Navire et Rail Canada") | H88: =IFERROR(__xludf.DUMMYFUNCTION("""COMPUTED_VALUE"""),458595.099999999) | J88: =IFERROR(__xludf.DUMMYFUNCTION("""COMPUTED_VALUE"""),"London, Ontario, Canada") | K88: =IFERROR(__xludf.DUMMYFUNCTION("""COMPUTED_VALUE"""),445162.69)
G89: =IFERROR(__xludf.DUMMYFUNCTION("""COMPUTED_VALUE"""),"Quebec Port Authority | Administration portuaire de Québec") | H89: =IFERROR(__xludf.DUMMYFUNCTION("""COMPUTED_VALUE"""),440291.31) | J89: =IFERROR(__xludf.DUMMYFUNCTION("""COMPUTED_VALUE"""),"Cape Town, South Africa") | K89: =IFERROR(__xludf.DUMMYFUNCTION("""COMPUTED_VALUE"""),441271.25)
G90: =IFERROR(__xludf.DUMMYFUNCTION("""COMPUTED_VALUE"""),"Canadian Museum of History | Musée canadien de l'histoire") | H90: =IFERROR(__xludf.DUMMYFUNCTION("""COMPUTED_VALUE"""),393754.169999999) | J90: =IFERROR(__xludf.DUMMYFUNCTION("""COMPUTED_VALUE"""),"Manila, Philippines") | K90: =IFERROR(__xludf.DUMMYFUNCTION("""COMPUTED_VALUE"""),437348.389999999)
G91: =IFERROR(__xludf.DUMMYFUNCTION("""COMPUTED_VALUE"""),"Canada Council for the Arts | Conseil des arts du Canada") | H91: =IFERROR(__xludf.DUMMYFUNCTION("""COMPUTED_VALUE"""),391736.099999999) | J91: =IFERROR(__xludf.DUMMYFUNCTION("""COMPUTED_VALUE"""),"Bali, Indonesia") | K91: =IFERROR(__xludf.DUMMYFUNCTION("""COMPUTED_VALUE"""),428019.65)
G92: =IFERROR(__xludf.DUMMYFUNCTION("""COMPUTED_VALUE"""),"Accessibility Standards Canada | Normes d’accessibilité Canada") | H92: =IFERROR(__xludf.DUMMYFUNCTION("""COMPUTED_VALUE"""),386061.14) | J92: =IFERROR(__xludf.DUMMYFUNCTION("""COMPUTED_VALUE"""),"Warsaw, Poland") | K92: =IFERROR(__xludf.DUMMYFUNCTION("""COMPUTED_VALUE"""),422924.59)
G93: =IFERROR(__xludf.DUMMYFUNCTION("""COMPUTED_VALUE"""),"Library and Archives Canada | Bibliothèque et Archives Canada") | H93: =IFERROR(__xludf.DUMMYFUNCTION("""COMPUTED_VALUE"""),378182.3) | J93: =IFERROR(__xludf.DUMMYFUNCTION("""COMPUTED_VALUE"""),"Saskatoon, Saskatchewan") | K93: =IFERROR(__xludf.DUMMYFUNCTION("""COMPUTED_VALUE"""),421505.389999999)
G94: =IFERROR(__xludf.DUMMYFUNCTION("""COMPUTED_VALUE"""),"Immigration and Refugee Board of Canada | Commission de l'immigration et du statut de réfugié du Canada") | H94: =IFERROR(__xludf.DUMMYFUNCTION("""COMPUTED_VALUE"""),373356.299999999) | J94: =IFERROR(__xludf.DUMMYFUNCTION("""COMPUTED_VALUE"""),"Washington, DC, USA") | K94: =IFERROR(__xludf.DUMMYFUNCTION("""COMPUTED_VALUE"""),416665.589999999)
G95: =IFERROR(__xludf.DUMMYFUNCTION("""COMPUTED_VALUE"""),"Canadian Northern Economic Development Agency | Agence canadienne de développement économique du Nord") | H95: =IFERROR(__xludf.DUMMYFUNCTION("""COMPUTED_VALUE"""),364686.74) | J95: =IFERROR(__xludf.DUMMYFUNCTION("""COMPUTED_VALUE"""),"Gatineau, Quebec") | K95: =IFERROR(__xludf.DUMMYFUNCTION("""COMPUTED_VALUE"""),411149.889999999)
G96: =IFERROR(__xludf.DUMMYFUNCTION("""COMPUTED_VALUE"""),"Status of Women Canada | Condition féminine Canada") | H96: =IFERROR(__xludf.DUMMYFUNCTION("""COMPUTED_VALUE"""),346948.599999999) | J96: =IFERROR(__xludf.DUMMYFUNCTION("""COMPUTED_VALUE"""),"Washington, D.C., United States") | K96: =IFERROR(__xludf.DUMMYFUNCTION("""COMPUTED_VALUE"""),395160.039999999)
G97: =IFERROR(__xludf.DUMMYFUNCTION("""COMPUTED_VALUE"""),"Transportation Safety Board of Canada | Bureau de la sécurité des transports du Canada") | H97: =IFERROR(__xludf.DUMMYFUNCTION("""COMPUTED_VALUE"""),333468.32) | J97: =IFERROR(__xludf.DUMMYFUNCTION("""COMPUTED_VALUE"""),"Oslo, Norway") | K97: =IFERROR(__xludf.DUMMYFUNCTION("""COMPUTED_VALUE"""),388842.37)
G98: =IFERROR(__xludf.DUMMYFUNCTION("""COMPUTED_VALUE"""),"Office of the Veterans Ombudsman | Bureau de l'ombudsman des vétérans") | H98: =IFERROR(__xludf.DUMMYFUNCTION("""COMPUTED_VALUE"""),328986.83) | J98: =IFERROR(__xludf.DUMMYFUNCTION("""COMPUTED_VALUE"""),"Munich, Germany") | K98: =IFERROR(__xludf.DUMMYFUNCTION("""COMPUTED_VALUE"""),382711.54)
G99: =IFERROR(__xludf.DUMMYFUNCTION("""COMPUTED_VALUE"""),"Secretariat of the National Security and Intelligence Committee of Parliamentarians | Secrétariat du Comité des parlementaires sur la sécurité nationale et le renseignement") | H99: =IFERROR(__xludf.DUMMYFUNCTION("""COMPUTED_VALUE"""),323444.809999999) | J99: =IFERROR(__xludf.DUMMYFUNCTION("""COMPUTED_VALUE"""),"Frankfurt, Germany") | K99: =IFERROR(__xludf.DUMMYFUNCTION("""COMPUTED_VALUE"""),380548.679999999)
G100: =IFERROR(__xludf.DUMMYFUNCTION("""COMPUTED_VALUE"""),"Development Finance Institution - FinDev Canada | Institution de financement du développement - FinDev Canada") | H100: =IFERROR(__xludf.DUMMYFUNCTION("""COMPUTED_VALUE"""),302207.589999999) | J100: =IFERROR(__xludf.DUMMYFUNCTION("""COMPUTED_VALUE"""),"Delhi, India") | K100: =IFERROR(__xludf.DUMMYFUNCTION("""COMPUTED_VALUE"""),367602.86)
...

Sheet Dashboard
E1: Travel Expense Analytics Dashboard
A2: KPI | B2: Value
A3: Total Travel Records | B3: =Analysis!B2
A4: Total Travel Expense | B4: =Analysis!B3
A5: Average Travel Expense | B5: =Analysis!B4
A6: Maximum Travel Expense | B6: =Analysis!B5
A7: Average Travel Days | B7: =Analysis!B13
A50: Recommendations Focus on airfare cost optimization through advance booking and travel policy controls. Monitor high-spending destinations such as Toronto and Ottawa. Review departments with unusually high travel expenses. Improve data completeness, especially for Other Expenses and Airfare. Investigate the records flagged for data-quality and scale issues before making final budget decisions.

Sheet README
A1: GitHub Portfolio Version
A2: Raw_Data and Cleaned_Data contain a 5,000-row sample to keep the workbook lightweight.
A3: The original full workbook remains unchanged on the user's computer.
A4: Summary, Analysis, and Dashboard sheets are retained for portfolio demonstration.
